Workbook

Sheet ПРАЙС_ЛИСТ
B2: МОДЕЛЬ | C2: КОД УСЛУГИ | D2: ГАРАНТИЯ, дн. | E2: УСЛУГА | F2: РОЗНИЧНАЯ ЦЕНА | G2: ДИАПОЗОН ЦЕНЫ
B3: iPhone | E3: Данные - резервная копия / перенос (1 - 128 ГБ) | *цена за фактический объем данных | F3: ='МАТРИЦА_СТОИМОСТИ_РАБОТ'!C5 -> 1600 | I3: 1000 - цена "от" | *требуется диагностика
E4: Данные - резервная копия / перенос (128 - 256 ГБ) | *цена за фактический объем данных | F4: ='МАТРИЦА_СТОИМОСТИ_РАБОТ'!C6 -> 2200 | I4: 1000 - фиксированная цена
E5: Данные - резервная копия / перенос (256 - 512 ГБ) | *цена за фактический объем данных | F5: ='МАТРИЦА_СТОИМОСТИ_РАБОТ'!C7 -> 4100 | I5: 1000 - цена "за работу" - уточнить запчасть .. стоимость .. наличие .. доступность заказа!
E6: Данные - резервная копия / перенос (512 ГБ - 1 ТБ) | *цена за фактический объем данных | F6: ='МАТРИЦА_СТОИМОСТИ_РАБОТ'!C8 -> 5100 | I6: есть дорогой закуп запчасти - предложить "вилку" из наличия / под заказ
E7: Данные - резервная копия / перенос (1 - 2 ТБ) | *цена за фактический объем данных | F7: ='МАТРИЦА_СТОИМОСТИ_РАБОТ'!C9 -> ?
E8: Приложения - установка | *цена за 1шт. | F8: ='МАТРИЦА_СТОИМОСТИ_РАБОТ'!C10 -> 500
E9: Прошивка / программные работы - БЕЗ РЕЗЕРВНОЙ копии | F9: ='МАТРИЦА_СТОИМОСТИ_РАБОТ'!C11 -> 1100
E10: Диагностика (без пайки компонентов) | F10: ='МАТРИЦА_СТОИМОСТИ_РАБОТ'!C17 -> 0
E11: Диагностика - составление и печать акта | F11: ='МАТРИЦА_СТОИМОСТИ_РАБОТ'!C18 -> 1000 | J11: МИН. ЦЕНА УСЛУГИ | K11: {={ "НАША ЦЕНА" ; IF(ROW(F12:F55), "", ); IF(F56:F1487="", "", F56:F1487) }} -> НАША ЦЕНА | L11: РЕМОНТ ЯБЛОК
B13: iPhone ШАБЛОН | D13: 0 | E13: Диагностика (с пайкой компонентов) | *бесплатно при дальнейшем ремонте | F13: -
B14: iPhone ШАБЛОН | D14: 0 | E14: Пылевлагозащита - восстановление | F14: -
B15: iPhone ШАБЛОН | D15: 0 | E15: Чистка сеток динамиков и разъема зарядки БЕЗ РАЗБОРА | F15: - | G15: =MIN(F15:F16) & " - " & MAX(F15:F16) -> 0 - 0
B16: iPhone ШАБЛОН | D16: 0 | E16: Чистка сеток динамиков и разъема зарядки С РАЗБОРОМ | F16: -
B17: iPhone ШАБЛОН | D17: 180 | E17: Аккумулятор - замена на СЕРВИСНЫЙ ОРИГИНАЛ (подлинное) | F17: - | G17: =MIN(F17:F22) & " - " & MAX(F17:F22) -> 0 - 0
B18: iPhone ШАБЛОН | D18: 180 | E18: Аккумулятор - замена на СНЯТЫЙ ОРИГИНАЛ (бу) | F18: -
B19: iPhone ШАБЛОН | D19: 180 | E19: Аккумулятор - замена на АНАЛОГ | F19: -
B20: iPhone ШАБЛОН | D20: 180 | E20: Аккумулятор - замена на АНАЛОГ (подлинное) | F20: -
B21: iPhone ШАБЛОН | D21: 180 | E21: Аккумулятор - замена на АНАЛОГ (бу) | F21: -
B22: iPhone ШАБЛОН | D22: 180 | E22: Аккумулятор - замена на АНАЛОГ (неизвестная деталь) | F22: -
B23: iPhone ШАБЛОН | D23: 180 | E23: Аккумулятор - замена с устранением уведомления | *цена под ключ | F23: -
B24: iPhone ШАБЛОН | D24: 90 | E24: Разъем зарядки - замена | F24: -
B25: iPhone ШАБЛОН | D25: 90 | E25: Дисплей - замена на СЕРВИСНЫЙ ОРИГИНАЛ (подлинное) | F25: - | G25: =MIN(F25:F34) & " - " & MAX(F25:F34) -> 0 - 0
B26: iPhone ШАБЛОН | D26: 90 | E26: Дисплей - замена на СНЯТЫЙ ОРИГИНАЛ | F26: -
B27: iPhone ШАБЛОН | D27: 90 | E27: Дисплей - замена на СНЯТЫЙ ОРИГИНАЛ (бу) | F27: -
B28: iPhone ШАБЛОН | D28: 90 | E28: Дисплей - замена на СНЯТЫЙ ОРИГИНАЛ (неизвестная деталь) | F28: -
B29: iPhone ШАБЛОН | D29: 90 | E29: Дисплей - замена на ВОССТАНОВЛЕННЫЙ ОРИГИНАЛ | F29: -
B30: iPhone ШАБЛОН | D30: 90 | E30: Дисплей - замена на ВОССТАНОВЛЕННЫЙ ОРИГИНАЛ (бу) | F30: -
B31: iPhone ШАБЛОН | D31: 90 | E31: Дисплей - замена на ВОССТАНОВЛЕННЫЙ ОРИГИНАЛ (неизвестная деталь) | F31: -
B32: iPhone ШАБЛОН | D32: 90 | E32: Дисплей - замена на АНАЛОГ | F32: -
B33: iPhone ШАБЛОН | D33: 90 | E33: Дисплей - замена на АНАЛОГ (бу) | F33: -
B34: iPhone ШАБЛОН | D34: 90 | E34: Дисплей - замена на АНАЛОГ (неизвестная деталь) | F34: -
B35: iPhone ШАБЛОН | D35: 90 | E35: Дисплей - устранение уведомления о замене | F35: -
B36: iPhone ШАБЛОН | D36: 90 | E36: Дисплей - замена (переклей) разбитого стекла | F36: - | G36: =MIN(F36:F37) & " - " & MAX(F36:F37) -> 0 - 0
B37: iPhone ШАБЛОН | D37: 90 | E37: Дисплей - замена (переклей) разбитого стекла с тачскрином | F37: -
B38: iPhone ШАБЛОН | D38: 90 | E38: Камера основная - замена | F38: -
B39: iPhone ШАБЛОН | D39: 90 | E39: Камера фронтальная - замена | F39: -
B40: iPhone ШАБЛОН | D40: 180 | E40: Камера - замена разбитого стекла | *цена за 1шт. | F40: -
B41: iPhone ШАБЛОН | D41: 90 | E41: Face ID - восстановление | *цена от, требуется диагностика | F41: -
B42: iPhone ШАБЛОН | D42: 180 | E42: Крышка (заднее стекло) - замена на СНЯТЫЙ ОРИГИНАЛ | F42: - | G42: =MIN(F42:F43) & " - " & MAX(F42:F43) -> 0 - 0
B43: iPhone ШАБЛОН | D43: 180 | E43: Крышка (заднее стекло) - замена на АНАЛОГ | F43: -
B44: iPhone ШАБЛОН | D44: 180 | E44: Корпус - замена | F44: -
B45: iPhone ШАБЛОН | D45: 180 | E45: Корпус (средняя часть) - замена | F45: -
B46: iPhone ШАБЛОН | D46: 90 | E46: Кнопка HOME - восстановление / замена | F46: -
B47: iPhone ШАБЛОН | D47: 90 | E47: Кнопки - восстановление / замена | *цена от, требуется диагностика | F47: -
B48: iPhone ШАБЛОН | D48: 90 | E48: Динамик полифонический (нижний, громкая связь) - замена | F48: -
B49: iPhone ШАБЛОН | D49: 90 | E49: Динамик разговорный (верхний, слуховой) - замена | F49: -
B50: iPhone ШАБЛОН | D50: 90 | E50: Микрофон - замена (один из..) | *требуется диагностика | F50: -
B51: iPhone ШАБЛОН | D51: 90 | E51: Ремонт платы - восстановление / замена | *цена от, требуется диагностика | F51: -
B52: iPhone ШАБЛОН | D52: 90 | E52: Профилактика после воды - восстановление | *цена от, требуется диагностика | F52: -
B53: iPhone ШАБЛОН | D53: 90 | E53: Модем - восстановление GSM сети | *цена от, требуется диагностика | F53: -
B54: iPhone ШАБЛОН | D54: 90 | E54: WiFi / Bluetooth - восстановление беспроводных сетей | *цена от, требуется диагностика | F54: -
B56: iPhone 5 | D56: 0 | E56: Диагностика (с пайкой компонентов) | *бесплатно при дальнейшем ремонте | F56: ='БД_УСЛУГИ_РО'!P56 -> 1 | K56: 1
B57: iPhone 5 | D57: 0 | E57: Чистка сеток динамиков и разъема зарядки БЕЗ РАЗБОРА | F57: ='БД_УСЛУГИ_РО'!P57 -> 400 | G57: =MIN(F57:F58) & " - " & MAX(F57:F58) -> 400 - 900 | K57: 400
B58: iPhone 5 | D58: 0 | E58: Чистка сеток динамиков и разъема зарядки С РАЗБОРОМ | F58: ='БД_УСЛУГИ_РО'!P58 -> 900 | K58: 900
B59: iPhone 5 | D59: 180 | E59: Аккумулятор - замена на АНАЛОГ | F59: ='БД_УСЛУГИ_РО'!P59+'БД_ЗАПЧАСТИ'!P5 -> 1200 | H59: ='БД_УСЛУГИ_РО'!P59 -> 700 | J59: =F59 -> 1200 | K59: 1200 | L59: =IFERROR(VLOOKUP("iPhone 5 Замена аккумулятора (1440mAh) 3.8V Standard", 'РЕМОНТ_ЯБЛОК'!C:D, 2, 0), "Ошибка") & " | " & IFERROR(VLOOKUP("iPhone 5 Замена аккумулятора (1800mAh) 3.8V HC (повышенная емкость)", 'РЕМОНТ_ЯБЛОК'!C:D, 2, 0), "Ошибка") -> 1200 | 1600
B60: iPhone 5 | D60: 90 | E60: Разъем зарядки - замена | F60: ='БД_УСЛУГИ_РО'!P60+'БД_ЗАПЧАСТИ'!P586 -> 750 | H60: ='БД_УСЛУГИ_РО'!P60 -> 700 | J60: =F60 -> 750 | K60: 750 | L60: =IFERROR(VLOOKUP("iPhone 5 Разъем питания", 'РЕМОНТ_ЯБЛОК'!C:D, 2, 0), "Ошибка") -> 1200
B61: iPhone 5 | D61: 90 | E61: Дисплей - замена на СНЯТЫЙ ОРИГИНАЛ | F61: ='БД_УСЛУГИ_РО'!P61 -> 800 | H61: ='БД_УСЛУГИ_РО'!P61 -> 800 | J61: =IFERROR(__xludf.DUMMYFUNCTION("MIN(FILTER(F61:F62, F61:F62 <> H61:H62, F61:F62 <> """"))"),"#N/A") -> #N/A | K61: 800 | L61: =IFERROR(VLOOKUP("iPhone 5 Замена дисплея (оригинал)", 'РЕМОНТ_ЯБЛОК'!C:D, 2, 0), "Ошибка") -> 3000
B62: iPhone 5 | D62: 90 | E62: Дисплей - замена на ВОССТАНОВЛЕННЫЙ ОРИГИНАЛ | F62: ='БД_УСЛУГИ_РО'!P61 -> 800 | H62: ='БД_УСЛУГИ_РО'!P61 -> 800 | K62: 800
B63: iPhone 5 | D63: 90 | E63: Дисплей - замена на АНАЛОГ | F63: ='БД_УСЛУГИ_РО'!P61 -> 800 | H63: ='БД_УСЛУГИ_РО'!P61 -> 800 | J63: =F63 -> 800 | K63: 800 | L63: =IFERROR(VLOOKUP("iPhone 5 Замена дисплея (аналог)", 'РЕМОНТ_ЯБЛОК'!C:D, 2, 0), "Ошибка") -> 2000
B64: iPhone 5 | D64: 90 | E64: Камера основная - замена | F64: ='БД_УСЛУГИ_РО'!P62+'БД_ЗАПЧАСТИ'!P751 -> 750 | H64: ='БД_УСЛУГИ_РО'!P62 -> 700 | J64: =F64 -> 750 | K64: 750 | L64: =IFERROR(VLOOKUP("iPhone 5 Замена основной камеры", 'РЕМОНТ_ЯБЛОК'!C:D, 2, 0), "Ошибка") -> 1200
B65: iPhone 5 | D65: 90 | E65: Камера фронтальная - замена | F65: ='БД_УСЛУГИ_РО'!P63+'БД_ЗАПЧАСТИ'!P792 -> 750 | H65: ='БД_УСЛУГИ_РО'!P63 -> 700 | J65: =F65 -> 750 | K65: 750 | L65: =IFERROR(VLOOKUP("iPhone 5 Замена фронтальной камеры", 'РЕМОНТ_ЯБЛОК'!C:D, 2, 0), "Ошибка") -> 1000
B66: iPhone 5 | D66: 180 | E66: Камера - замена разбитого стекла | *цена за 1шт. | F66: ='БД_УСЛУГИ_РО'!P64 -> 500 | H66: ='БД_УСЛУГИ_РО'!P64 -> 500 | K66: 500
B67: iPhone 5 | D67: 180 | E67: Корпус - замена | F67: ='БД_УСЛУГИ_РО'!P65 -> 800 | H67: ='БД_УСЛУГИ_РО'!P65 -> 800 | J67: =F67 -> 800 | K67: 800 | L67: =IFERROR(VLOOKUP("iPhone 5 Замена корпуса", 'РЕМОНТ_ЯБЛОК'!C:D, 2, 0), "Ошибка") -> 2500
B68: iPhone 5 | D68: 90 | E68: Кнопка HOME - восстановление / замена | F68: ='БД_УСЛУГИ_РО'!P66 -> 700 | H68: ='БД_УСЛУГИ_РО'!P66 -> 700 | J68: =F68 -> 700 | K68: 700 | L68: =IFERROR(VLOOKUP("iPhone 5 Замена кнопки Home", 'РЕМОНТ_ЯБЛОК'!C:D, 2, 0), "Ошибка") -> 1000
B69: iPhone 5 | D69: 90 | E69: Кнопки - восстановление / замена | *цена от, требуется диагностика | F69: ='БД_УСЛУГИ_РО'!P67 -> 700 | J69: =F69 -> 700 | K69: 700 | L69: =IFERROR(VLOOKUP("iPhone 5 Ремонт кнопки включения", 'РЕМОНТ_ЯБЛОК'!C:D, 2, 0), "Ошибка") & " | " & IFERROR(VLOOKUP("iPhone 5 Ремонт кнопок громкости", 'РЕМОНТ_ЯБЛОК'!C:D, 2, 0), "Ошибка") -> 1200 | 1200
B70: iPhone 5 | D70: 90 | E70: Динамик полифонический (нижний, громкая связь) - замена | F70: ='БД_УСЛУГИ_РО'!P68+'БД_ЗАПЧАСТИ'!P881 -> 850 | H70: ='БД_УСЛУГИ_РО'!P68 -> 800 | J70: =F70 -> 850 | K70: 850 | L70: =IFERROR(VLOOKUP("iPhone 5 Замена динамика", 'РЕМОНТ_ЯБЛОК'!C:D, 2, 0), "Ошибка") -> 800
B71: iPhone 5 | D71: 90 | E71: Динамик разговорный (верхний, слуховой) - замена | F71: ='БД_УСЛУГИ_РО'!P69+'БД_ЗАПЧАСТИ'!P836 -> 850 | H71: ='БД_УСЛУГИ_РО'!P69 -> 800 | J71: =F71 -> 850 | K71: 850 | L71: =IFERROR(VLOOKUP("iPhone 5 Замена динамика", 'РЕМОНТ_ЯБЛОК'!C:D, 2, 0), "Ошибка") -> 800
B72: iPhone 5 | D72: 90 | E72: Микрофон - замена (один из..) | *требуется диагностика | F72: ='БД_УСЛУГИ_РО'!P70+'БД_ЗАПЧАСТИ'!P586 -> 1050 | H72: ='БД_УСЛУГИ_РО'!P70 -> 1000 | J72: =F72 -> 1050 | K72: 1050 | L72: =IFERROR(VLOOKUP("iPhone 5 Замена микрофона", 'РЕМОНТ_ЯБЛОК'!C:D, 2, 0), "Ошибка") -> 1200
B73: iPhone 5 | D73: 90 | E73: Ремонт платы - восстановление / замена | *цена от, требуется диагностика | F73: ='БД_УСЛУГИ_РО'!P71 -> 1600 | K73: 1600
B74: iPhone 5 | D74: 90 | E74: Профилактика после воды - восстановление | *цена от, требуется диагностика | F74: ='БД_УСЛУГИ_РО'!P72 -> 2000 | K74: 2000
B75: iPhone 5 | D75: 90 | E75: Модем - восстановление GSM сети | *цена от, требуется диагностика | F75: ='БД_УСЛУГИ_РО'!P73 -> 2000 | K75: 2000
B76: iPhone 5 | D76: 90 | E76: WiFi / Bluetooth - восстановление беспроводных сетей | *цена от, требуется диагностика | F76: ='БД_УСЛУГИ_РО'!P74 -> 900 | J76: =F76 -> 900 | K76: 900 | L76: =IFERROR(VLOOKUP("iPhone 5 Ремонт WI-FI", 'РЕМОНТ_ЯБЛОК'!C:D, 2, 0), "Ошибка") -> 3000
B78: iPhone 5С | D78: 0 | E78: Диагностика (с пайкой компонентов) | *бесплатно при дальнейшем ремонте | F78: ='БД_УСЛУГИ_РО'!P56 -> 1 | K78: 1
B79: iPhone 5С | D79: 0 | E79: Чистка сеток динамиков и разъема зарядки БЕЗ РАЗБОРА | F79: ='БД_УСЛУГИ_РО'!P57 -> 400 | G79: =MIN(F79:F80) & " - " & MAX(F79:F80) -> 400 - 900 | K79: 400
B80: iPhone 5С | D80: 0 | E80: Чистка сеток динамиков и разъема зарядки С РАЗБОРОМ | F80: ='БД_УСЛУГИ_РО'!P58 -> 900 | K80: 900
B81: iPhone 5С | D81: 180 | E81: Аккумулятор - замена на АНАЛОГ | F81: ='БД_УСЛУГИ_РО'!P59+'БД_ЗАПЧАСТИ'!P6 -> 1200 | H81: ='БД_УСЛУГИ_РО'!P59 -> 700 | J81: =F81 -> 1200 | K81: 1200 | L81: =IFERROR(VLOOKUP("iPhone 5C Замена аккумулятора (1560mAh) 3.8V Standard", 'РЕМОНТ_ЯБЛОК'!C:D, 2, 0), "Ошибка") & " | " & IFERROR(VLOOKUP("iPhone 5C Замена аккумулятора (1800mAh) 3.8V HC (повышенная емкость)", 'РЕМОНТ_ЯБЛОК'!C:D, 2, 0), "Ошибка") -> 1200 | 1600
B82: iPhone 5С | D82: 90 | E82: Разъем зарядки - замена | F82: ='БД_УСЛУГИ_РО'!P60+'БД_ЗАПЧАСТИ'!P586 -> 750 | H82: ='БД_УСЛУГИ_РО'!P60 -> 700 | J82: =F82 -> 750 | K82: 750 | L82: =IFERROR(VLOOKUP("iPhone 5C Разъем питания", 'РЕМОНТ_ЯБЛОК'!C:D, 2, 0), "Ошибка") -> 1200
B83: iPhone 5С | D83: 90 | E83: Дисплей - замена на СНЯТЫЙ ОРИГИНАЛ | F83: ='БД_УСЛУГИ_РО'!P61 -> 800 | H83: ='БД_УСЛУГИ_РО'!P61 -> 800 | J83: =IFERROR(__xludf.DUMMYFUNCTION("MIN(FILTER(F83:F84, F83:F84 <> H83:H84, F83:F84 <> """"))"),850.0) -> 850 | K83: 800 | L83: =IFERROR(VLOOKUP("iPhone 5C Замена дисплея (оригинал)", 'РЕМОНТ_ЯБЛОК'!C:D, 2, 0), "Ошибка") -> 3000
B84: iPhone 5С | D84: 90 | E84: Дисплей - замена на ВОССТАНОВЛЕННЫЙ ОРИГИНАЛ | F84: ='БД_УСЛУГИ_РО'!P61+'БД_ЗАПЧАСТИ'!P149 -> 850 | H84: ='БД_УСЛУГИ_РО'!P61 -> 800 | K84: 850
B85: iPhone 5С | D85: 90 | E85: Дисплей - замена на АНАЛОГ | F85: ='БД_УСЛУГИ_РО'!P61 -> 800 | H85: ='БД_УСЛУГИ_РО'!P61 -> 800 | J85: =F85 -> 800 | K85: 800 | L85: =IFERROR(VLOOKUP("iPhone 5C Замена дисплея (аналог)", 'РЕМОНТ_ЯБЛОК'!C:D, 2, 0), "Ошибка") -> 2000
B86: iPhone 5С | D86: 90 | E86: Камера основная - замена | F86: ='БД_УСЛУГИ_РО'!P62+'БД_ЗАПЧАСТИ'!P751 -> 750 | H86: ='БД_УСЛУГИ_РО'!P62 -> 700 | J86: =F86 -> 750 | K86: 750 | L86: =IFERROR(VLOOKUP("iPhone 5C Замена основной камеры", 'РЕМОНТ_ЯБЛОК'!C:D, 2, 0), "Ошибка") -> 1200
B87: iPhone 5С | D87: 90 | E87: Камера фронтальная - замена | F87: ='БД_УСЛУГИ_РО'!P63+'БД_ЗАПЧАСТИ'!P792 -> 750 | H87: ='БД_УСЛУГИ_РО'!P63 -> 700 | J87: =F87 -> 750 | K87: 750 | L87: =IFERROR(VLOOKUP("iPhone 5C Замена фронтальной камеры", 'РЕМОНТ_ЯБЛОК'!C:D, 2, 0), "Ошибка") -> 1000
B88: iPhone 5С | D88: 180 | E88: Камера - замена разбитого стекла | *цена за 1шт. | F88: ='БД_УСЛУГИ_РО'!P64 -> 500 | H88: ='БД_УСЛУГИ_РО'!P64 -> 500 | K88: 500
B89: iPhone 5С | D89: 180 | E89: Корпус - замена | F89: ='БД_УСЛУГИ_РО'!P65 -> 800 | H89: ='БД_УСЛУГИ_РО'!P65 -> 800 | J89: =F89 -> 800 | K89: 800 | L89: =IFERROR(VLOOKUP("iPhone 5C Замена корпуса", 'РЕМОНТ_ЯБЛОК'!C:D, 2, 0), "Ошибка") -> 2500
B90: iPhone 5С | D90: 90 | E90: Кнопка HOME - восстановление / замена | F90: ='БД_УСЛУГИ_РО'!P66 -> 700 | H90: ='БД_УСЛУГИ_РО'!P66 -> 700 | J90: =F90 -> 700 | K90: 700 | L90: =IFERROR(VLOOKUP("iPhone 5 Замена кнопки Home", 'РЕМОНТ_ЯБЛОК'!C:D, 2, 0), "Ошибка") -> 1000
B91: iPhone 5С | D91: 90 | E91: Кнопки - восстановление / замена | *цена от, требуется диагностика | F91: ='БД_УСЛУГИ_РО'!P67 -> 700 | J91: =F91 -> 700 | K91: 700 | L91: =IFERROR(VLOOKUP("iPhone 5C Ремонт кнопки включения", 'РЕМОНТ_ЯБЛОК'!C:D, 2, 0), "Ошибка") & " | " & IFERROR(VLOOKUP("iPhone 5C Ремонт кнопок громкости", 'РЕМОНТ_ЯБЛОК'!C:D, 2, 0), "Ошибка") -> 1200 | 1200
B92: iPhone 5С | D92: 90 | E92: Динамик полифонический (нижний, громкая связь) - замена | F92: ='БД_УСЛУГИ_РО'!P68 -> 800 | H92: ='БД_УСЛУГИ_РО'!P68 -> 800 | J92: =F92 -> 800 | K92: 800 | L92: =IFERROR(VLOOKUP("iPhone 5C Замена динамика", 'РЕМОНТ_ЯБЛОК'!C:D, 2, 0), "Ошибка") -> 800
B93: iPhone 5С | D93: 90 | E93: Динамик разговорный (верхний, слуховой) - замена | F93: ='БД_УСЛУГИ_РО'!P69+'БД_ЗАПЧАСТИ'!P836 -> 850 | H93: ='БД_УСЛУГИ_РО'!P69 -> 800 | J93: =F93 -> 850 | K93: 850 | L93: =IFERROR(VLOOKUP("iPhone 5 Замена динамика", 'РЕМОНТ_ЯБЛОК'!C:D, 2, 0), "Ошибка") -> 800
B94: iPhone 5С | D94: 90 | E94: Микрофон - замена (один из..) | *требуется диагностика | F94: ='БД_УСЛУГИ_РО'!P70+'БД_ЗАПЧАСТИ'!P586 -> 1050 | H94: ='БД_УСЛУГИ_РО'!P70 -> 1000 | J94: =F94 -> 1050 | K94: 1050 | L94: =IFERROR(VLOOKUP("iPhone 5C Замена микрофона", 'РЕМОНТ_ЯБЛОК'!C:D, 2, 0), "Ошибка") -> 1200
B95: iPhone 5С | D95: 90 | E95: Ремонт платы - восстановление / замена | *цена от, требуется диагностика | F95: ='БД_УСЛУГИ_РО'!P71 -> 1600 | K95: 1600
B96: iPhone 5С | D96: 90 | E96: Профилактика после воды - восстановление | *цена от, требуется диагностика | F96: ='БД_УСЛУГИ_РО'!P72 -> 2000 | K96: 2000
B97: iPhone 5С | D97: 90 | E97: Модем - восстановление GSM сети | *цена от, требуется диагностика | F97: ='БД_УСЛУГИ_РО'!P73 -> 2000 | K97: 2000
B98: iPhone 5С | D98: 90 | E98: WiFi / Bluetooth - восстановление беспроводных сетей | *цена от, требуется диагностика | F98: ='БД_УСЛУГИ_РО'!P74 -> 900 | J98: =F98 -> 900 | K98: 900 | L98: =IFERROR(VLOOKUP("iPhone 5C Ремонт WI-FI", 'РЕМОНТ_ЯБЛОК'!C:D, 2, 0), "Ошибка") -> 4900
B100: iPhone 5S | D100: 0 | E100: Диагностика (с пайкой компонентов) | *бесплатно при дальнейшем ремонте | F100: ='БД_УСЛУГИ_РО'!P56 -> 1 | K100: 1
B101: iPhone 5S | D101: 0 | E101: Чистка сеток динамиков и разъема зарядки БЕЗ РАЗБОРА | F101: ='БД_УСЛУГИ_РО'!P57 -> 400 | G101: =MIN(F101:F102) & " - " & MAX(F101:F102) -> 400 - 900 | K101: 400
B102: iPhone 5S | D102: 0 | E102: Чистка сеток динамиков и разъема зарядки С РАЗБОРОМ | F102: ='БД_УСЛУГИ_РО'!P58 -> 900 | K102: 900
B103: iPhone 5S | D103: 180 | E103: Аккумулятор - замена на АНАЛОГ | F103: ='БД_УСЛУГИ_РО'!P59+'БД_ЗАПЧАСТИ'!P6 -> 1200 | H103: ='БД_УСЛУГИ_РО'!P59 -> 700 | J103: =F103 -> 1200 | K103: 1200 | L103: =IFERROR(VLOOKUP("iPhone 5S Замена аккумулятора (1560mAh) 3.8V Standard", 'РЕМОНТ_ЯБЛОК'!C:D, 2, 0), "Ошибка") & " | " & IFERROR(VLOOKUP("iPhone 5S Замена аккумулятора (1800mAh) 3.8V HC (повышенная емкость)", 'РЕМОНТ_ЯБЛОК'!C:D, 2, 0), "Ошибка") -> 1200 | 1600
B104: iPhone 5S | D104: 90 | E104: Разъем зарядки - замена | F104: ='БД_УСЛУГИ_РО'!P60+'БД_ЗАПЧАСТИ'!P586 -> 750 | H104: ='БД_УСЛУГИ_РО'!P60 -> 700 | J104: =F104 -> 750 | K104: 750 | L104: =IFERROR(VLOOKUP("iPhone 5S Разъем питания", 'РЕМОНТ_ЯБЛОК'!C:D, 2, 0), "Ошибка") -> 1200
B105: iPhone 5S | D105: 90 | E105: Дисплей - замена на СНЯТЫЙ ОРИГИНАЛ | F105: ='БД_УСЛУГИ_РО'!P61+'БД_ЗАПЧАСТИ'!P150 -> 2000 | G105: =MIN(F105:F107) & " - " & MAX(F105:F107) -> 800 - 2000 | H105: ='БД_УСЛУГИ_РО'!P61 -> 800 | J105: =IFERROR(__xludf.DUMMYFUNCTION("MIN(FILTER(F105:F106, F105:F106 <> H105:H106, F105:F106 <> """"))"),1850.0) -> 1850 | K105: 2000 | L105: =IFERROR(VLOOKUP("iPhone 5S Замена дисплея (оригинал)", 'РЕМОНТ_ЯБЛОК'!C:D, 2, 0), "Ошибка") -> 2500
...

Sheet БД_МОЙ СКЛАД
B2: МОДЕЛЬ | C2: КОД | D2: ЦЕНА | E2: Услуга | F2: Время | G2: Цена "ОТ" | H2: Гарантия | I2: Ссылка | J2: Описание | L2: ЗАВИСИМОСТЬ
B3: iPhone 17 Pro Max | C3: 782129785272454612 | D3: =IF('ПРАЙС_ЛИСТ'!F1470 <> 'ПРАЙС_ЛИСТ'!H1470, IF('ПРАЙС_ЛИСТ'!F1470 = 1, 0, 'ПРАЙС_ЛИСТ'!F1470), 0) -> 38500 | E3: Замена стекла | F3: 30 мин | H3: 90 дней | I3: https://maxmobiles.ru/zamena-stekla-iphone-17-pro-max/ | J3: При поломке только стекла на Вашем аппарате, без ущерба для дисплея и сенсора, возможна замена только стекла. Мы выполняем эту процедуру с использованием профессионального оборудования, обеспечивая сохранение оригинального экрана
C4: 7821297852724555125 | D4: 0 | E4: Замена дисплея (копия) | F4: 30 мин | G4: уточняйте | H4: 90 дней | I4: https://maxmobiles.ru/zamena-displeya-iphone-17-pro-max-kopiya/ | J4: У нас есть несколько вариантов копий на любой кошелек! Разница заключается в цветопередаче и возможности использования функции True Tone
C5: 782129785272454591 | D5: {=MIN(IF('ПРАЙС_ЛИСТ'!F1462:F1466 <> 'ПРАЙС_ЛИСТ'!H1462:H1466, 'ПРАЙС_ЛИСТ'!F1462:F1466, ""))} -> 42050 | E5: Замена дисплея (оригинал) | F5: 30 мин | G5: цена от | H5: 90 дней | I5: https://maxmobiles.ru/zamena-displeya-iphone-17-pro-max/ | J5: Хотите, чтобы всё работало как по-старому? Тогда оригинальный дисплей — ваш выбор. Сохранится цветопередача, Face ID и True Tone | L5: типа запчасти
C6: 782129785272454630 | D6: {=MIN(IF('ПРАЙС_ЛИСТ'!F1475:F1476 <> 'ПРАЙС_ЛИСТ'!H1475:H1476, 'ПРАЙС_ЛИСТ'!F1475:F1476, ""))} -> 12000 | E6: Замена заднего стекла | F6: 120 мин | G6: цена от | H6: 180 дней | I6: https://maxmobiles.ru/zamena-zadney-kryshki-stekla-iphone-17-pro-max/ | J6: Повреждённая задняя панель не только ухудшает внешний вид смартфона, но и может стать источником микроскопических осколков. В Макмобайлс мы применяем лазерную технологию для замены стекла, что обеспечивает безопасность и сохранность аппарата | L6: типа запчасти
C7: 782129785272454633 | D7: ='ПРАЙС_ЛИСТ'!F1484 -> 10300 | E7: Чистка после попадания воды | F7: 30 мин | G7: цена от | H7: 90 дней | I7: https://maxmobiles.ru/profilaktika-posle-vody-iphone-17-pro-max/ | J7: Apple заявляет, что их гаджеты надёжно защищены от воды, но это не так. При этом не сохраняется официальная гарантия. Протрите, отключите телефон и бегом в сервис! | L7: повреждения
C8: 782129785272454566 | D8: {=MIN(IF('ПРАЙС_ЛИСТ'!F1455:F1460 <> 'ПРАЙС_ЛИСТ'!H1455:H1460, 'ПРАЙС_ЛИСТ'!F1455:F1460, ""))} -> 0 | E8: Замена аккумулятора | F8: 35 мин | G8: уточняйте | H8: 180 дней | I8: https://maxmobiles.ru/zamena-akkumulyatora-iphone-17-pro-max/ | J8: Аккумулятор нетрудно заменить, однако проблема может быть не в нём. Приходите на диагностику, и мы разберёмся, что нужно менять: АКБ, контроллер питания или разъём зарядки
C9: 782129785272454590 | D9: =IF('ПРАЙС_ЛИСТ'!F1461 <> 'ПРАЙС_ЛИСТ'!H1461, 'ПРАЙС_ЛИСТ'!F1461, "0") -> 19300 | E9: Замена разъема зарядки | F9: 35 мин | H9: 90 дней | I9: https://maxmobiles.ru/zamena-razema-zaryadki-iphone-17-pro-max/ | J9: Почему iPhone не заряжается? Это может быть как проблема с батареей, контроллером питания или разъёмом зарядки. Если причина неочевидна, определить её поможет диагностика
C10: 782129785272454629 | D10: =IF('ПРАЙС_ЛИСТ'!F1482 <> 'ПРАЙС_ЛИСТ'!H1482, 'ПРАЙС_ЛИСТ'!F1482, "0") -> 18100 | E10: Замена микрофона | F10: 30 мин | H10: 90 дней | I10: https://maxmobiles.ru/zamena-mikrofona-iphone-17-pro-max/ | J10: Эту поломку легко обнаружить при разговоре или записи, но устранить её сможет только квалифицированный мастер, ведь нужно разбирать устройство и менять шлейфы
C11: 782129785272454621 | D11: =IF('ПРАЙС_ЛИСТ'!F1480 <> 'ПРАЙС_ЛИСТ'!H1480, 'ПРАЙС_ЛИСТ'!F1480, "0") -> 0 | E11: Замена динамика | F11: 35 мин | G11: уточняйте | H11: 90 дней | I11: https://maxmobiles.ru/zamena-dinamika-gromkoy-svyazi-iphone-17-pro-max/ | J11: Динамик iPhone хрипит? Это могло произойти из-за воды, грязи или механического повреждения. Не рискуйте техникой — обращайтесь в наш сервис
C12: 782129785272454572 | D12: =IF('ПРАЙС_ЛИСТ'!F1481 <> 'ПРАЙС_ЛИСТ'!H1481, 'ПРАЙС_ЛИСТ'!F1481, "0") -> 0 | E12: Замена слухового динамика | F12: 35 мин | G12: уточняйте | H12: 90 дней | I12: https://maxmobiles.ru/zamena-dinamika-iphone-17-pro-max/ | J12: На замену верхнего динамика, как и нижнего, предоставляется гарантия 90 дней. Процедура нужна, если Вы не слышите собеседника, звук верхнего динамика отсутствует
C13: 782129785272454594 | D13: =IF('ПРАЙС_ЛИСТ'!F1471 <> 'ПРАЙС_ЛИСТ'!H1471, 'ПРАЙС_ЛИСТ'!F1471, "0") -> 17200 | E13: Замена камеры | F13: 40 мин | H13: 90 дней | I13: https://maxmobiles.ru/zamena-osnovnoy-kamery-iphone-17-pro-max/ | J13: Не работает камера iPhone? Приходите в сервис на диагностику. Выявим все неполадки и устраним в кратчайшие сроки
C14: 782129785272454597 | D14: =IF('ПРАЙС_ЛИСТ'!F1472 <> 'ПРАЙС_ЛИСТ'!H1472, 'ПРАЙС_ЛИСТ'!F1472, "0") -> 18500 | E14: Замена фронтальной камеры | F14: 35 мин | H14: 90 дней | I14: https://maxmobiles.ru/zamena-frontalnoy-kamery-iphone-17-pro-max/ | J14: Почему камера на Айфоне не работает? Проблема может быть в сбое ПО, механических повреждениях, замыкании
C15: 782129785272454615 | D15: =IF('ПРАЙС_ЛИСТ'!F1473 <> 'ПРАЙС_ЛИСТ'!H1473, 'ПРАЙС_ЛИСТ'!F1473, "0") -> 9600 | E15: Замена стекла камеры | F15: 35 мин | H15: 180 дней | I15: https://maxmobiles.ru/zamena-stekla-kamery-iphone-17-pro-max/ | J15: Повреждения камеры, проявляющиеся в виде отказа макросъемки и проблем с фокусировкой, обычно связаны с загрязнением подвижного объектива мелкими частицами. Если в камеру попала пыль или осколки стекла, это может нарушить её нормальную работу
C16: 782129785272454603 | D16: 0 | E16: Замена корпуса | F16: 60 мин | G16: уточняйте | H16: 180 дней | I16: https://maxmobiles.ru/zamena-korpusa-iphone-17-pro-max/ | J16: Для замены корпуса потребуется полная разборка аппарата. Не стоит поручать столь ответственную процедуру дилетантам. Сертифицированные инженеры Максмобайлс быстро и качественно выполнят все ремонтные работы и Ваш гаджет будет как новый
C17: 782129785272454628 | D17: 0 | E17: Ремонт кнопок | F17: 40 мин | G17: уточняйте | H17: 90 дней | I17: https://maxmobiles.ru/zamena-knopok-iphone-17-pro-max/ | J17: Регулировка громкости связана с другими элементами — кнопкой блокировки, переключателем вибро-режима, датчиком приближения и вспышкой. Эти детали объединяются верхним шлейфом, из-за чего при его повреждении может понадобиться комплексный ремонт
C18: 78212978527245362 | D18: =IF('ПРАЙС_ЛИСТ'!F9 <> 'ПРАЙС_ЛИСТ'!H9, 'ПРАЙС_ЛИСТ'!F9, "0") -> 1100 | E18: Прошивка | F18: 120 мин | I18: https://maxmobiles.ru/proshivka-bez-rezervnoy-kopii-iphone-11/ | J18: Только после оценки состояния Вашего девайса и выявления всех неполадок наш специалист сможет определить, нужна ли восстановительная прошивка или полная замена системного ПО
C19: 782129785272455011 | D19: ='ПРАЙС_ЛИСТ'!F1483 -> 8800 | E19: Ремонт материнской платы | F19: 180 мин | G19: цена от | H19: 90 дней | I19: https://maxmobiles.ru/remont-platy-iphone-17-pro-max/ | J19: Инженеры Максмобайлс проведут комплексную диагностику вашего iPhone, чтобы точно определить проблему. Мы используем современное оборудование для выявления неисправностей и восстановления работоспособности платы | L19: повреждения
C20: 782129785272454583 | D20: ='ПРАЙС_ЛИСТ'!F1474 -> 10800 | E20: Ремонт Face ID | F20: 180 мин | G20: цена от | H20: 90 дней | I20: https://maxmobiles.ru/remont-face-id-iphone-17-pro-max/ | J20: Если повредилась камера TrueDepth, распознавание лица не происходит либо вовсе невозможно, требуется замена Face ID | L20: повреждения
B22: iPhone 17 Pro | C22: 782129785272454577 | D22: =IF('ПРАЙС_ЛИСТ'!F1433 <> 'ПРАЙС_ЛИСТ'!H1433, IF('ПРАЙС_ЛИСТ'!F1433 = 1, 0, 'ПРАЙС_ЛИСТ'!F1433), 0) -> 0 | E22: Замена стекла | F22: 30 мин | G22: уточняйте | H22: 90 дней | I22: https://maxmobiles.ru/zamena-stekla-iphone-17-pro/ | J22: При поломке только стекла на Вашем аппарате, без ущерба для дисплея и сенсора, возможна замена только стекла. Мы выполняем эту процедуру с использованием профессионального оборудования, обеспечивая сохранение оригинального экрана
C23: 7821297852724555129 | D23: 0 | E23: Замена дисплея (копия) | F23: 30 мин | G23: уточняйте | H23: 90 дней | I23: https://maxmobiles.ru/zamena-displeya-iphone-17-pro-kopiya/ | J23: У нас есть несколько вариантов копий на любой кошелек! Разница заключается в цветопередаче и возможности использования функции True Tone
C24: 782129785272454639 | D24: {=MIN(IF('ПРАЙС_ЛИСТ'!F1425:F1429 <> 'ПРАЙС_ЛИСТ'!H1425:H1429, 'ПРАЙС_ЛИСТ'!F1425:F1429, ""))} -> 38650 | E24: Замена дисплея (оригинал) | F24: 30 мин | G24: цена от | H24: 90 дней | I24: https://maxmobiles.ru/zamena-displeya-iphone-17-pro/ | J24: Хотите, чтобы всё работало как по-старому? Тогда оригинальный дисплей — ваш выбор. Сохранится цветопередача, Face ID и True Tone | L24: типа запчасти
C25: 782129785272454635 | D25: {=MIN(IF('ПРАЙС_ЛИСТ'!F1438:F1439 <> 'ПРАЙС_ЛИСТ'!H1438:H1439, 'ПРАЙС_ЛИСТ'!F1438:F1439, ""))} -> 11000 | E25: Замена заднего стекла | F25: 120 мин | G25: цена от | H25: 180 дней | I25: https://maxmobiles.ru/zamena-zadney-kryshki-stekla-iphone-17-pro/ | J25: Повреждённая задняя панель не только ухудшает внешний вид смартфона, но и может стать источником микроскопических осколков. В Макмобайлс мы применяем лазерную технологию для замены стекла, что обеспечивает безопасность и сохранность аппарата | L25: типа запчасти
C26: 782129785272454647 | D26: ='ПРАЙС_ЛИСТ'!F1447 -> 10300 | E26: Чистка после попадания воды | F26: 30 мин | G26: цена от | H26: 90 дней | I26: https://maxmobiles.ru/profilaktika-posle-vody-iphone-17-pro/ | J26: Apple заявляет, что их гаджеты надёжно защищены от воды, но это не так. При этом не сохраняется официальная гарантия. Протрите, отключите телефон и бегом в сервис! | L26: повреждения
C27: 782129785272454579 | D27: {=MIN(IF('ПРАЙС_ЛИСТ'!F1418:F1423 <> 'ПРАЙС_ЛИСТ'!H1418:H1423, 'ПРАЙС_ЛИСТ'!F1418:F1423, ""))} -> 0 | E27: Замена аккумулятора | F27: 35 мин | G27: уточняйте | H27: 180 дней | I27: https://maxmobiles.ru/zamena-akkumulyatora-iphone-17-pro/ | J27: Аккумулятор нетрудно заменить, однако проблема может быть не в нём. Приходите на диагностику, и мы разберёмся, что нужно менять: АКБ, контроллер питания или разъём зарядки
C28: 782129785272454642 | D28: =IF('ПРАЙС_ЛИСТ'!F1424 <> 'ПРАЙС_ЛИСТ'!H1424, 'ПРАЙС_ЛИСТ'!F1424, "0") -> 18200 | E28: Замена разъема зарядки | F28: 35 мин | H28: 90 дней | I28: https://maxmobiles.ru/zamena-razema-zaryadki-iphone-17-pro/ | J28: Почему iPhone не заряжается? Это может быть как проблема с батареей, контроллером питания или разъёмом зарядки. Если причина неочевидна, определить её поможет диагностика
C29: 782129785272454645 | D29: =IF('ПРАЙС_ЛИСТ'!F1445 <> 'ПРАЙС_ЛИСТ'!H1445, 'ПРАЙС_ЛИСТ'!F1445, "0") -> 17000 | E29: Замена микрофона | F29: 30 мин | H29: 90 дней | I29: https://maxmobiles.ru/zamena-mikrofona-iphone-17-pro/ | J29: Эту поломку легко обнаружить при разговоре или записи, но устранить её сможет только квалифицированный мастер, ведь нужно разбирать устройство и менять шлейфы
C30: 782129785272454585 | D30: =IF('ПРАЙС_ЛИСТ'!F1443 <> 'ПРАЙС_ЛИСТ'!H1443, 'ПРАЙС_ЛИСТ'!F1443, "0") -> 0 | E30: Замена динамика | F30: 35 мин | G30: уточняйте | H30: 90 дней | I30: https://maxmobiles.ru/zamena-dinamika-gromkoy-svyazi-iphone-17-pro/ | J30: Динамик iPhone хрипит? Это могло произойти из-за воды, грязи или механического повреждения. Не рискуйте техникой — обращайтесь в наш сервис
C31: 782129785272454620 | D31: =IF('ПРАЙС_ЛИСТ'!F1444 <> 'ПРАЙС_ЛИСТ'!H1444, 'ПРАЙС_ЛИСТ'!F1444, "0") -> 0 | E31: Замена слухового динамика | F31: 35 мин | G31: уточняйте | H31: 90 дней | I31: https://maxmobiles.ru/zamena-dinamika-iphone-17-pro/ | J31: На замену верхнего динамика, как и нижнего, предоставляется гарантия 90 дней. Процедура нужна, если Вы не слышите собеседника, звук верхнего динамика отсутствует
C32: 782129785272454623 | D32: =IF('ПРАЙС_ЛИСТ'!F1434 <> 'ПРАЙС_ЛИСТ'!H1434, 'ПРАЙС_ЛИСТ'!F1434, "0") -> 16650 | E32: Замена камеры | F32: 40 мин | H32: 90 дней | I32: https://maxmobiles.ru/zamena-osnovnoy-kamery-iphone-17-pro/ | J32: Не работает камера iPhone? Приходите в сервис на диагностику. Выявим все неполадки и устраним в кратчайшие сроки
C33: 782129785272454626 | D33: =IF('ПРАЙС_ЛИСТ'!F1435 <> 'ПРАЙС_ЛИСТ'!H1435, 'ПРАЙС_ЛИСТ'!F1435, "0") -> 17300 | E33: Замена фронтальной камеры | F33: 35 мин | H33: 90 дней | I33: https://maxmobiles.ru/zamena-frontalnoy-kamery-iphone-17-pro/ | J33: Почему камера на Айфоне не работает? Проблема может быть в сбое ПО, механических повреждениях, замыкании
C34: 782129785272454605 | D34: =IF('ПРАЙС_ЛИСТ'!F1436 <> 'ПРАЙС_ЛИСТ'!H1436, 'ПРАЙС_ЛИСТ'!F1436, "0") -> 8900 | E34: Замена стекла камеры | F34: 35 мин | H34: 180 дней | I34: https://maxmobiles.ru/zamena-stekla-kamery-iphone-17-pro/ | J34: Повреждения камеры, проявляющиеся в виде отказа макросъемки и проблем с фокусировкой, обычно связаны с загрязнением подвижного объектива мелкими частицами. Если в камеру попала пыль или осколки стекла, это может нарушить её нормальную работу
C35: 782129785272454617 | D35: 0 | E35: Замена корпуса | F35: 60 мин | G35: уточняйте | H35: 180 дней | I35: https://maxmobiles.ru/zamena-korpusa-iphone-17-pro/ | J35: Для замены корпуса потребуется полная разборка аппарата. Не стоит поручать столь ответственную процедуру дилетантам. Сертифицированные инженеры Максмобайлс быстро и качественно выполнят все ремонтные работы и Ваш гаджет будет как новый
C36: 782129785272454614 | D36: 0 | E36: Ремонт кнопок | F36: 40 мин | G36: уточняйте | H36: 90 дней | I36: https://maxmobiles.ru/zamena-knopok-iphone-17-pro/ | J36: Регулировка громкости связана с другими элементами — кнопкой блокировки, переключателем вибро-режима, датчиком приближения и вспышкой. Эти детали объединяются верхним шлейфом, из-за чего при его повреждении может понадобиться комплексный ремонт
C37: 78212978527245362 | D37: =IF('ПРАЙС_ЛИСТ'!F9 <> 'ПРАЙС_ЛИСТ'!H9, 'ПРАЙС_ЛИСТ'!F9, "0") -> 1100 | E37: Прошивка | F37: 120 мин | I37: https://maxmobiles.ru/proshivka-bez-rezervnoy-kopii-iphone-11/ | J37: Только после оценки состояния Вашего девайса и выявления всех неполадок наш специалист сможет определить, нужна ли восстановительная прошивка или полная замена системного ПО
C38: 782129785272455010 | D38: ='ПРАЙС_ЛИСТ'!F1446 -> 8800 | E38: Ремонт материнской платы | F38: 180 мин | G38: цена от | H38: 90 дней | I38: https://maxmobiles.ru/remont-platy-iphone-17-pro/ | J38: Инженеры Максмобайлс проведут комплексную диагностику вашего iPhone, чтобы точно определить проблему. Мы используем современное оборудование для выявления неисправностей и восстановления работоспособности платы | L38: повреждения
C39: 782129785272454588 | D39: ='ПРАЙС_ЛИСТ'!F1437 -> 10800 | E39: Ремонт Face ID | F39: 180 мин | G39: цена от | H39: 90 дней | I39: https://maxmobiles.ru/remont-face-id-iphone-17-pro/ | J39: Если повредилась камера TrueDepth, распознавание лица не происходит либо вовсе невозможно, требуется замена Face ID | L39: повреждения
B41: iPhone 17 Air | C41: 782129785272454571 | D41: =IF('ПРАЙС_ЛИСТ'!F1396 <> 'ПРАЙС_ЛИСТ'!H1396, IF('ПРАЙС_ЛИСТ'!F1396 = 1, 0, 'ПРАЙС_ЛИСТ'!F1396), 0) -> 0 | E41: Замена стекла | F41: 30 мин | G41: уточняйте | H41: 90 дней | I41: https://maxmobiles.ru/zamena-stekla-iphone-air/ | J41: При поломке только стекла на Вашем аппарате, без ущерба для дисплея и сенсора, возможна замена только стекла. Мы выполняем эту процедуру с использованием профессионального оборудования, обеспечивая сохранение оригинального экрана
C42: 7821297852724555130 | D42: 0 | E42: Замена дисплея (копия) | F42: 30 мин | G42: уточняйте | H42: 90 дней | I42: https://maxmobiles.ru/zamena-displeya-iphone-air-kopiya/ | J42: У нас есть несколько вариантов копий на любой кошелек! Разница заключается в цветопередаче и возможности использования функции True Tone
C43: 782129785272454604 | D43: {=MIN(IF('ПРАЙС_ЛИСТ'!F1388:F1392 <> 'ПРАЙС_ЛИСТ'!H1388:H1392, 'ПРАЙС_ЛИСТ'!F1388:F1392, ""))} -> 39200 | E43: Замена дисплея (оригинал) | F43: 30 мин | G43: цена от | H43: 90 дней | I43: https://maxmobiles.ru/zamena-displeya-iphone-air/ | J43: Хотите, чтобы всё работало как по-старому? Тогда оригинальный дисплей — ваш выбор. Сохранится цветопередача, Face ID и True Tone | L43: типа запчасти
C44: 782129785272454584 | D44: {=MIN(IF('ПРАЙС_ЛИСТ'!F1401:F1402 <> 'ПРАЙС_ЛИСТ'!H1401:H1402, 'ПРАЙС_ЛИСТ'!F1401:F1402, ""))} -> 19000 | E44: Замена заднего стекла | F44: 120 мин | G44: цена от | H44: 180 дней | I44: https://maxmobiles.ru/zamena-zadney-kryshki-stekla-iphone-air/ | J44: Повреждённая задняя панель не только ухудшает внешний вид смартфона, но и может стать источником микроскопических осколков. В Макмобайлс мы применяем лазерную технологию для замены стекла, что обеспечивает безопасность и сохранность аппарата | L44: типа запчасти
C45: 782129785272454602 | D45: ='ПРАЙС_ЛИСТ'!F1410 -> 10300 | E45: Чистка после попадания воды | F45: 30 мин | G45: цена от | H45: 90 дней | I45: https://maxmobiles.ru/profilaktika-posle-vody-iphone-air/ | J45: Apple заявляет, что их гаджеты надёжно защищены от воды, но это не так. При этом не сохраняется официальная гарантия. Протрите, отключите телефон и бегом в сервис! | L45: повреждения
C46: 782129785272454613 | D46: {=MIN(IF('ПРАЙС_ЛИСТ'!F1381:F1386 <> 'ПРАЙС_ЛИСТ'!H1381:H1386, 'ПРАЙС_ЛИСТ'!F1381:F1386, ""))} -> 0 | E46: Замена аккумулятора | F46: 35 мин | G46: уточняйте | H46: 180 дней | I46: https://maxmobiles.ru/zamena-akkumulyatora-iphone-air/ | J46: Аккумулятор нетрудно заменить, однако проблема может быть не в нём. Приходите на диагностику, и мы разберёмся, что нужно менять: АКБ, контроллер питания или разъём зарядки
C47: 782129785272454568 | D47: =IF('ПРАЙС_ЛИСТ'!F1387 <> 'ПРАЙС_ЛИСТ'!H1387, 'ПРАЙС_ЛИСТ'!F1387, "0") -> 16800 | E47: Замена разъема зарядки | F47: 35 мин | H47: 90 дней | I47: https://maxmobiles.ru/zamena-razema-zaryadki-iphone-air/ | J47: Почему iPhone не заряжается? Это может быть как проблема с батареей, контроллером питания или разъёмом зарядки. Если причина неочевидна, определить её поможет диагностика
C48: 782129785272454576 | D48: =IF('ПРАЙС_ЛИСТ'!F1408 <> 'ПРАЙС_ЛИСТ'!H1408, 'ПРАЙС_ЛИСТ'!F1408, "0") -> 15100 | E48: Замена микрофона | F48: 30 мин | H48: 90 дней | I48: https://maxmobiles.ru/zamena-mikrofona-iphone-air/ | J48: Эту поломку легко обнаружить при разговоре или записи, но устранить её сможет только квалифицированный мастер, ведь нужно разбирать устройство и менять шлейфы
C49: 782129785272454573 | D49: =IF('ПРАЙС_ЛИСТ'!F1406 <> 'ПРАЙС_ЛИСТ'!H1406, 'ПРАЙС_ЛИСТ'!F1406, "0") -> 0 | E49: Замена динамика | F49: 35 мин | G49: уточняйте | H49: 90 дней | I49: https://maxmobiles.ru/zamena-dinamika-gromkoy-svyazi-iphone-air/ | J49: Динамик iPhone хрипит? Это могло произойти из-за воды, грязи или механического повреждения. Не рискуйте техникой — обращайтесь в наш сервис
C50: 782129785272454586 | D50: =IF('ПРАЙС_ЛИСТ'!F1407 <> 'ПРАЙС_ЛИСТ'!H1407, 'ПРАЙС_ЛИСТ'!F1407, "0") -> 0 | E50: Замена слухового динамика | F50: 35 мин | G50: уточняйте | H50: 90 дней | I50: https://maxmobiles.ru/zamena-dinamika-iphone-air/ | J50: На замену верхнего динамика, как и нижнего, предоставляется гарантия 90 дней. Процедура нужна, если Вы не слышите собеседника, звук верхнего динамика отсутствует
C51: 782129785272454644 | D51: =IF('ПРАЙС_ЛИСТ'!F1397 <> 'ПРАЙС_ЛИСТ'!H1397, 'ПРАЙС_ЛИСТ'!F1397, "0") -> 15100 | E51: Замена камеры | F51: 40 мин | H51: 90 дней | I51: https://maxmobiles.ru/zamena-osnovnoy-kamery-iphone-air/ | J51: Не работает камера iPhone? Приходите в сервис на диагностику. Выявим все неполадки и устраним в кратчайшие сроки
C52: 782129785272454570 | D52: =IF('ПРАЙС_ЛИСТ'!F1398 <> 'ПРАЙС_ЛИСТ'!H1398, 'ПРАЙС_ЛИСТ'!F1398, "0") -> 16500 | E52: Замена фронтальной камеры | F52: 35 мин | H52: 90 дней | I52: https://maxmobiles.ru/zamena-frontalnoy-kamery-iphone-air/ | J52: Почему камера на Айфоне не работает? Проблема может быть в сбое ПО, механических повреждениях, замыкании
C53: 782129785272454581 | D53: =IF('ПРАЙС_ЛИСТ'!F1399 <> 'ПРАЙС_ЛИСТ'!H1399, 'ПРАЙС_ЛИСТ'!F1399, "0") -> 7800 | E53: Замена стекла камеры | F53: 35 мин | H53: 180 дней | I53: https://maxmobiles.ru/zamena-stekla-kamery-iphone-air/ | J53: Повреждения камеры, проявляющиеся в виде отказа макросъемки и проблем с фокусировкой, обычно связаны с загрязнением подвижного объектива мелкими частицами. Если в камеру попала пыль или осколки стекла, это может нарушить её нормальную работу
C54: 782129785272454563 | D54: 0 | E54: Замена корпуса | F54: 60 мин | G54: уточняйте | H54: 180 дней | I54: https://maxmobiles.ru/zamena-korpusa-iphone-air/ | J54: Для замены корпуса потребуется полная разборка аппарата. Не стоит поручать столь ответственную процедуру дилетантам. Сертифицированные инженеры Максмобайлс быстро и качественно выполнят все ремонтные работы и Ваш гаджет будет как новый
C55: 782129785272454561 | D55: 0 | E55: Ремонт кнопок | F55: 40 мин | G55: уточняйте | H55: 90 дней | I55: https://maxmobiles.ru/zamena-knopok-iphone-air/ | J55: Регулировка громкости связана с другими элементами — кнопкой блокировки, переключателем вибро-режима, датчиком приближения и вспышкой. Эти детали объединяются верхним шлейфом, из-за чего при его повреждении может понадобиться комплексный ремонт
C56: 78212978527245362 | D56: =IF('ПРАЙС_ЛИСТ'!F9 <> 'ПРАЙС_ЛИСТ'!H9, 'ПРАЙС_ЛИСТ'!F9, "0") -> 1100 | E56: Прошивка | F56: 120 мин | I56: https://maxmobiles.ru/proshivka-bez-rezervnoy-kopii-iphone-11/ | J56: Только после оценки состояния Вашего девайса и выявления всех неполадок наш специалист сможет определить, нужна ли восстановительная прошивка или полная замена системного ПО
C57: 782129785272455012 | D57: ='ПРАЙС_ЛИСТ'!F1409 -> 8800 | E57: Ремонт материнской платы | F57: 180 мин | G57: цена от | H57: 90 дней | I57: https://maxmobiles.ru/remont-platy-iphone-air/ | J57: Инженеры Максмобайлс проведут комплексную диагностику вашего iPhone, чтобы точно определить проблему. Мы используем современное оборудование для выявления неисправностей и восстановления работоспособности платы | L57: повреждения
C58: 782129785272454569 | D58: ='ПРАЙС_ЛИСТ'!F1400 -> 10800 | E58: Ремонт Face ID | F58: 180 мин | G58: цена от | H58: 90 дней | I58: https://maxmobiles.ru/remont-face-id-iphone-air/ | J58: Если повредилась камера TrueDepth, распознавание лица не происходит либо вовсе невозможно, требуется замена Face ID | L58: повреждения
B60: iPhone 17 | C60: 782129785272454557 | D60: =IF('ПРАЙС_ЛИСТ'!F1359 <> 'ПРАЙС_ЛИСТ'!H1359, IF('ПРАЙС_ЛИСТ'!F1359 = 1, 0, 'ПРАЙС_ЛИСТ'!F1359), 0) -> 0 | E60: Замена стекла | F60: 30 мин | G60: уточняйте | H60: 90 дней | I60: https://maxmobiles.ru/zamena-stekla-iphone-17/ | J60: При поломке только стекла на Вашем аппарате, без ущерба для дисплея и сенсора, возможна замена только стекла. Мы выполняем эту процедуру с использованием профессионального оборудования, обеспечивая сохранение оригинального экрана
C61: 7821297852724555128 | D61: 0 | E61: Замена дисплея (копия) | F61: 30 мин | G61: уточняйте | H61: 90 дней | I61: https://maxmobiles.ru/zamena-displeya-iphone-17-kopiya/ | J61: У нас есть несколько вариантов копий на любой кошелек! Разница заключается в цветопередаче и возможности использования функции True Tone
C62: 782129785272454631 | D62: {=MIN(IF('ПРАЙС_ЛИСТ'!F1351:F1355 <> 'ПРАЙС_ЛИСТ'!H1351:H1355, 'ПРАЙС_ЛИСТ'!F1351:F1355, ""))} -> 38700 | E62: Замена дисплея (оригинал) | F62: 30 мин | G62: цена от | H62: 90 дней | I62: https://maxmobiles.ru/zamena-displeya-iphone-17/ | J62: Хотите, чтобы всё работало как по-старому? Тогда оригинальный дисплей — ваш выбор. Сохранится цветопередача, Face ID и True Tone | L62: типа запчасти
C63: 782129785272454593 | D63: {=MIN(IF('ПРАЙС_ЛИСТ'!F1364:F1365 <> 'ПРАЙС_ЛИСТ'!H1364:H1365, 'ПРАЙС_ЛИСТ'!F1364:F1365, ""))} -> 10000 | E63: Замена заднего стекла | F63: 120 мин | G63: цена от | H63: 180 дней | I63: https://maxmobiles.ru/zamena-zadney-kryshki-stekla-iphone-17/ | J63: Повреждённая задняя панель не только ухудшает внешний вид смартфона, но и может стать источником микроскопических осколков. В Макмобайлс мы применяем лазерную технологию для замены стекла, что обеспечивает безопасность и сохранность аппарата | L63: типа запчасти
C64: 782129785272454552 | D64: ='ПРАЙС_ЛИСТ'!F1373 -> 10300 | E64: Чистка после попадания воды | F64: 30 мин | G64: цена от | H64: 90 дней | I64: https://maxmobiles.ru/profilaktika-posle-vody-iphone-17/ | J64: Apple заявляет, что их гаджеты надёжно защищены от воды, но это не так. При этом не сохраняется официальная гарантия. Протрите, отключите телефон и бегом в сервис! | L64: повреждения
C65: 782129785272454589 | D65: {=MIN(IF('ПРАЙС_ЛИСТ'!F1344:F1349 <> 'ПРАЙС_ЛИСТ'!H1344:H1349, 'ПРАЙС_ЛИСТ'!F1344:F1349, ""))} -> 0 | E65: Замена аккумулятора | F65: 35 мин | G65: уточняйте | H65: 180 дней | I65: https://maxmobiles.ru/zamena-akkumulyatora-iphone-17/ | J65: Аккумулятор нетрудно заменить, однако проблема может быть не в нём. Приходите на диагностику, и мы разберёмся, что нужно менять: АКБ, контроллер питания или разъём зарядки
C66: 782129785272454558 | D66: =IF('ПРАЙС_ЛИСТ'!F1350 <> 'ПРАЙС_ЛИСТ'!H1350, 'ПРАЙС_ЛИСТ'!F1350, "0") -> 15250 | E66: Замена разъема зарядки | F66: 35 мин | H66: 90 дней | I66: https://maxmobiles.ru/zamena-razema-zaryadki-iphone-17/ | J66: Почему iPhone не заряжается? Это может быть как проблема с батареей, контроллером питания или разъёмом зарядки. Если причина неочевидна, определить её поможет диагностика
C67: 782129785272454560 | D67: =IF('ПРАЙС_ЛИСТ'!F1371 <> 'ПРАЙС_ЛИСТ'!H1371, 'ПРАЙС_ЛИСТ'!F1371, "0") -> 13550 | E67: Замена микрофона | F67: 30 мин | H67: 90 дней | I67: https://maxmobiles.ru/zamena-mikrofona-iphone-17/ | J67: Эту поломку легко обнаружить при разговоре или записи, но устранить её сможет только квалифицированный мастер, ведь нужно разбирать устройство и менять шлейфы
C68: 782129785272454625 | D68: =IF('ПРАЙС_ЛИСТ'!F1369 <> 'ПРАЙС_ЛИСТ'!H1369, 'ПРАЙС_ЛИСТ'!F1369, "0") -> 0 | E68: Замена динамика | F68: 35 мин | G68: уточняйте | H68: 90 дней | I68: https://maxmobiles.ru/zamena-dinamika-gromkoy-svyazi-iphone-17/ | J68: Динамик iPhone хрипит? Это могло произойти из-за воды, грязи или механического повреждения. Не рискуйте техникой — обращайтесь в наш сервис
C69: 782129785272454606 | D69: =IF('ПРАЙС_ЛИСТ'!F1370 <> 'ПРАЙС_ЛИСТ'!H1370, 'ПРАЙС_ЛИСТ'!F1370, "0") -> 0 | E69: Замена слухового динамика | F69: 35 мин | G69: уточняйте | H69: 90 дней | I69: https://maxmobiles.ru/zamena-dinamika-iphone-17/ | J69: На замену верхнего динамика, как и нижнего, предоставляется гарантия 90 дней. Процедура нужна, если Вы не слышите собеседника, звук верхнего динамика отсутствует
C70: 782129785272454559 | D70: =IF('ПРАЙС_ЛИСТ'!F1360 <> 'ПРАЙС_ЛИСТ'!H1360, 'ПРАЙС_ЛИСТ'!F1360, "0") -> 16200 | E70: Замена камеры | F70: 40 мин | H70: 90 дней | I70: https://maxmobiles.ru/zamena-osnovnoy-kamery-iphone-17/ | J70: Не работает камера iPhone? Приходите в сервис на диагностику. Выявим все неполадки и устраним в кратчайшие сроки
C71: 782129785272454555 | D71: =IF('ПРАЙС_ЛИСТ'!F1361 <> 'ПРАЙС_ЛИСТ'!H1361, 'ПРАЙС_ЛИСТ'!F1361, "0") -> 16000 | E71: Замена фронтальной камеры | F71: 35 мин | H71: 90 дней | I71: https://maxmobiles.ru/zamena-frontalnoy-kamery-iphone-17/ | J71: Почему камера на Айфоне не работает? Проблема может быть в сбое ПО, механических повреждениях, замыкании
C72: 782129785272454556 | D72: =IF('ПРАЙС_ЛИСТ'!F1362 <> 'ПРАЙС_ЛИСТ'!H1362, 'ПРАЙС_ЛИСТ'!F1362, "0") -> 7700 | E72: Замена стекла камеры | F72: 35 мин | H72: 180 дней | I72: https://maxmobiles.ru/zamena-stekla-kamery-iphone-17/ | J72: Повреждения камеры, проявляющиеся в виде отказа макросъемки и проблем с фокусировкой, обычно связаны с загрязнением подвижного объектива мелкими частицами. Если в камеру попала пыль или осколки стекла, это может нарушить её нормальную работу
C73: 782129785272454611 | D73: 0 | E73: Замена корпуса | F73: 60 мин | G73: уточняйте | H73: 180 дней | I73: https://maxmobiles.ru/zamena-korpusa-iphone-17/ | J73: Для замены корпуса потребуется полная разборка аппарата. Не стоит поручать столь ответственную процедуру дилетантам. Сертифицированные инженеры Максмобайлс быстро и качественно выполнят все ремонтные работы и Ваш гаджет будет как новый
C74: 782129785272454627 | D74: 0 | E74: Ремонт кнопок | F74: 40 мин | G74: уточняйте | H74: 90 дней | I74: https://maxmobiles.ru/zamena-knopok-iphone-17/ | J74: Регулировка громкости связана с другими элементами — кнопкой блокировки, переключателем вибро-режима, датчиком приближения и вспышкой. Эти детали объединяются верхним шлейфом, из-за чего при его повреждении может понадобиться комплексный ремонт
C75: 78212978527245362 | D75: =IF('ПРАЙС_ЛИСТ'!F9 <> 'ПРАЙС_ЛИСТ'!H9, 'ПРАЙС_ЛИСТ'!F9, "0") -> 1100 | E75: Прошивка | F75: 120 мин | I75: https://maxmobiles.ru/proshivka-bez-rezervnoy-kopii-iphone-11/ | J75: Только после оценки состояния Вашего девайса и выявления всех неполадок наш специалист сможет определить, нужна ли восстановительная прошивка или полная замена системного ПО
C76: 782129785272455009 | D76: ='ПРАЙС_ЛИСТ'!F1372 -> 8800 | E76: Ремонт материнской платы | F76: 180 мин | G76: цена от | H76: 90 дней | I76: https://maxmobiles.ru/remont-platy-iphone-17/ | J76: Инженеры Максмобайлс проведут комплексную диагностику вашего iPhone, чтобы точно определить проблему. Мы используем современное оборудование для выявления неисправностей и восстановления работоспособности платы | L76: повреждения
C77: 782129785272454553 | D77: ='ПРАЙС_ЛИСТ'!F1363 -> 10800 | E77: Ремонт Face ID | F77: 180 мин | G77: цена от | H77: 90 дней | I77: https://maxmobiles.ru/remont-face-id-iphone-17/ | J77: Если повредилась камера TrueDepth, распознавание лица не происходит либо вовсе невозможно, требуется замена Face ID | L77: повреждения
B79: iPhone 16 Pro Max | C79: 782129785272454051 | D79: =IF('ПРАЙС_ЛИСТ'!F1322 <> 'ПРАЙС_ЛИСТ'!H1322, IF('ПРАЙС_ЛИСТ'!F1322 = 1, 0, 'ПРАЙС_ЛИСТ'!F1322), 0) -> 26000 | E79: Замена стекла | F79: 30 мин | H79: 90 дней | I79: https://maxmobiles.ru/displey-zamena-razbitogo-stekla-iphone-16-pro-max/ | J79: При поломке только стекла на Вашем аппарате, без ущерба для дисплея и сенсора, возможна замена только стекла. Мы выполняем эту процедуру с использованием профессионального оборудования, обеспечивая сохранение оригинального экрана
C80: 782129785272454074 | D80: 0 | E80: Замена дисплея (копия) | F80: 30 мин | G80: уточняйте | H80: 90 дней | I80: https://maxmobiles.ru/displey-kopiya-vysochayshego-kachestva-zamena-iphone-16-pro-max/ | J80: У нас есть несколько вариантов копий на любой кошелек! Разница заключается в цветопередаче и возможности использования функции True Tone
C81: 782129785272454216 | D81: {=MIN(IF('ПРАЙС_ЛИСТ'!F1314:F1318 <> 'ПРАЙС_ЛИСТ'!H1314:H1318, 'ПРАЙС_ЛИСТ'!F1314:F1318, ""))} -> 35000 | E81: Замена дисплея (оригинал) | F81: 30 мин | G81: цена от | H81: 90 дней | I81: https://maxmobiles.ru/displey-snyatyy-original-bez-privyazki-zamena-iphone-16-pro-max/ | J81: Хотите, чтобы всё работало как по-старому? Тогда оригинальный дисплей — ваш выбор. Сохранится цветопередача, Face ID и True Tone | L81: типа запчасти
C82: 782129785272454185 | D82: {=MIN(IF('ПРАЙС_ЛИСТ'!F1327:F1328 <> 'ПРАЙС_ЛИСТ'!H1327:H1328, 'ПРАЙС_ЛИСТ'!F1327:F1328, ""))} -> 8000 | E82: Замена заднего стекла | F82: 120 мин | G82: цена от | H82: 180 дней | I82: https://maxmobiles.ru/zadnyaya-kryshka-kopiya-vysochayshego-kachestva-zamena-stekla-iphone-16-pro-max/ | J82: Повреждённая задняя панель не только ухудшает внешний вид смартфона, но и может стать источником микроскопических осколков. В Макмобайлс мы применяем лазерную технологию для замены стекла, что обеспечивает безопасность и сохранность аппарата | L82: типа запчасти
C83: 782129785272454068 | D83: ='ПРАЙС_ЛИСТ'!F1336 -> 9000 | E83: Чистка после попадания воды | F83: 30 мин | G83: цена от | H83: 90 дней | I83: https://maxmobiles.ru/profilaktika-posle-vody-vosstanovlenie-cena-ot-trebuetsya-diagnostika-iphone-16-pro-max/ | J83: Apple заявляет, что их гаджеты надёжно защищены от воды, но это не так. При этом не сохраняется официальная гарантия. Протрите, отключите телефон и бегом в сервис! | L83: повреждения
C84: 782129785272454058 | D84: {=MIN(IF('ПРАЙС_ЛИСТ'!F1307:F1312 <> 'ПРАЙС_ЛИСТ'!H1307:H1312, 'ПРАЙС_ЛИСТ'!F1307:F1312, ""))} -> 12000 | E84: Замена аккумулятора | F84: 35 мин | G84: цена от | H84: 180 дней | I84: https://maxmobiles.ru/akkumulyator-original-zamena-iphone-16-pro-max/ | J84: Аккумулятор нетрудно заменить, однако проблема может быть не в нём. Приходите на диагностику, и мы разберёмся, что нужно менять: АКБ, контроллер питания или разъём зарядки | L84: типа запчасти
C85: 782129785272454060 | D85: =IF('ПРАЙС_ЛИСТ'!F1313 <> 'ПРАЙС_ЛИСТ'!H1313, 'ПРАЙС_ЛИСТ'!F1313, "0") -> 13750 | E85: Замена разъема зарядки | F85: 35 мин | H85: 90 дней | I85: https://maxmobiles.ru/razem-zaryadki-zamena-iphone-16-pro-max/ | J85: Почему iPhone не заряжается? Это может быть как проблема с батареей, контроллером питания или разъёмом зарядки. Если причина неочевидна, определить её поможет диагностика
C86: 782129785272454154 | D86: =IF('ПРАЙС_ЛИСТ'!F1334 <> 'ПРАЙС_ЛИСТ'!H1334, 'ПРАЙС_ЛИСТ'!F1334, "0") -> 13650 | E86: Замена микрофона | F86: 30 мин | H86: 90 дней | I86: https://maxmobiles.ru/mikrofon-zamena-odin-iz-iphone-16-pro-max/ | J86: Эту поломку легко обнаружить при разговоре или записи, но устранить её сможет только квалифицированный мастер, ведь нужно разбирать устройство и менять шлейфы
C87: 782129785272454106 | D87: =IF('ПРАЙС_ЛИСТ'!F1332 <> 'ПРАЙС_ЛИСТ'!H1332, 'ПРАЙС_ЛИСТ'!F1332, "0") -> 0 | E87: Замена динамика | F87: 35 мин | G87: уточняйте | H87: 90 дней | I87: https://maxmobiles.ru/dinamik-polifonicheskiy-nizhniy-gromkaya-svyaz-zamena-iphone-16-pro-max/ | J87: Динамик iPhone хрипит? Это могло произойти из-за воды, грязи или механического повреждения. Не рискуйте техникой — обращайтесь в наш сервис
C88: 782129785272454198 | D88: =IF('ПРАЙС_ЛИСТ'!F1333 <> 'ПРАЙС_ЛИСТ'!H1333, 'ПРАЙС_ЛИСТ'!F1333, "0") -> 10900 | E88: Замена слухового динамика | F88: 35 мин | H88: 90 дней | I88: https://maxmobiles.ru/dinamik-razgovornyy-verhniy-sluhovoy-zamena-iphone-16-pro-max/ | J88: На замену верхнего динамика, как и нижнего, предоставляется гарантия 90 дней. Процедура нужна, если Вы не слышите собеседника, звук верхнего динамика отсутствует
C89: 782129785272454108 | D89: =IF('ПРАЙС_ЛИСТ'!F1323 <> 'ПРАЙС_ЛИСТ'!H1323, 'ПРАЙС_ЛИСТ'!F1323, "0") -> 16100 | E89: Замена камеры | F89: 40 мин | H89: 90 дней | I89: https://maxmobiles.ru/kamera-osnovnaya-zadnyaya-zamena-iphone-16-pro-max/ | J89: Не работает камера iPhone? Приходите в сервис на диагностику. Выявим все неполадки и устраним в кратчайшие сроки
C90: 782129785272454173 | D90: =IF('ПРАЙС_ЛИСТ'!F1324 <> 'ПРАЙС_ЛИСТ'!H1324, 'ПРАЙС_ЛИСТ'!F1324, "0") -> 12000 | E90: Замена фронтальной камеры | F90: 35 мин | H90: 90 дней | I90: https://maxmobiles.ru/kamera-frontalnaya-perednyaya-zamena-iphone-16-pro-max/ | J90: Почему камера на Айфоне не работает? Проблема может быть в сбое ПО, механических повреждениях, замыкании
C91: 782129785272454123 | D91: =IF('ПРАЙС_ЛИСТ'!F1325 <> 'ПРАЙС_ЛИСТ'!H1325, 'ПРАЙС_ЛИСТ'!F1325, "0") -> 6500 | E91: Замена стекла камеры | F91: 35 мин | H91: 180 дней | I91: https://maxmobiles.ru/kamera-zamena-razbitogo-stekla-odno-iz-iphone-16-pro-max/ | J91: Повреждения камеры, проявляющиеся в виде отказа макросъемки и проблем с фокусировкой, обычно связаны с загрязнением подвижного объектива мелкими частицами. Если в камеру попала пыль или осколки стекла, это может нарушить её нормальную работу
C92: 782129785272454048 | D92: 0 | E92: Замена корпуса | F92: 60 мин | G92: уточняйте | H92: 180 дней | I92: https://maxmobiles.ru/korpus-kopiya-vysochayshego-kachestva-zamena-iphone-16-pro-max/ | J92: Для замены корпуса потребуется полная разборка аппарата. Не стоит поручать столь ответственную процедуру дилетантам. Сертифицированные инженеры Максмобайлс быстро и качественно выполнят все ремонтные работы и Ваш гаджет будет как новый
C93: 782129785272454215 | D93: 0 | E93: Ремонт кнопок | F93: 40 мин | G93: уточняйте | H93: 90 дней | I93: https://maxmobiles.ru/knopka-vklyucheniya-gromkosti-deystviya-vosstanovlenie-zamena-iphone-16-pro-max/ | J93: Регулировка громкости связана с другими элементами — кнопкой блокировки, переключателем вибро-режима, датчиком приближения и вспышкой. Эти детали объединяются верхним шлейфом, из-за чего при его повреждении может понадобиться комплексный ремонт
C94: 78212978527245362 | D94: =IF('ПРАЙС_ЛИСТ'!F9 <> 'ПРАЙС_ЛИСТ'!H9, 'ПРАЙС_ЛИСТ'!F9, "0") -> 1100 | E94: Прошивка | F94: 120 мин | I94: https://maxmobiles.ru/proshivka-bez-rezervnoy-kopii-iphone-11/ | J94: Только после оценки состояния Вашего девайса и выявления всех неполадок наш специалист сможет определить, нужна ли восстановительная прошивка или полная замена системного ПО
C95: 782129785272455008 | D95: ='ПРАЙС_ЛИСТ'!F1335 -> 7700 | E95: Ремонт материнской платы | F95: 180 мин | G95: цена от | H95: 90 дней | I95: https://maxmobiles.ru/remont-platy-iphone-16-pro-max/ | J95: Инженеры Максмобайлс проведут комплексную диагностику вашего iPhone, чтобы точно определить проблему. Мы используем современное оборудование для выявления неисправностей и восстановления работоспособности платы | L95: повреждения
C96: 782129785272454111 | D96: ='ПРАЙС_ЛИСТ'!F1326 -> 9700 | E96: Ремонт Face ID | F96: 180 мин | G96: цена от | H96: 90 дней | I96: https://maxmobiles.ru/face-id-vosstanovlenie-zamena-cena-ot-trebuetsya-diagnostika-iphone-16-pro-max/ | J96: Если повредилась камера TrueDepth, распознавание лица не происходит либо вовсе невозможно, требуется замена Face ID | L96: повреждения
B98: iPhone 16 Pro | C98: 782129785272454125 | D98: =IF('ПРАЙС_ЛИСТ'!F1285 <> 'ПРАЙС_ЛИСТ'!H1285, IF('ПРАЙС_ЛИСТ'!F1285 = 1, 0, 'ПРАЙС_ЛИСТ'!F1285), 0) -> 25000 | E98: Замена стекла | F98: 30 мин | H98: 90 дней | I98: https://maxmobiles.ru/displey-zamena-razbitogo-stekla-iphone-16-pro/ | J98: При поломке только стекла на Вашем аппарате, без ущерба для дисплея и сенсора, возможна замена только стекла. Мы выполняем эту процедуру с использованием профессионального оборудования, обеспечивая сохранение оригинального экрана
C99: 782129785272454160 | D99: 0 | E99: Замена дисплея (копия) | F99: 30 мин | G99: уточняйте | H99: 90 дней | I99: https://maxmobiles.ru/displey-kopiya-vysochayshego-kachestva-zamena-iphone-16-pro/ | J99: У нас есть несколько вариантов копий на любой кошелек! Разница заключается в цветопередаче и возможности использования функции True Tone
C100: 782129785272454105 | D100: {=MIN(IF('ПРАЙС_ЛИСТ'!F1277:F1281 <> 'ПРАЙС_ЛИСТ'!H1277:H1281, 'ПРАЙС_ЛИСТ'!F1277:F1281, ""))} -> 30000 | E100: Замена дисплея (оригинал) | F100: 30 мин | G100: цена от | H100: 90 дней | I100: https://maxmobiles.ru/displey-snyatyy-original-bez-privyazki-zamena-iphone-16-pro/ | J100: Хотите, чтобы всё работало как по-старому? Тогда оригинальный дисплей — ваш выбор. Сохранится цветопередача, Face ID и True Tone | L100: типа запчасти
C101: 782129785272454176 | D101: {=MIN(IF('ПРАЙС_ЛИСТ'!F1290:F1291 <> 'ПРАЙС_ЛИСТ'!H1290:H1291, 'ПРАЙС_ЛИСТ'!F1290:F1291, ""))} -> 8000 | E101: Замена заднего стекла | F101: 120 мин | G101: цена от | H101: 180 дней | I101: https://maxmobiles.ru/zadnyaya-kryshka-kopiya-vysochayshego-kachestva-zamena-stekla-iphone-16-pro/ | J101: Повреждённая задняя панель не только ухудшает внешний вид смартфона, но и может стать источником микроскопических осколков. В Макмобайлс мы применяем лазерную технологию для замены стекла, что обеспечивает безопасность и сохранность аппарата | L101: типа запчасти
C102: 782129785272454067 | D102: ='ПРАЙС_ЛИСТ'!F1299 -> 9000 | E102: Чистка после попадания воды | F102: 30 мин | G102: цена от | H102: 90 дней | I102: https://maxmobiles.ru/profilaktika-posle-vody-vosstanovlenie-cena-ot-trebuetsya-diagnostika-iphone-16-pro/ | J102: Apple заявляет, что их гаджеты надёжно защищены от воды, но это не так. При этом не сохраняется официальная гарантия. Протрите, отключите телефон и бегом в сервис! | L102: повреждения
C103: 782129785272454100 | D103: {=MIN(IF('ПРАЙС_ЛИСТ'!F1270:F1275 <> 'ПРАЙС_ЛИСТ'!H1270:H1275, 'ПРАЙС_ЛИСТ'!F1270:F1275, ""))} -> 12000 | E103: Замена аккумулятора | F103: 35 мин | G103: цена от | H103: 180 дней | I103: https://maxmobiles.ru/akkumulyator-original-zamena-iphone-16-pro/ | J103: Аккумулятор нетрудно заменить, однако проблема может быть не в нём. Приходите на диагностику, и мы разберёмся, что нужно менять: АКБ, контроллер питания или разъём зарядки | L103: типа запчасти
C104: 782129785272454083 | D104: =IF('ПРАЙС_ЛИСТ'!F1276 <> 'ПРАЙС_ЛИСТ'!H1276, 'ПРАЙС_ЛИСТ'!F1276, "0") -> 13000 | E104: Замена разъема зарядки | F104: 35 мин | H104: 90 дней | I104: https://maxmobiles.ru/razem-zaryadki-zamena-iphone-16-pro/ | J104: Почему iPhone не заряжается? Это может быть как проблема с батареей, контроллером питания или разъёмом зарядки. Если причина неочевидна, определить её поможет диагностика
C105: 782129785272454195 | D105: =IF('ПРАЙС_ЛИСТ'!F1297 <> 'ПРАЙС_ЛИСТ'!H1297, 'ПРАЙС_ЛИСТ'!F1297, "0") -> 12900 | E105: Замена микрофона | F105: 30 мин | H105: 90 дней | I105: https://maxmobiles.ru/mikrofon-zamena-odin-iz-iphone-16-pro/ | J105: Эту поломку легко обнаружить при разговоре или записи, но устранить её сможет только квалифицированный мастер, ведь нужно разбирать устройство и менять шлейфы
C106: 782129785272454172 | D106: =IF('ПРАЙС_ЛИСТ'!F1295 <> 'ПРАЙС_ЛИСТ'!H1295, 'ПРАЙС_ЛИСТ'!F1295, "0") -> 0 | E106: Замена динамика | F106: 35 мин | G106: уточняйте | H106: 90 дней | I106: https://maxmobiles.ru/dinamik-polifonicheskiy-nizhniy-gromkaya-svyaz-zamena-iphone-16-pro/ | J106: Динамик iPhone хрипит? Это могло произойти из-за воды, грязи или механического повреждения. Не рискуйте техникой — обращайтесь в наш сервис
...

Sheet БД_УСЛУГИ_РО
B2: МОДЕЛЬ | C2: ШТРИХКОД | D2: ТИП | E2: НАИМЕНОВАНИЕ УСЛУГИ | F2: ОПИСАНИЕ | G2: ЕДИНИЦА ИЗМЕРЕНИЯ | H2: ГРУППА | I2: ГАРАНТИЯ | J2: ГАРАНТИЯ ПЕРИОД | K2: ДЛИТЕЛЬНОСТЬ | L2: СЕБЕСТОИМОСТЬ | M2: СУММА ВОЗНАГРАЖДЕНИЯ | N2: % ВОЗНАГРАЖДЕНИЯ | O2: УСЛОВИЕ ВОЗНАГРАЖДЕНИЯ | P2: СТОИМОСТЬ УСЛУГИ
B3: РЕМОНТ APPLE "ОБЩИЙ НАБОР УСЛУГ" | E3: Данные - резервная копия / перенос (1 - 128 ГБ) | *цена за фактический объем данных | I3: 0 | P3: 1600
E4: Данные - резервная копия / перенос (128 - 256 ГБ) | *цена за фактический объем данных | I4: 0 | P4: 2200
E5: Данные - резервная копия / перенос (256 - 512 ГБ) | *цена за фактический объем данных | I5: 0 | P5: 4100
E6: Данные - резервная копия / перенос (512 ГБ - 1 ТБ) | *цена за фактический объем данных | I6: 0 | P6: 5100
E7: Данные - резервная копия / перенос (1 - 2 ТБ) | *цена за фактический объем данных | I7: 0 | P7: ?
E8: Приложения - установка | *цена за 1шт. | I8: 0 | P8: 500
E9: Программное обеспечение - установка до 3х программ | I9: 0 | P9: 600
E10: Программное обеспечение - установка более 3х программ | I10: 0 | P10: 1100
E11: Mac OS - установка | I11: 0 | P11: 1600
E12: Windows OS - установка | I12: 0 | P12: 1600
E13: Microsoft Office - установка | I13: 0 | P13: 1600
E14: Прошивка / программные работы - БЕЗ РЕЗЕРВНОЙ копии | I14: 0 | P14: 1100
E15: Сопровождение - ремонт устройства ** | I15: 0 | P15: 1
E16: Сопровождение - обмен устройства ** | I16: 0 | P16: 1
E17: Схематическая работа ** | I17: 0 | P17: 1
E18: Компонентный ремонт ** | I18: 90 | P18: 1
E19: Модульный ремонт ** | I19: 90 | P19: 1
... E22: Диагностика - составление и печать акта | I22: 0 | P22: 1000
B24: iPhone ШАБЛОН | E24: [i___-DGN] iPhone ___ Диагностика (с пайкой компонентов) | *бесплатно при дальнейшем ремонте | I24: 0
E25: [i___-WTR1] iPhone ___ Пылевлагозащита (этап 1) - восстановление | I25: 0 | N25: 30 | O25: приб.
E26: [i___-WTR2] iPhone ___ Пылевлагозащита (этап 2) - восстановление | I26: 0 | N26: 30 | O26: приб.
E27: [i___-CLNB] iPhone ___ Чистка сеток динамиков и разъема зарядки БЕЗ РАЗБОРА | I27: 0
E28: [i___-CLN] iPhone ___ Чистка сеток динамиков и разъема зарядки С РАЗБОРОМ | I28: 0
E29: [i___-BAT] iPhone ___ Аккумулятор - замена | I29: 180
E30: [i___-BATE] iPhone ___ Аккумулятор - устранение уведомления о замене | I30: 180
E31: [i___-CHG] iPhone ___ Разъем зарядки - замена | I31: 90
E32: [i___-DIS] iPhone ___ Дисплей - замена | I32: 90
E33: [i___-DISE] iPhone ___ Дисплей - устранение уведомления о замене | I33: 90
E34: [i___-DGL] iPhone ___ Дисплей - замена (переклей) разбитого стекла | I34: 90 | N34: 20 | O34: приб.
E35: [i___-DGT] iPhone ___ Дисплей - замена (переклей) разбитого стекла с тачскрином | I35: 90 | N35: 20 | O35: приб.
E36: [i___-CAMR] iPhone ___ Камера основная - замена | I36: 90
E37: [i___-CAMF] iPhone ___ Камера фронтальная - замена | I37: 90
E38: [i___-CGL] iPhone ___ Камера - замена разбитого стекла | *цена за 1шт. | I38: 180 | N38: 50 | O38: приб.
E39: [i___-FID] iPhone ___ Face ID - восстановление | *требуется диагностика | I39: 90
E40: [i___-BGL] iPhone ___ Крышка (заднее стекло) - замена | I40: 180
E41: [i___-HSG] iPhone ___ Корпус - замена | I41: 180
E42: [i___-MID] iPhone ___ Корпус (средняя часть) - замена | I42: 180
E43: [i___-HOM] iPhone ___ Кнопка Home - восстановление / замена | I43: 90
E44: [i___-BTN] iPhone ___ Кнопки - восстановление / замена | *требуется диагностика | I44: 90
E45: [i___-SPK] iPhone ___ Динамик полифонический (нижний, громкая связь) - замена | I45: 90
E46: [i___-EAR] iPhone ___ Динамик разговорный (верхний, слуховой) - замена | I46: 90
E47: [i___-MIC] iPhone ___ Микрофон - замена (один из..) | *требуется диагностика | I47: 90
E48: [i___-BRD] iPhone ___ Ремонт платы - восстановление / замена | *требуется диагностика | I48: 90
E49: [i___-BRDS] iPhone ___ Ремонт платы - распайка половинок | I49: 90
E50: [i___-LIQ] iPhone ___ Профилактика после воды - восстановление | *требуется диагностика | I50: 90
... E52: [i___-WFB] iPhone ___ WiFi / Bluetooth - восстановление беспроводных сетей | *требуется диагностика | I52: 90
D55: Услуга | E55: Прошивка | G55: pcs | H55: Прочие работы и услуги | I55: 0 | P55: 1100
B56: iPhone 5 / 5C / 5S / SE 2016 | C56: i5/5C/5S/SE1-DGN | D56: Работа | E56: [i5/5C/5S/SE1-DGN] iPhone 5 / 5C / 5S / SE1 Диагностика (с пайкой компонентов) | *бесплатно при дальнейшем ремонте | G56: pcs | H56: Ремонт iPhone > iPhone 5 / 5C / 5S / SE 2016 | I56: 0 | J56: дн | P56: 1
C57: i5/5C/5S/SE1-CLNB | D57: Работа | E57: [i5/5C/5S/SE1-CLNB] iPhone 5 / 5C / 5S / SE1 Чистка сеток динамиков и разъема зарядки БЕЗ РАЗБОРА | G57: pcs | H57: Ремонт iPhone > iPhone 5 / 5C / 5S / SE 2016 | I57: 0 | J57: дн | P57: 400
C58: i5/5C/5S/SE1-CLN | D58: Работа | E58: [i5/5C/5S/SE1-CLN] iPhone 5 / 5C / 5S / SE1 Чистка сеток динамиков и разъема зарядки С РАЗБОРОМ | G58: pcs | H58: Ремонт iPhone > iPhone 5 / 5C / 5S / SE 2016 | I58: 0 | J58: дн | P58: 900
C59: i5/5C/5S/SE1-BAT | D59: Работа | E59: [i5/5C/5S/SE1-BAT] iPhone 5 / 5C / 5S / SE1 Аккумулятор - замена | G59: pcs | H59: Ремонт iPhone > iPhone 5 / 5C / 5S / SE 2016 | I59: 180 | J59: дн | P59: 700
C60: i5/5C/5S/SE1-CHG | D60: Работа | E60: [i5/5C/5S/SE1-CHG] iPhone 5 / 5C / 5S / SE1 Разъем зарядки - замена | G60: pcs | H60: Ремонт iPhone > iPhone 5 / 5C / 5S / SE 2016 | I60: 90 | J60: дн | P60: 700
C61: i5/5C/5S/SE1-DIS | D61: Работа | E61: [i5/5C/5S/SE1-DIS] iPhone 5 / 5C / 5S / SE1 Дисплей - замена | G61: pcs | H61: Ремонт iPhone > iPhone 5 / 5C / 5S / SE 2016 | I61: 90 | J61: дн | P61: 800
C62: i5/5C/5S/SE1-CAMR | D62: Работа | E62: [i5/5C/5S/SE1-CAMR] iPhone 5 / 5C / 5S / SE1 Камера основная - замена | G62: pcs | H62: Ремонт iPhone > iPhone 5 / 5C / 5S / SE 2016 | I62: 90 | J62: дн | P62: 700
C63: i5/5C/5S/SE1-CAMF | D63: Работа | E63: [i5/5C/5S/SE1-CAMF] iPhone 5 / 5C / 5S / SE1 Камера фронтальная - замена | G63: pcs | H63: Ремонт iPhone > iPhone 5 / 5C / 5S / SE 2016 | I63: 90 | J63: дн | P63: 700
C64: i5/5C/5S/SE1-CGL | D64: Работа | E64: [i5/5C/5S/SE1-CGL] iPhone 5 / 5C / 5S / SE1 Камера - замена разбитого стекла | *цена за 1шт. | G64: pcs | H64: Ремонт iPhone > iPhone 5 / 5C / 5S / SE 2016 | I64: 180 | J64: дн | N64: 50 | O64: приб. | P64: 500
C65: i5/5C/5S/SE1-HSG | D65: Работа | E65: [i5/5C/5S/SE1-HSG] iPhone 5 / 5C / 5S / SE1 Корпус - замена | G65: pcs | H65: Ремонт iPhone > iPhone 5 / 5C / 5S / SE 2016 | I65: 180 | J65: дн | P65: 800
C66: i5/5C/5S/SE1-HOM | D66: Работа | E66: [i5/5C/5S/SE1-HOM] iPhone 5 / 5C / 5S / SE1 Кнопка Home - восстановление / замена | G66: pcs | H66: Ремонт iPhone > iPhone 5 / 5C / 5S / SE 2016 | I66: 90 | J66: дн | P66: 700
C67: i5/5C/5S/SE1-BTN | D67: Работа | E67: [i5/5C/5S/SE1-BTN] iPhone 5 / 5C / 5S / SE1 Кнопки - восстановление / замена | *требуется диагностика | G67: pcs | H67: Ремонт iPhone > iPhone 5 / 5C / 5S / SE 2016 | I67: 90 | J67: дн | P67: 700
C68: i5/5C/5S/SE1-SPK | D68: Работа | E68: [i5/5C/5S/SE1-SPK] iPhone 5 / 5C / 5S / SE1 Динамик полифонический (нижний, громкая связь) - замена | G68: pcs | H68: Ремонт iPhone > iPhone 5 / 5C / 5S / SE 2016 | I68: 90 | J68: дн | P68: 800
C69: i5/5C/5S/SE1-EAR | D69: Работа | E69: [i5/5C/5S/SE1-EAR] iPhone 5 / 5C / 5S / SE1 Динамик разговорный (верхний, слуховой) - замена | G69: pcs | H69: Ремонт iPhone > iPhone 5 / 5C / 5S / SE 2016 | I69: 90 | J69: дн | P69: 800
C70: i5/5C/5S/SE1-MIC | D70: Работа | E70: [i5/5C/5S/SE1-MIC] iPhone 5 / 5C / 5S / SE1 Микрофон - замена (один из..) | *требуется диагностика | G70: pcs | H70: Ремонт iPhone > iPhone 5 / 5C / 5S / SE 2016 | I70: 90 | J70: дн | P70: 1000
C71: i5/5C/5S/SE1-BRD | D71: Работа | E71: [i5/5C/5S/SE1-BRD] iPhone 5 / 5C / 5S / SE1 Ремонт платы - восстановление / замена | *требуется диагностика | G71: pcs | H71: Ремонт iPhone > iPhone 5 / 5C / 5S / SE 2016 | I71: 90 | J71: дн | P71: 1600
C72: i5/5C/5S/SE1-LIQ | D72: Работа | E72: [i5/5C/5S/SE1-LIQ] iPhone 5 / 5C / 5S / SE1 Профилактика после воды - восстановление | *требуется диагностика | G72: pcs | H72: Ремонт iPhone > iPhone 5 / 5C / 5S / SE 2016 | I72: 90 | J72: дн | P72: 2000
C73: i5/5C/5S/SE1-MDM | D73: Работа | E73: [i5/5C/5S/SE1-MDM] iPhone 5 / 5C / 5S / SE1 Модем - восстановление GSM сети | *требуется диагностика | G73: pcs | H73: Ремонт iPhone > iPhone 5 / 5C / 5S / SE 2016 | I73: 90 | J73: дн | P73: 2000
C74: i5/5C/5S/SE1-WFB | D74: Работа | E74: [i5/5C/5S/SE1-WFB] iPhone 5 / 5C / 5S / SE1 WiFi / Bluetooth - восстановление беспроводных сетей | *требуется диагностика | G74: pcs | H74: Ремонт iPhone > iPhone 5 / 5C / 5S / SE 2016 | I74: 90 | J74: дн | P74: 900
B75: iPhone 6 | C75: i6-DGN | D75: Работа | E75: [i6-DGN] iPhone 6 Диагностика (с пайкой компонентов) | *бесплатно при дальнейшем ремонте | G75: pcs | H75: Ремонт iPhone > iPhone 6 | I75: 0 | J75: дн | P75: 1
C76: i6-CLNB | D76: Работа | E76: [i6-CLNB] iPhone 6 Чистка сеток динамиков и разъема зарядки БЕЗ РАЗБОРА | G76: pcs | H76: Ремонт iPhone > iPhone 6 | I76: 0 | J76: дн | P76: 400
C77: i6-CLN | D77: Работа | E77: [i6-CLN] iPhone 6 Чистка сеток динамиков и разъема зарядки С РАЗБОРОМ | G77: pcs | H77: Ремонт iPhone > iPhone 6 | I77: 0 | J77: дн | P77: 1000
C78: i6-BAT | D78: Работа | E78: [i6-BAT] iPhone 6 Аккумулятор - замена | G78: pcs | H78: Ремонт iPhone > iPhone 6 | I78: 180 | J78: дн | P78: 800
C79: i6-CHG | D79: Работа | E79: [i6-CHG] iPhone 6 Разъем зарядки - замена | G79: pcs | H79: Ремонт iPhone > iPhone 6 | I79: 90 | J79: дн | P79: 900
C80: i6-DIS | D80: Работа | E80: [i6-DIS] iPhone 6 Дисплей - замена | G80: pcs | H80: Ремонт iPhone > iPhone 6 | I80: 90 | J80: дн | P80: 900
C81: i6-DGL | D81: Работа | E81: [i6-DGL] iPhone 6 Дисплей - замена (переклей) разбитого стекла | G81: pcs | H81: Ремонт iPhone > iPhone 6 | I81: 90 | J81: дн | N81: 20 | O81: приб. | P81: 2000
C82: i6-CAMR | D82: Работа | E82: [i6-CAMR] iPhone 6 Камера основная - замена | G82: pcs | H82: Ремонт iPhone > iPhone 6 | I82: 90 | J82: дн | P82: 800
C83: i6-CAMF | D83: Работа | E83: [i6-CAMF] iPhone 6 Камера фронтальная - замена | G83: pcs | H83: Ремонт iPhone > iPhone 6 | I83: 90 | J83: дн | P83: 900
C84: i6-CGL | D84: Работа | E84: [i6-CGL] iPhone 6 Камера - замена разбитого стекла | *цена за 1шт. | G84: pcs | H84: Ремонт iPhone > iPhone 6 | I84: 180 | J84: дн | N84: 50 | O84: приб. | P84: 800
C85: i6-HSG | D85: Работа | E85: [i6-HSG] iPhone 6 Корпус - замена | G85: pcs | H85: Ремонт iPhone > iPhone 6 | I85: 180 | J85: дн | P85: 800
C86: i6-HOM | D86: Работа | E86: [i6-HOM] iPhone 6 Кнопка Home - восстановление / замена | G86: pcs | H86: Ремонт iPhone > iPhone 6 | I86: 90 | J86: дн | P86: 900
C87: i6-BTN | D87: Работа | E87: [i6-BTN] iPhone 6 Кнопки - восстановление / замена | *требуется диагностика | G87: pcs | H87: Ремонт iPhone > iPhone 6 | I87: 90 | J87: дн | P87: 900
C88: i6-SPK | D88: Работа | E88: [i6-SPK] iPhone 6 Динамик полифонический (нижний, громкая связь) - замена | G88: pcs | H88: Ремонт iPhone > iPhone 6 | I88: 90 | J88: дн | P88: 1000
C89: i6-EAR | D89: Работа | E89: [i6-EAR] iPhone 6 Динамик разговорный (верхний, слуховой) - замена | G89: pcs | H89: Ремонт iPhone > iPhone 6 | I89: 90 | J89: дн | P89: 1000
C90: i6-MIC | D90: Работа | E90: [i6-MIC] iPhone 6 Микрофон - замена (один из..) | *требуется диагностика | G90: pcs | H90: Ремонт iPhone > iPhone 6 | I90: 90 | J90: дн | P90: 1200
C91: i6-BRD | D91: Работа | E91: [i6-BRD] iPhone 6 Ремонт платы - восстановление / замена | *требуется диагностика | G91: pcs | H91: Ремонт iPhone > iPhone 6 | I91: 90 | J91: дн | P91: 1800
C92: i6-LIQ | D92: Работа | E92: [i6-LIQ] iPhone 6 Профилактика после воды - восстановление | *требуется диагностика | G92: pcs | H92: Ремонт iPhone > iPhone 6 | I92: 90 | J92: дн | P92: 2000
C93: i6-MDM | D93: Работа | E93: [i6-MDM] iPhone 6 Модем - восстановление GSM сети | *требуется диагностика | G93: pcs | H93: Ремонт iPhone > iPhone 6 | I93: 90 | J93: дн | P93: 2000
C94: i6-WFB | D94: Работа | E94: [i6-WFB] iPhone 6 WiFi / Bluetooth - восстановление беспроводных сетей | *требуется диагностика | G94: pcs | H94: Ремонт iPhone > iPhone 6 | I94: 90 | J94: дн | P94: 1000
B95: iPhone 6 Plus | C95: i6PL-DGN | D95: Работа | E95: [i6PL-DGN] iPhone 6 Plus Диагностика (с пайкой компонентов) | *бесплатно при дальнейшем ремонте | G95: pcs | H95: Ремонт iPhone > iPhone 6 Plus | I95: 0 | J95: дн | P95: 1
C96: i6PL-CLNB | D96: Работа | E96: [i6PL-CLNB] iPhone 6 Plus Чистка сеток динамиков и разъема зарядки БЕЗ РАЗБОРА | G96: pcs | H96: Ремонт iPhone > iPhone 6 Plus | I96: 0 | J96: дн | P96: 400
C97: i6PL-CLN | D97: Работа | E97: [i6PL-CLN] iPhone 6 Plus Чистка сеток динамиков и разъема зарядки С РАЗБОРОМ | G97: pcs | H97: Ремонт iPhone > iPhone 6 Plus | I97: 0 | J97: дн | P97: 1000
C98: i6PL-BAT | D98: Работа | E98: [i6PL-BAT] iPhone 6 Plus Аккумулятор - замена | G98: pcs | H98: Ремонт iPhone > iPhone 6 Plus | I98: 180 | J98: дн | P98: 800
C99: i6PL-CHG | D99: Работа | E99: [i6PL-CHG] iPhone 6 Plus Разъем зарядки - замена | G99: pcs | H99: Ремонт iPhone > iPhone 6 Plus | I99: 90 | J99: дн | P99: 900
C100: i6PL-DIS | D100: Работа | E100: [i6PL-DIS] iPhone 6 Plus Дисплей - замена | G100: pcs | H100: Ремонт iPhone > iPhone 6 Plus | I100: 90 | J100: дн | P100: 900
C101: i6PL-DGL | D101: Работа | E101: [i6PL-DGL] iPhone 6 Plus Дисплей - замена (переклей) разбитого стекла | G101: pcs | H101: Ремонт iPhone > iPhone 6 Plus | I101: 90 | J101: дн | N101: 20 | O101: приб. | P101: 2000
C102: i6PL-CAMR | D102: Работа | E102: [i6PL-CAMR] iPhone 6 Plus Камера основная - замена | G102: pcs | H102: Ремонт iPhone > iPhone 6 Plus | I102: 90 | J102: дн | P102: 800
C103: i6PL-CAMF | D103: Работа | E103: [i6PL-CAMF] iPhone 6 Plus Камера фронтальная - замена | G103: pcs | H103: Ремонт iPhone > iPhone 6 Plus | I103: 90 | J103: дн | P103: 900
C104: i6PL-CGL | D104: Работа | E104: [i6PL-CGL] iPhone 6 Plus Камера - замена разбитого стекла | *цена за 1шт. | G104: pcs | H104: Ремонт iPhone > iPhone 6 Plus | I104: 180 | J104: дн | N104: 50 | O104: приб. | P104: 800
C105: i6PL-HSG | D105: Работа | E105: [i6PL-HSG] iPhone 6 Plus Корпус - замена | G105: pcs | H105: Ремонт iPhone > iPhone 6 Plus | I105: 180 | J105: дн | P105: 800
C106: i6PL-HOM | D106: Работа | E106: [i6PL-HOM] iPhone 6 Plus Кнопка Home - восстановление / замена | G106: pcs | H106: Ремонт iPhone > iPhone 6 Plus | I106: 90 | J106: дн | P106: 900
C107: i6PL-BTN | D107: Работа | E107: [i6PL-BTN] iPhone 6 Plus Кнопки - восстановление / замена | *требуется диагностика | G107: pcs | H107: Ремонт iPhone > iPhone 6 Plus | I107: 90 | J107: дн | P107: 900
...

Sheet БД_УСЛУГИ_МС
B2: МОДЕЛЬ | C2: ГАРАНТИЯ, дн. | D2: КОД УСЛУГИ | E2: УСЛУГА | F2: ЦЕНА
B3: iPhone | C3: 0 | D3: 78212978527245361 | E3: Данные - резервная копия / перенос (1 - 128 ГБ) | *цена за фактический объем данных | F3: ='ПРАЙС_ЛИСТ'!F3 -> 1600 | H3: 1000 - цена "от" | *требуется диагностика
C4: 0 | E4: Данные - резервная копия / перенос (129 - 256 ГБ) | *цена за фактический объем данных | F4: ='ПРАЙС_ЛИСТ'!F4 -> 2200 | H4: 1000 - фиксированная цена
C5: 0 | E5: Данные - резервная копия / перенос (257 - 512 ГБ) | *цена за фактический объем данных | F5: ='ПРАЙС_ЛИСТ'!F5 -> 4100 | H5: 1000 - цена "за работу" - уточнить стоимость и наличие запчасти у поставщиков!
C6: 0 | E6: Данные - резервная копия / перенос (513 - 1024 ГБ) | *цена за фактический объем данных | F6: ='ПРАЙС_ЛИСТ'!F6 -> 5100 | H6: есть дорогой закуп запчасти - предложить "вилку" из наличия / под заказ
C7: 0 | E7: Данные - резервная копия / перенос (1025 - 2056 ГБ) | *цена за фактический объем данных | F7: ='ПРАЙС_ЛИСТ'!F7 -> ?
C8: 0 | D8: 78212978527245363 | E8: Приложения - установка | *цена за 1шт. / 2-5 = скидка 25% / более 5 = скидка 30% | F8: ='ПРАЙС_ЛИСТ'!F8 -> 500
C9: 0 | D9: 78212978527245362 | E9: Прошивка iPhone - БЕЗ РЕЗЕРВНОЙ копии | F9: ='ПРАЙС_ЛИСТ'!F9 -> 1100
C10: 0 | E10: Диагностика (без пайки компонентов) | F10: ='ПРАЙС_ЛИСТ'!F10 -> 0
C11: 0 | E11: Диагностика - составление и печать акта | F11: ='ПРАЙС_ЛИСТ'!F11 -> 1000
B13: iPhone ШАБЛОН | C13: 0 | E13: iPhone ШАБЛОН Диагностика (с пайкой компонентов) | *бесплатно при дальнейшем ремонте | F13: -
B14: iPhone ШАБЛОН | C14: 0 | E14: iPhone ШАБЛОН Чистка сеток динамиков и разъема зарядки БЕЗ РАЗБОРА (минимальная) | F14: -
B15: iPhone ШАБЛОН | C15: 0 | E15: iPhone ШАБЛОН Чистка сеток динамиков и разъема зарядки С РАЗБОРОМ (максимальная) | F15: -
B16: iPhone ШАБЛОН | C16: 180 | E16: iPhone ШАБЛОН Аккумулятор - замена (минимальная) | F16: -
B17: iPhone ШАБЛОН | C17: 180 | E17: iPhone ШАБЛОН Аккумулятор - замена (максимальная) | F17: -
B18: iPhone ШАБЛОН | C18: 90 | E18: iPhone ШАБЛОН Разъем зарядки - замена | F18: -
B19: iPhone ШАБЛОН | C19: 90 | E19: iPhone ШАБЛОН Дисплей - замена (минимальная) | F19: -
B20: iPhone ШАБЛОН | C20: 90 | E20: iPhone ШАБЛОН Дисплей - замена (максимальная) | F20: -
B21: iPhone ШАБЛОН | C21: 90 | E21: iPhone ШАБЛОН Дисплей - замена разбитого стекла (минимальная) | F21: -
B22: iPhone ШАБЛОН | C22: 90 | E22: iPhone ШАБЛОН Дисплей - замена разбитого стекла с тачскрином (максимальная) | F22: -
B23: iPhone ШАБЛОН | C23: 90 | E23: iPhone ШАБЛОН Камера основная - замена | F23: -
B24: iPhone ШАБЛОН | C24: 90 | E24: iPhone ШАБЛОН Камера фронтальная - замена | F24: -
... B39: iPhone ШАБЛОН | C39: 90 | E39: iPhone ШАБЛОН WiFi / Bluetooth - восстановление беспроводных сетей | *цена от, требуется диагностика | F39: -
B41: iPhone 5 | C41: 0 | E41: iPhone 5 Диагностика (с пайкой компонентов) | *бесплатно при дальнейшем ремонте | F41: 0
B42: iPhone 5 | C42: 0 | D42: 67567465236906 | E42: iPhone 5 Чистка сеток динамиков и разъема зарядки БЕЗ РАЗБОРА (минимальная) | F42: ='ПРАЙС_ЛИСТ'!F57 -> 400
B43: iPhone 5 | C43: 0 | E43: iPhone 5 Чистка сеток динамиков и разъема зарядки С РАЗБОРОМ (максимальная) | F43: ='ПРАЙС_ЛИСТ'!F58 -> 900
B44: iPhone 5 | C44: 180 | D44: 67567465236905 | E44: iPhone 5 Аккумулятор - замена | F44: ='ПРАЙС_ЛИСТ'!F59 -> 1200
B45: iPhone 5 | C45: 90 | D45: 67567465236921 | E45: iPhone 5 Разъем зарядки - замена | F45: ='ПРАЙС_ЛИСТ'!F60 -> 750
B46: iPhone 5 | C46: 90 | D46: 67567465236911 | E46: iPhone 5 Дисплей - замена | F46: ='ПРАЙС_ЛИСТ'!F63 -> 800 | H46: только аналог
B47: iPhone 5 | C47: 90 | D47: 67567465236916 | E47: iPhone 5 Камера основная - замена | F47: ='ПРАЙС_ЛИСТ'!F64 -> 750
B48: iPhone 5 | C48: 90 | D48: 67567465236917 | E48: iPhone 5 Камера фронтальная - замена | F48: ='ПРАЙС_ЛИСТ'!F65 -> 750
B49: iPhone 5 | C49: 90 | D49: 67567465236915 | E49: iPhone 5 Камера - замена разбитого стекла | *цена за 1шт. | F49: =IF('ПРАЙС_ЛИСТ'!F66 = G49, 0, 'ПРАЙС_ЛИСТ'!F66) -> 0 | G49: ='БД_УСЛУГИ_РО'!P64 -> 500
B50: iPhone 5 | C50: 180 | D50: 67567465236918 | E50: iPhone 5 Корпус - замена | F50: =IF('ПРАЙС_ЛИСТ'!F67 = G50, 0, 'ПРАЙС_ЛИСТ'!F67) -> 0 | G50: ='БД_УСЛУГИ_РО'!P65 -> 800
B51: iPhone 5 | C51: 90 | D51: 67567465236922 | E51: iPhone 5 Кнопка HOME - восстановление / замена | F51: =IF('ПРАЙС_ЛИСТ'!F68 = G51, 0, 'ПРАЙС_ЛИСТ'!F68) -> 0 | G51: ='БД_УСЛУГИ_РО'!P66 -> 700
B52: iPhone 5 | C52: 90 | D52: 67567465236929 | E52: iPhone 5 Кнопки - восстановление / замена | *цена от, требуется диагностика | F52: ='ПРАЙС_ЛИСТ'!F69 -> 700
B53: iPhone 5 | C53: 90 | D53: 67567465236908 | E53: iPhone 5 Динамик полифонический - замена | F53: ='ПРАЙС_ЛИСТ'!F70 -> 850
B54: iPhone 5 | C54: 90 | D54: 67567465236909 | E54: iPhone 5 Динамик слуховой - замена | F54: ='ПРАЙС_ЛИСТ'!F71 -> 850
B55: iPhone 5 | C55: 90 | D55: 67567465236910 | E55: iPhone 5 Микрофон - замена (один из..) | *требуется диагностика | F55: ='ПРАЙС_ЛИСТ'!F72 -> 1050
B56: iPhone 5 | C56: 90 | D56: 782129785272455013 | E56: iPhone 5 Ремонт платы - восстановление / замена | *цена от, требуется диагностика | F56: ='ПРАЙС_ЛИСТ'!F73 -> 1600
B57: iPhone 5 | C57: 90 | D57: 67567465236920 | E57: iPhone 5 Профилактика после воды - восстановление | *цена от, требуется диагностика | F57: ='ПРАЙС_ЛИСТ'!F74 -> 2000
B58: iPhone 5 | C58: 90 | D58: 67567465236941 | E58: iPhone 5 Модем - восстановление GSM сети | *цена от, требуется диагностика | F58: ='ПРАЙС_ЛИСТ'!F75 -> 2000
B59: iPhone 5 | C59: 90 | D59: 67567465236940 | E59: iPhone 5 WiFi / Bluetooth - восстановление беспроводных сетей | *цена от, требуется диагностика | F59: ='ПРАЙС_ЛИСТ'!F76 -> 900
B61: iPhone 5C | C61: 0 | E61: iPhone 5C Диагностика (с пайкой компонентов) | *бесплатно при дальнейшем ремонте | F61: 0
B62: iPhone 5C | C62: 0 | D62: 7821297852724554966 | E62: iPhone 5C Чистка сеток динамиков и разъема зарядки БЕЗ РАЗБОРА (минимальная) | F62: ='ПРАЙС_ЛИСТ'!F79 -> 400
B63: iPhone 5C | C63: 0 | E63: iPhone 5C Чистка сеток динамиков и разъема зарядки С РАЗБОРОМ (максимальная) | K63: Чистка динамика iPhone
B64: iPhone 5C | C64: 180 | D64: 7821297852724554968 | E64: iPhone 5C Аккумулятор - замена | F64: ='ПРАЙС_ЛИСТ'!F81 -> 1200 | K64: Замена аккумулятора iPhone
B65: iPhone 5C | C65: 90 | D65: 7821297852724554967 | E65: iPhone 5C Разъем зарядки - замена | F65: ='ПРАЙС_ЛИСТ'!F82 -> 750 | K65: Замена разъема зарядки iPhone
B66: iPhone 5C | C66: 90 | D66: 7821297852724554971 | E66: iPhone 5C Дисплей - замена | F66: ='ПРАЙС_ЛИСТ'!F84 -> 850 | H66: только восстановленный оригинал | K66: Замена дисплея iPhone
B67: iPhone 5C | C67: 90 | D67: 7821297852724554960 | E67: iPhone 5C Камера основная - замена | F67: ='ПРАЙС_ЛИСТ'!F86 -> 750 | K67: Замена основной камеры iPhone
B68: iPhone 5C | C68: 90 | D68: 7821297852724554974 | E68: iPhone 5C Камера фронтальная - замена | F68: ='ПРАЙС_ЛИСТ'!F87 -> 750 | K68: Замена фронтальной камеры iPhone
B69: iPhone 5C | C69: 90 | D69: 7821297852724554962 | E69: iPhone 5C Камера - замена разбитого стекла | *цена за 1шт. | F69: =IF('ПРАЙС_ЛИСТ'!F88 = G69, 0, 'ПРАЙС_ЛИСТ'!F88) -> 0 | G69: ='БД_УСЛУГИ_РО'!P64 -> 500 | K69: Замена стекла камеры iPhone
B70: iPhone 5C | C70: 180 | D70: 7821297852724554961 | E70: iPhone 5C Корпус - замена | F70: =IF('ПРАЙС_ЛИСТ'!F89 = G70, 0, 'ПРАЙС_ЛИСТ'!F89) -> 0 | G70: ='БД_УСЛУГИ_РО'!P65 -> 800 | K70: Замена корпуса iPhone
B71: iPhone 5C | C71: 90 | D71: 7821297852724554973 | E71: iPhone 5C Кнопка HOME - восстановление / замена | F71: =IF('ПРАЙС_ЛИСТ'!F90 = G71, 0, 'ПРАЙС_ЛИСТ'!F90) -> 0 | G71: ='БД_УСЛУГИ_РО'!P66 -> 700 | K71: Замена кнопки Home iPhone
B72: iPhone 5C | C72: 90 | D72: 7821297852724554964 | E72: iPhone 5C Кнопки - восстановление / замена | *цена от, требуется диагностика | F72: ='ПРАЙС_ЛИСТ'!F91 -> 700 | K72: Замена кнопок iPhone
B73: iPhone 5C | C73: 90 | D73: 7821297852724554976 | E73: iPhone 5C Динамик полифонический - замена | F73: =IF('ПРАЙС_ЛИСТ'!F92 = G73, 0, 'ПРАЙС_ЛИСТ'!F92) -> 0 | G73: ='БД_УСЛУГИ_РО'!P68 -> 800 | K73: Замена динамика громкой связи iPhone
B74: iPhone 5C | C74: 90 | D74: 7821297852724554963 | E74: iPhone 5C Динамик слуховой - замена | F74: ='ПРАЙС_ЛИСТ'!F93 -> 850 | K74: Замена динамика iPhone
B75: iPhone 5C | C75: 90 | D75: 7821297852724554975 | E75: iPhone 5C Микрофон - замена (один из..) | *требуется диагностика | F75: ='ПРАЙС_ЛИСТ'!F94 -> 1050 | K75: Замена микрофона iPhone
B76: iPhone 5C | C76: 90 | D76: 7821297852724554969 | E76: iPhone 5C Ремонт платы - восстановление / замена | *цена от, требуется диагностика | F76: ='ПРАЙС_ЛИСТ'!F95 -> 1600 | K76: Ремонт платы iPhone
B77: iPhone 5C | C77: 90 | D77: 7821297852724554972 | E77: iPhone 5C Профилактика после воды - восстановление | *цена от, требуется диагностика | F77: ='ПРАЙС_ЛИСТ'!F96 -> 2000 | K77: Профилактика после воды iPhone
B78: iPhone 5C | C78: 90 | D78: 7821297852724554965 | E78: iPhone 5C Модем - восстановление GSM сети | *цена от, требуется диагностика | F78: ='ПРАЙС_ЛИСТ'!F97 -> 2000 | K78: Модем - восстановление GSM сети iPhone
B79: iPhone 5C | C79: 90 | D79: 7821297852724554970 | E79: iPhone 5C WiFi / Bluetooth - восстановление беспроводных сетей | *цена от, требуется диагностика | F79: ='ПРАЙС_ЛИСТ'!F98 -> 900 | K79: WiFi / Bluetooth - восстановление беспроводных сетей iPhone
B81: iPhone 5S | C81: 0 | E81: iPhone 5S Диагностика (с пайкой компонентов) | *бесплатно при дальнейшем ремонте | F81: 0
B82: iPhone 5S | C82: 0 | E82: iPhone 5S Чистка сеток динамиков и разъема зарядки БЕЗ РАЗБОРА (минимальная) | F82: ='ПРАЙС_ЛИСТ'!F101 -> 400
B83: iPhone 5S | C83: 0 | E83: iPhone 5S Чистка сеток динамиков и разъема зарядки С РАЗБОРОМ (максимальная) | F83: ='ПРАЙС_ЛИСТ'!F102 -> 900
B84: iPhone 5S | C84: 180 | E84: iPhone 5S Аккумулятор - замена | F84: ='ПРАЙС_ЛИСТ'!F103 -> 1200
B85: iPhone 5S | C85: 90 | E85: iPhone 5S Разъем зарядки - замена | F85: ='ПРАЙС_ЛИСТ'!F104 -> 750
B86: iPhone 5S | C86: 90 | E86: iPhone 5S Дисплей - замена (минимальная) | F86: =IFERROR(__xludf.DUMMYFUNCTION("MIN(FILTER('ПРАЙС_ЛИСТ'!F105:F107, 'ПРАЙС_ЛИСТ'!F105:F107 <> 'ПРАЙС_ЛИСТ'!H105:H107))"),1850.0) -> 1850
B87: iPhone 5S | C87: 90 | E87: iPhone 5S Дисплей - замена (максимальная) | F87: =IFERROR(__xludf.DUMMYFUNCTION("MAX(FILTER('ПРАЙС_ЛИСТ'!F105:F107, 'ПРАЙС_ЛИСТ'!F105:F107 <> 'ПРАЙС_ЛИСТ'!H105:H107))"),2000.0) -> 2000
B88: iPhone 5S | C88: 90 | E88: iPhone 5S Камера основная - замена | F88: ='ПРАЙС_ЛИСТ'!F108 -> 750
B89: iPhone 5S | C89: 90 | E89: iPhone 5S Камера фронтальная - замена | F89: ='ПРАЙС_ЛИСТ'!F109 -> 750
B90: iPhone 5S | C90: 90 | E90: iPhone 5S Камера - замена разбитого стекла | *цена за 1шт. | F90: =IF('ПРАЙС_ЛИСТ'!F110 = G90, 0, 'ПРАЙС_ЛИСТ'!F110) -> 0 | G90: ='БД_УСЛУГИ_РО'!P64 -> 500
B91: iPhone 5S | C91: 180 | E91: iPhone 5S Корпус - замена | F91: =IF('ПРАЙС_ЛИСТ'!F111 = G91, 0, 'ПРАЙС_ЛИСТ'!F111) -> 0 | G91: ='БД_УСЛУГИ_РО'!P65 -> 800
B92: iPhone 5S | C92: 90 | E92: iPhone 5S Кнопка HOME - восстановление / замена | F92: =IF('ПРАЙС_ЛИСТ'!F112 = G92, 0, 'ПРАЙС_ЛИСТ'!F112) -> 0 | G92: ='БД_УСЛУГИ_РО'!P66 -> 700
B93: iPhone 5S | C93: 90 | E93: iPhone 5S Кнопки - восстановление / замена | *цена от, требуется диагностика | F93: ='ПРАЙС_ЛИСТ'!F113 -> 700
B94: iPhone 5S | C94: 90 | E94: iPhone 5S Динамик полифонический - замена | F94: =IF('ПРАЙС_ЛИСТ'!F114 = G94, 0, 'ПРАЙС_ЛИСТ'!F114) -> 0 | G94: ='БД_УСЛУГИ_РО'!P68 -> 800
B95: iPhone 5S | C95: 90 | E95: iPhone 5S Динамик слуховой - замена | F95: ='ПРАЙС_ЛИСТ'!F115 -> 850
B96: iPhone 5S | C96: 90 | E96: iPhone 5S Микрофон - замена (один из..) | *требуется диагностика | F96: ='ПРАЙС_ЛИСТ'!F116 -> 1050
B97: iPhone 5S | C97: 90 | E97: iPhone 5S Ремонт платы - восстановление / замена | *цена от, требуется диагностика | F97: ='ПРАЙС_ЛИСТ'!F117 -> 1600
B98: iPhone 5S | C98: 90 | E98: iPhone 5S Профилактика после воды - восстановление | *цена от, требуется диагностика | F98: ='ПРАЙС_ЛИСТ'!F118 -> 2000
B99: iPhone 5S | C99: 90 | E99: iPhone 5S Модем - восстановление GSM сети | *цена от, требуется диагностика | F99: ='ПРАЙС_ЛИСТ'!F119 -> 2000
B100: iPhone 5S | C100: 90 | E100: iPhone 5S WiFi / Bluetooth - восстановление беспроводных сетей | *цена от, требуется диагностика | F100: ='ПРАЙС_ЛИСТ'!F120 -> 900
B102: iPhone SE 2016 | C102: 0 | E102: iPhone SE 2016 Диагностика (с пайкой компонентов) | *бесплатно при дальнейшем ремонте | F102: 0
B103: iPhone SE 2016 | C103: 0 | E103: iPhone SE 2016 Чистка сеток динамиков и разъема зарядки БЕЗ РАЗБОРА (минимальная) | F103: ='ПРАЙС_ЛИСТ'!F123 -> 400
B104: iPhone SE 2016 | C104: 0 | E104: iPhone SE 2016 Чистка сеток динамиков и разъема зарядки С РАЗБОРОМ (максимальная) | F104: ='ПРАЙС_ЛИСТ'!F124 -> 900
B105: iPhone SE 2016 | C105: 180 | E105: iPhone SE 2016 Аккумулятор - замена | F105: ='ПРАЙС_ЛИСТ'!F125 -> 1400
B106: iPhone SE 2016 | C106: 90 | E106: iPhone SE 2016 Разъем зарядки - замена | F106: ='ПРАЙС_ЛИСТ'!F126 -> 1500
B107: iPhone SE 2016 | C107: 90 | E107: iPhone SE 2016 Дисплей - замена (минимальная) | F107: =IFERROR(__xludf.DUMMYFUNCTION("MIN(FILTER('ПРАЙС_ЛИСТ'!F127:F129, 'ПРАЙС_ЛИСТ'!F127:F129 <> 'ПРАЙС_ЛИСТ'!H127:H129))"),1850.0) -> 1850
B108: iPhone SE 2016 | C108: 90 | E108: iPhone SE 2016 Дисплей - замена (максимальная) | F108: =IFERROR(__xludf.DUMMYFUNCTION("MAX(FILTER('ПРАЙС_ЛИСТ'!F127:F129, 'ПРАЙС_ЛИСТ'!F127:F129 <> 'ПРАЙС_ЛИСТ'!H127:H129))"),2000.0) -> 2000
B109: iPhone SE 2016 | C109: 90 | E109: iPhone SE 2016 Камера основная - замена | F109: ='ПРАЙС_ЛИСТ'!F130 -> 750
B110: iPhone SE 2016 | C110: 90 | E110: iPhone SE 2016 Камера фронтальная - замена | F110: ='ПРАЙС_ЛИСТ'!F131 -> 750
B111: iPhone SE 2016 | C111: 90 | E111: iPhone SE 2016 Камера - замена разбитого стекла | *цена за 1шт. | F111: =IF('ПРАЙС_ЛИСТ'!F132 = G111, 0, 'ПРАЙС_ЛИСТ'!F132) -> 0 | G111: ='БД_УСЛУГИ_РО'!P64 -> 500
B112: iPhone SE 2016 | C112: 180 | E112: iPhone SE 2016 Корпус - замена | F112: =IF('ПРАЙС_ЛИСТ'!F133 = G112, 0, 'ПРАЙС_ЛИСТ'!F133) -> 0 | G112: ='БД_УСЛУГИ_РО'!P65 -> 800
B113: iPhone SE 2016 | C113: 90 | E113: iPhone SE 2016 Кнопка HOME - восстановление / замена | F113: =IF('ПРАЙС_ЛИСТ'!F134 = G113, 0, 'ПРАЙС_ЛИСТ'!F134) -> 0 | G113: ='БД_УСЛУГИ_РО'!P66 -> 700
B114: iPhone SE 2016 | C114: 90 | E114: iPhone SE 2016 Кнопки - восстановление / замена | *цена от, требуется диагностика | F114: ='ПРАЙС_ЛИСТ'!F135 -> 700
B115: iPhone SE 2016 | C115: 90 | E115: iPhone SE 2016 Динамик полифонический - замена | F115: =IF('ПРАЙС_ЛИСТ'!F136 = G115, 0, 'ПРАЙС_ЛИСТ'!F136) -> 0 | G115: ='БД_УСЛУГИ_РО'!P68 -> 800
B116: iPhone SE 2016 | C116: 90 | E116: iPhone SE 2016 Динамик слуховой - замена | F116: ='ПРАЙС_ЛИСТ'!F137 -> 850
B117: iPhone SE 2016 | C117: 90 | E117: iPhone SE 2016 Микрофон - замена (один из..) | *требуется диагностика | F117: ='ПРАЙС_ЛИСТ'!F138 -> 1800
B118: iPhone SE 2016 | C118: 90 | E118: iPhone SE 2016 Ремонт платы - восстановление / замена | *цена от, требуется диагностика | F118: ='ПРАЙС_ЛИСТ'!F139 -> 1600
B119: iPhone SE 2016 | C119: 90 | E119: iPhone SE 2016 Профилактика после воды - восстановление | *цена от, требуется диагностика | F119: ='ПРАЙС_ЛИСТ'!F140 -> 2000
B120: iPhone SE 2016 | C120: 90 | E120: iPhone SE 2016 Модем - восстановление GSM сети | *цена от, требуется диагностика | F120: ='ПРАЙС_ЛИСТ'!F141 -> 2000
...

Sheet МАТРИЦА_СТОИМОСТИ_РАБОТ
B2: КОЭФИЦИЕНТ МОДЕЛИ | D2: 0.27 | E2: 0.33 | F2: 0.45 | G2: 0.5 | H2: 0.6 | I2: 0.76 | J2: 0.76 | K2: 0.87 | L2: 0.87 | M2: 1 | N2: 1 | O2: 1.15 | P2: 1.15 | Q2: 1.32 | R2: 1.32 | S2: 1.52 | T2: 1.52 | U2: 1.75 | V2: 1.75
B3: НАДБАВКА ДЛЯ PRO СЕРИИ | D3: 1 | E3: 1 | F3: 1 | G3: 1 | H3: 1 | I3: 1 | J3: 1.05 | K3: 1 | L3: 1.05 | M3: 1 | N3: 1.05 | O3: 1 | P3: 1.05 | Q3: 1 | R3: 1.05 | S3: 1 | T3: 1.05 | U3: 1 | V3: 1.05
B4: НАИМЕНОВАНИЕ | МОДЕЛЬ | C4: НЕ ЗАВИСИТ ОТ МОДЕЛИ | D4: {={ "5 SE 2016"; MAKEARRAY(15, 1, LAMBDA(r,c, "")); IF(M20:M48="", "", MROUND(M20:M48 * D2 * D3, 50)) }} -> 5 SE 2016 | E4: {={ "6"; MAKEARRAY(15, 1, LAMBDA(r,c, "")); IF(M20:M48="", "", MROUND(M20:M48 * E2 * E3, 50)) }} -> 6 | F4: {={ "7"; MAKEARRAY(15, 1, LAMBDA(r,c, "")); IF(M20:M48="", "", MROUND(M20:M48 * F2 * F3, 50)) }} -> 7 | G4: {={ "8 SE 2020 SE 2022"; MAKEARRAY(15, 1, LAMBDA(r,c, "")); IF(M20:M48="", "", MROUND(M20:M48 * G2 * G3, 50)) }} -> 8 SE 2020 SE 2022 | H4: {={ "X"; MAKEARRAY(15, 1, LAMBDA(r,c, "")); IF(M20:M48="", "", MROUND(M20:M48 * H2 * H3, 50)) }} -> X | I4: {={ "11"; MAKEARRAY(15, 1, LAMBDA(r,c, "")); IF(M20:M48="", "", MROUND(M20:M48 * I2 * I3, 50)) }} -> 11 | J4: {={ "11 Pro 11 Pro Max"; MAKEARRAY(15, 1, LAMBDA(r,c, "")); IF(M20:M48="", "", MROUND(M20:M48 * J2 * J3, 50)) }} -> 11 Pro 11 Pro Max | K4: {={ "12 12 Mini"; MAKEARRAY(15, 1, LAMBDA(r,c, "")); IF(M20:M48="", "", MROUND(M20:M48 * K2 * K3, 50)) }} -> 12 12 Mini | L4: {={ "12 Pro 12 Pro Max"; MAKEARRAY(15, 1, LAMBDA(r,c, "")); IF(M20:M48="", "", MROUND(M20:M48 * L2 * L3, 50)) }} -> 12 Pro 12 Pro Max | M4: 13 13 Mini | N4: {={ "13 Pro 13 Pro Max"; MAKEARRAY(15, 1, LAMBDA(r,c, "")); IF(M20:M48="", "", MROUND(M20:M48 * N2 * N3, 50)) }} -> 13 Pro 13 Pro Max | O4: {={ "14 14 Plus"; MAKEARRAY(15, 1, LAMBDA(r,c, "")); IF(M20:M48="", "", MROUND(M20:M48 * O2 * O3, 50)) }} -> 14 14 Plus | P4: {={ "14 Pro 14 Pro Max"; MAKEARRAY(15, 1, LAMBDA(r,c, "")); IF(M20:M48="", "", MROUND(M20:M48 * P2 * P3, 50)) }} -> 14 Pro 14 Pro Max | Q4: {={ "15 15 Plus"; MAKEARRAY(15, 1, LAMBDA(r,c, "")); IF(M20:M48="", "", MROUND(M20:M48 * Q2 * Q3, 50)) }} -> 15 15 Plus | R4: {={ "15 Pro 15 Pro Max"; MAKEARRAY(15, 1, LAMBDA(r,c, "")); IF(M20:M48="", "", MROUND(M20:M48 * R2 * R3, 50)) }} -> 15 Pro 15 Pro Max | S4: {={ "16 16E 16 Plus"; MAKEARRAY(15, 1, LAMBDA(r,c, "")); IF(M20:M48="", "", MROUND(M20:M48 * S2 * S3, 50)) }} -> 16 16E 16 Plus | T4: {={ "16 Pro 16 Pro Max"; MAKEARRAY(15, 1, LAMBDA(r,c, "")); IF(M20:M48="", "", MROUND(M20:M48 * T2 * T3, 50)) }} -> 16 Pro 16 Pro Max | U4: {={ "17 17 Air"; MAKEARRAY(15, 1, LAMBDA(r,c, "")); IF(M20:M48="", "", MROUND(M20:M48 * U2 * U3, 50)) }} -> 17 17 Air | V4: {={ "17 Pro 17 Pro Max"; MAKEARRAY(15, 1, LAMBDA(r,c, "")); IF(M20:M48="", "", MROUND(M20:M48 * V2 * V3, 50)) }} -> 17 Pro 17 Pro Max
B5: Данные - резервная копия / перенос (1 - 128 ГБ) | *цена за фактический объем данных | C5: 1600
B6: Данные - резервная копия / перенос (128 - 256 ГБ) | *цена за фактический объем данных | C6: 2200
B7: Данные - резервная копия / перенос (256 - 512 ГБ) | *цена за фактический объем данных | C7: 4100
B8: Данные - резервная копия / перенос (512 ГБ - 1 ТБ) | *цена за фактический объем данных | C8: 5100
B9: Данные - резервная копия / перенос (1 - 2 ТБ) | *цена за фактический объем данных | C9: ?
B10: Приложения - установка | *цена за 1шт. | C10: 500
B11: Прошивка - БЕЗ РЕЗЕРВНОЙ копии | C11: 1100
B12: Сопровождение - ремонт устройства * | C12: 1
B13: Сопровождение - обмен устройства * | C13: 1
B14: Схематическая работа * | C14: 1
B15: Компонентный ремонт * | C15: 1
B16: Модульный ремонт * | C16: 1
B17: Диагностика (без пайки компонентов) | C17: 0
B18: Диагностика - составление и печать акта | C18: 1000
B20: Диагностика (с пайкой компонентов) | *бесплатно при дальнейшем ремонте | D20: 250 | E20: 300 | F20: 400 | G20: 450 | H20: 550 | I20: 700 | J20: 700 | K20: 800 | L20: 800 | M20: 900 | N20: 950 | O20: 1050 | P20: 1100 | Q20: 1200 | R20: 1250 | S20: 1350 | T20: 1450 | U20: 1600 | V20: 1650
B21: Влагозащита (этап 1) - восстановление | D21: 200 | E21: 250 | F21: 300 | G21: 350 | H21: 400 | I21: 550 | J21: 550 | K21: 600 | L21: 650 | M21: 700 | N21: 750 | O21: 800 | P21: 850 | Q21: 900 | R21: 950 | S21: 1050 | T21: 1100 | U21: 1250 | V21: 1300
B22: Влагозащита (этап 2) - восстановление | D22: 200 | E22: 250 | F22: 300 | G22: 350 | H22: 400 | I22: 550 | J22: 550 | K22: 600 | L22: 650 | M22: 700 | N22: 750 | O22: 800 | P22: 850 | Q22: 900 | R22: 950 | S22: 1050 | T22: 1100 | U22: 1250 | V22: 1300
B23: Чистка сеток динамиков и разъема зарядки БЕЗ РАЗБОРА | D23: 150 | E23: 150 | F23: 250 | G23: 250 | H23: 300 | I23: 400 | J23: 400 | K23: 450 | L23: 450 | M23: 500 | N23: 550 | O23: 600 | P23: 600 | Q23: 650 | R23: 700 | S23: 750 | T23: 800 | U23: 900 | V23: 900
B24: Чистка сеток динамиков и разъема зарядки С РАЗБОРОМ | D24: 1000 | E24: 1200 | F24: 1650 | G24: 1850 | H24: 2200 | I24: 2800 | J24: 2950 | K24: 3200 | L24: 3400 | M24: 3700 | N24: 3900 | O24: 4250 | P24: 4450 | Q24: 4900 | R24: 5150 | S24: 5600 | T24: 5900 | U24: 6500 | V24: 6800
B25: Аккумулятор - замена | D25: 1100 | E25: 1300 | F25: 1800 | G25: 2000 | H25: 2400 | I25: 3050 | J25: 3200 | K25: 3500 | L25: 3650 | M25: 4000 | N25: 4200 | O25: 4600 | P25: 4850 | Q25: 5300 | R25: 5550 | S25: 6100 | T25: 6400 | U25: 7000 | V25: 7350
B26: Аккумулятор - устранение уведомления о замене | D26: 850 | E26: 1050 | F26: 1450 | G26: 1600 | H26: 1900 | I26: 2450 | J26: 2550 | K26: 2800 | L26: 2900 | M26: 3200 | N26: 3350 | O26: 3700 | P26: 3850 | Q26: 4200 | R26: 4450 | S26: 4850 | T26: 5100 | U26: 5600 | V26: 5900
B27: Разъем зарядки - замена | D27: 1100 | E27: 1300 | F27: 1800 | G27: 2000 | H27: 2400 | I27: 3050 | J27: 3200 | K27: 3500 | L27: 3650 | M27: 4000 | N27: 4200 | O27: 4600 | P27: 4850 | Q27: 5300 | R27: 5550 | S27: 6100 | T27: 6400 | U27: 7000 | V27: 7350
B28: Дисплей - замена | D28: 1100 | E28: 1300 | F28: 1800 | G28: 2000 | H28: 2400 | I28: 3050 | J28: 3200 | K28: 3500 | L28: 3650 | M28: 4000 | N28: 4200 | O28: 4600 | P28: 4850 | Q28: 5300 | R28: 5550 | S28: 6100 | T28: 6400 | U28: 7000 | V28: 7350
B29: Дисплей - устранение уведомления о замене | D29: 900 | E29: 1100 | F29: 1500 | G29: 1650 | H29: 2000 | I29: 2500 | J29: 2650 | K29: 2850 | L29: 3000 | M29: 3300 | N29: 3450 | O29: 3800 | P29: 4000 | Q29: 4350 | R29: 4550 | S29: 5000 | T29: 5250 | U29: 5800 | V29: 6050
B30: Дисплей - замена разбитого стекла | D30: 1100 | E30: 1300 | F30: 1800 | G30: 2000 | H30: 2400 | I30: 3050 | J30: 3200 | K30: 3500 | L30: 3650 | M30: 4000 | N30: 4200 | O30: 4600 | P30: 4850 | Q30: 5300 | R30: 5550 | S30: 6100 | T30: 6400 | U30: 7000 | V30: 7350
B31: Дисплей - замена разбитого стекла с тачскрином | D31: 1100 | E31: 1300 | F31: 1800 | G31: 2000 | H31: 2400 | I31: 3050 | J31: 3200 | K31: 3500 | L31: 3650 | M31: 4000 | N31: 4200 | O31: 4600 | P31: 4850 | Q31: 5300 | R31: 5550 | S31: 6100 | T31: 6400 | U31: 7000 | V31: 7350
... B47: WiFi / Bluetooth - восстановление беспроводных сетей | *требуется диагностика | D47: 1400 | E47: 1700 | F47: 2350 | G47: 2600 | H47: 3100 | I47: 3950 | J47: 4150 | K47: 4500 | L47: 4750 | M47: 5200 | N47: 5450 | O47: 6000 | P47: 6300 | Q47: 6850 | R47: 7200 | S47: 7900 | T47: 8300 | U47: 9100 | V47: 9550

Sheet РЕМОНТ_ЯБЛОК
G4: Обновлено: 05.05.2026 11:44
B5: iPhone 5 | C5: iPhone 5 Диагностика | D5: 0 | E5: 1 мес.
C6: iPhone 5 Защитное стекло | D6: 200 | E6: 1 мес.
C7: iPhone 5 Переклейка (восстановление) вашего дисплея | D7: 1500 | E7: 1 мес.
C8: iPhone 5 Замена дисплея (оригинал) | D8: 3000 | E8: 1 мес.
C9: iPhone 5 Замена дисплея (аналог) | D9: 2000 | E9: 1 мес.
C10: iPhone 5 Замена динамика | D10: 800 | E10: 1 мес.
C11: iPhone 5 Замена микрофона | D11: 1200 | E11: 1 мес.
C12: iPhone 5 Ремонт кнопки включения | D12: 1200 | E12: 1 мес.
C13: iPhone 5 Ремонт кнопок громкости | D13: 1200 | E13: 1 мес.
C14: iPhone 5 Замена аккумулятора (1440mAh) 3.8V Standard | D14: 1200 | E14: 1 мес.
C15: iPhone 5 Замена аккумулятора (1800mAh) 3.8V HC (повышенная емкость) | D15: 1600 | E15: 1 мес.
C16: iPhone 5 Замена основной камеры | D16: 1200 | E16: 1 мес.
C17: iPhone 5 Замена фронтальной камеры | D17: 1000 | E17: 1 мес.
... C25: iPhone 5 Разблокировка | D25: 900 | E25: 1 мес.
B27: iPhone 5C | C27: iPhone 5C Диагностика | D27: 0 | E27: 1 мес.
C28: iPhone 5C Защитное стекло | D28: 200 | E28: 1 мес.
C29: iPhone 5C Переклейка (восстановление) вашего дисплея | D29: 1500 | E29: 1 мес.
C30: iPhone 5C Замена дисплея (оригинал) | D30: 3000 | E30: 1 мес.
C31: iPhone 5C Замена дисплея (аналог) | D31: 2000 | E31: 1 мес.
C32: iPhone 5C Замена динамика | D32: 800 | E32: 1 мес.
C33: iPhone 5C Замена микрофона | D33: 1200 | E33: 1 мес.
C34: iPhone 5C Ремонт кнопки включения | D34: 1200 | E34: 1 мес.
C35: iPhone 5C Ремонт кнопок громкости | D35: 1200 | E35: 1 мес.
C36: iPhone 5C Замена аккумулятора (1560mAh) 3.8V Standard | D36: 1200 | E36: 1 мес.
C37: iPhone 5C Замена аккумулятора (1800mAh) 3.8V HC (повышенная емкость) | D37: 1600 | E37: 1 мес.
C38: iPhone 5C Замена основной камеры | D38: 1200 | E38: 1 мес.
C39: iPhone 5C Замена фронтальной камеры | D39: 1000 | E39: 1 мес.
... C47: iPhone 5C Разблокировка | D47: 900 | E47: 1 мес.
B49: iPhone 5S | C49: iPhone 5S Диагностика | D49: 0 | E49: 1 мес.
C50: iPhone 5S Защитное стекло | D50: 200 | E50: 1 мес.
C51: iPhone 5S Переклейка (восстановление) вашего дисплея | D51: 1500 | E51: 1 мес.
C52: iPhone 5S Замена дисплея (оригинал) | D52: 2500 | E52: 1 мес.
C53: iPhone 5S Замена дисплея (аналог) | D53: 2000 | E53: 1 мес.
C54: iPhone 5S Замена динамика | D54: 800 | E54: 1 мес.
C55: iPhone 5S Замена микрофона | D55: 1200 | E55: 1 мес.
C56: iPhone 5S Ремонт кнопки включения | D56: 1200 | E56: 1 мес.
C57: iPhone 5S Ремонт кнопок громкости | D57: 1200 | E57: 1 мес.
C58: iPhone 5S Замена аккумулятора (1560mAh) 3.8V Standard | D58: 1200 | E58: 1 мес.
C59: iPhone 5S Замена аккумулятора (1800mAh) 3.8V HC (повышенная емкость) | D59: 1600 | E59: 1 мес.
C60: iPhone 5S Замена основной камеры | D60: 1200 | E60: 1 мес.
C61: iPhone 5S Замена фронтальной камеры | D61: 1000 | E61: 1 мес.
... C69: iPhone 5S Разблокировка | D69: 900 | E69: 1 мес.
B71: iPhone SE | C71: iPhone SE Диагностика | D71: 0 | E71: 1 мес.
C72: iPhone SE Переклейка вашего дисплея | D72: 2000 | E72: 1 мес.
C73: iPhone SE Замена дисплея (оригинал) | D73: 2500 | E73: 1 мес.
C74: iPhone SE Замена дисплея (аналог) | D74: 2000 | E74: 1 мес.
C75: iPhone SE Замена динамика | D75: 1000 | E75: 1 мес.
C76: iPhone SE Замена микрофона | D76: 1200 | E76: 1 мес.
C77: iPhone SE Замена кнопки включения | D77: 1200 | E77: 1 мес.
C78: iPhone SE Замена кнопок громкости | D78: 1000 | E78: 1 мес.
C79: iPhone SE Замена аккумулятора (1624mAh) 3.82V Standard | D79: 1400 | E79: 1 мес.
C80: iPhone SE Замена аккумулятора (2010mAh) 3.82V HC (повышенная емкость) | D80: 1800 | E80: 1 мес.
C81: iPhone SE Замена основной камеры | D81: 1800 | E81: 1 мес.
C82: iPhone SE Замена фронтальной камеры | D82: 1200 | E82: 1 мес.
C83: iPhone SE Замена разъема наушников | D83: 1400 | E83: 1 мес.
... C90: iPhone SE Разблокировка | D90: 900 | E90: 1 мес.
B92: iPhone 6 | C92: iPhone 6 Диагностика | D92: 0 | E92: 1 мес.
C93: iPhone 6 Переклейка (восстановление) вашего дисплея | D93: 2000 | E93: 1 мес.
C94: iPhone 6 Замена дисплея (оригинал) | D94: 2500 | E94: 1 мес.
C95: iPhone 6 Замена дисплея (аналог) | D95: 1800 | E95: 1 мес.
C96: iPhone 6 Замена динамика | D96: 1000 | E96: 1 мес.
C97: iPhone 6 Замена микрофона | D97: 1600 | E97: 1 мес.
C98: iPhone 6 Замена кнопки включения | D98: 1600 | E98: 1 мес.
C99: iPhone 6 Замена кнопок громкости | D99: 1600 | E99: 1 мес.
C100: iPhone 6 Замена аккумулятора (1810mAh) 3.82V Standard | D100: 1400 | E100: 1 мес.
C101: iPhone 6 Замена аккумулятора (2300mAh) 3.82V HC (повышенная емкость) | D101: 1800 | E101: 1 мес.
C102: iPhone 6 Замена основной камеры | D102: 1400 | E102: 1 мес.
C103: iPhone 6 Замена фронтальной камеры | D103: 1200 | E103: 1 мес.
C104: iPhone 6 Замена разъема наушников | D104: 1400 | E104: 1 мес.
... C112: iPhone 6 Замена стекла камеры | D112: 1000 | E112: 1 мес.
B114: iPhone 6 Plus | C114: iPhone 6 Plus Диагностика | D114: 0 | E114: 1 мес.
C115: iPhone 6 Plus Переклейка (восстановление) вашего дисплея | D115: 2000 | E115: 1 мес.
C116: iPhone 6 Plus Замена дисплея (оригинал) | D116: 2500 | E116: 1 мес.
C117: iPhone 6 Plus Замена дисплея (аналог) | D117: 2000 | E117: 1 мес.
C118: iPhone 6 Plus Замена динамика | D118: 1200 | E118: 1 мес.
C119: iPhone 6 Plus Замена микрофона | D119: 1900 | E119: 1 мес.
C120: iPhone 6 Plus Замена кнопки включения | D120: 1800 | E120: 1 мес.
C121: iPhone 6 Plus Замена кнопок громкости | D121: 1800 | E121: 1 мес.
C122: iPhone 6 Plus Замена аккумулятора (2915mAh) 3.82V Standard | D122: 1600 | E122: 1 мес.
C123: iPhone 6 Plus Замена аккумулятора (3410mAh) 3.82V HC (повышенная емкость) | D123: 2000 | E123: 1 мес.
C124: iPhone 6 Plus Замена основной камеры | D124: 1800 | E124: 1 мес.
C125: iPhone 6 Plus Замена фронтальной камеры | D125: 1600 | E125: 1 мес.
C126: iPhone 6 Plus Замена разъема наушников | D126: 1600 | E126: 1 мес.
... C134: iPhone 6 Plus Замена стекла камеры | D134: 1000 | E134: 1 мес.
B136: iPhone 6S | C136: iPhone 6S Диагностика | D136: 0 | E136: 1 мес.
C137: iPhone 6S Переклейка (восстановление) вашего дисплея | D137: 2000 | E137: 1 мес.
C138: iPhone 6S Замена дисплея (оригинал) | D138: 2500 | E138: 1 мес.
C139: iPhone 6S Замена дисплея (аналог) | D139: 2000 | E139: 1 мес.
C140: iPhone 6S Замена динамика | D140: 1200 | E140: 1 мес.
C141: iPhone 6S Замена микрофона | D141: 1900 | E141: 1 мес.
C142: iPhone 6S Замена кнопки включения | D142: 2000 | E142: 1 мес.
C143: iPhone 6S Замена кнопок громкости | D143: 2000 | E143: 1 мес.
C144: iPhone 6S Замена аккумулятора (1715mAh) 3.82V Standard | D144: 1600 | E144: 1 мес.
C145: iPhone 6S Замена аккумулятора (2510mAh) 3.82V HC (повышенная емкость) | D145: 2000 | E145: 1 мес.
C146: iPhone 6S Замена основной камеры | D146: 2000 | E146: 1 мес.
C147: iPhone 6S Замена фронтальной камеры | D147: 1800 | E147: 1 мес.
C148: iPhone 6S Замена разъема наушников | D148: 1600 | E148: 1 мес.
... C156: iPhone 6S Замена стекла камеры | D156: 1000 | E156: 1 мес.
B158: iPhone 6S Plus | C158: iPhone 6S Plus Диагностика | D158: 0 | E158: 1 мес.
...

Sheet БД_ЗАПЧАСТИ
G2: ПАРСИНГ
G3: ICOMPONENTS | J3: MOS - LCD | U3: НАЦЕНКА В РУБЛЯХ | X3: ЦЕНЫ НА ЗАПЧАСТИ
B4: НАИМЕНОВАНИЕ ЗАПЧАСТИ | C4: ID ЗАПЧАСТИ | D4: ГАРАНТИЯ | E4: МОДЕЛЬ | F4: КАТЕГОРИЯ | G4: НАИМЕНОВАНИЕ НА САЙТЕ ICOMPONENTS | H4: СТАРАЯ ЦЕНА ЗАПЧАСТИ ICOMPONENTS | I4: АКТ. ЦЕНА ЗАПЧАСТИ ICOMPONENTS | J4: НАИМЕНОВАНИЕ В ПРАЙСЕ MOS - LCD | K4: СТАРАЯ ЦЕНА ЗАПЧАСТИ MOS - LCD | L4: АКТ. ЦЕНА ЗАПЧАСТИ MOS - LCD | M4: {={"ПОДХОДЯЩАЯ ЦЕНА ЗАПЧАСТИ*"; BYROW(H5:L921, LAMBDA(row, IF(COUNT(row)>0, MAX(row), "")))}} -> ПОДХОДЯЩАЯ ЦЕНА ЗАПЧАСТИ* | N4: НАЦЕНКА НА ЗАПЧАСТЬ | O4: {={"СТОИМОСТЬ ЗАПЧАСТИ С НАЦЕНКОЙ*"; IF(M5:M921<>"", MROUND(M5:M921*(1+N5:N921), 50), "")}} -> СТОИМОСТЬ ЗАПЧАСТИ С НАЦЕНКОЙ* | P4: ИТОГОВАЯ СТОИМОСТЬ ЗАПЧАСТИ (ПРАЙС) | Q4: ИТОГОВАЯ СТОИМОСТЬ ЗАПЧАСТИ (РЕМОНЛАЙН) | R4: ССЫЛКА НА ЗАПЧАСТЬ ICOMPONENTS | S4: ДАТА ПАРСИНГА | U4: НАЦЕНКА В РУБЛЯХ ICOMPONENTS | V4: НАЦЕНКА В РУБЛЯХ MOS - LCD | X4: {={"ЦЕНА ICOMPONENTS*"; I5:I921}} -> ЦЕНА ICOMPONENTS* | Y4: {={"ЦЕНА MOS - LCD*"; L5:L921}} -> ЦЕНА MOS - LCD* | AA4: {={"ID*"; C5:C921}} -> ID* | AB4: {={"КОД*"; AA5:AA921}} -> КОД* | AC4: Артикул | AD4: {={"ШТРИХКОД*"; AA5:AA921}} -> ШТРИХКОД* | AE4: {={"Наименование*"; B5:B921}} -> Наименование* | AF4: Описание | AG4: {={ "Единица измерения*" ; IF(AG5:AG921 <> "", "pcs", "pcs") }} -> Единица измерения* | AH4: Категория | AI4: {={"Гарантия*"; D5:D921}} -> Гарантия* | AJ4: {={ "Гарантийный период*" ; IF(AJ5:AJ921 <> "", "дн", "дн") }} -> Гарантийный период* | AK4: Серийный учет | AL4: {={ "Включить отслеживание срока годности*" ; IF(AL5:AL921 <> "", "нет", "нет") }} -> Включить отслеживание срока годности* | AM4: Длина | AN4: Ширина | AO4: Высота | AP4: Единица измерения размеров | AQ4: Вес | AR4: Единица веса | AS4: ID поставщика по умолчанию | AT4: Имя поставщика по умолчанию | AU4: {={"Закупочная*"; M5:M921}} -> Закупочная* | AV4: {={"Розничная*"; Q5:Q921}} -> Розничная*
B5: iPhone 5 [BAT] Аккумулятор - Аналог ORIG | C5: 161 990 | D5: 180 | E5: =LEFT(B5,FIND("[",B5) - 2) -> iPhone 5 | F5: Аккумулятор | G5: iPhone 5 - аккумуляторная батарея (АКБ), ORIG | I5: 430 | L5: 340 | M5: 430 | N5: 0.12 | O5: 500 | P5: =O5 -> 500 | Q5: =P5 -> 500 | R5: https://icomponents.ru/catalog/iphone/iphone_5/iphone_5_akkumulyatornaya_batareya_akb_orig/ | S5: 46140.38 | U5: =IF(I5>0, Q5 - I5, "нет з/ч") -> 70 | V5: =IF(L5>0, Q5 - L5, "нет з/ч") -> 160 | X5: 430 | Y5: 340 | AA5: 161 990 | AB5: 161 990 | AD5: 161 990 | AE5: iPhone 5 [BAT] Аккумулятор - Аналог ORIG | AG5: pcs | AH5: Сервис > Ремонт Apple > Ремонт iPhone > 5 | AI5: 180 | AJ5: дн | AK5: да | AL5: нет | AU5: 430 | AV5: 500
B6: iPhone 5C / 5S [BAT] Аккумулятор - Аналог ORIG | C6: 162 011 | D6: 180 | E6: =LEFT(B6,FIND("[",B6) - 2) -> iPhone 5C / 5S | F6: Аккумулятор | G6: iPhone 5s - аккумуляторная батарея (АКБ), ORIG | I6: 370 | L6: 340 | M6: 370 | N6: 0.3 | O6: 500 | P6: =O6 -> 500 | Q6: =P6 -> 500 | R6: https://icomponents.ru/catalog/iphone/iphone_5s/iphone_5s_akkumulyatornaya_batareya_akb_orig/ | S6: 46140.38 | U6: =IF(I6>0, Q6 - I6, "нет з/ч") -> 130 | V6: =IF(L6>0, Q6 - L6, "нет з/ч") -> 160 | X6: 370 | Y6: 340 | AA6: 162 011 | AB6: 162 011 | AD6: 162 011 | AE6: iPhone 5C / 5S [BAT] Аккумулятор - Аналог ORIG | AG6: pcs | AH6: Сервис > Ремонт Apple > Ремонт iPhone > 5C | AI6: 180 | AJ6: дн | AK6: да | AL6: нет | AU6: 370 | AV6: 500
B7: iPhone SE 2016 [BAT] Аккумулятор - Аналог ORIG | C7: 4643 101 | D7: 180 | E7: =LEFT(B7,FIND("[",B7) - 2) -> iPhone SE 2016 | F7: Аккумулятор | G7: iPhone SE - Аккумуляторная батарея (АКБ), ORIG | I7: 530 | L7: 480 | M7: 530 | N7: 0.3 | O7: 700 | P7: =O7 -> 700 | Q7: =P7 -> 700 | R7: https://icomponents.ru/catalog/iphone/iphone_se/iphone_se_akkumulyatornaya_batareya_akb_orig/ | S7: 46140.38 | U7: =IF(I7>0, Q7 - I7, "нет з/ч") -> 170 | V7: =IF(L7>0, Q7 - L7, "нет з/ч") -> 220 | X7: 530 | Y7: 480 | AA7: 4643 101 | AB7: 4643 101 | AD7: 4643 101 | AE7: iPhone SE 2016 [BAT] Аккумулятор - Аналог ORIG | AG7: pcs | AH7: Сервис > Ремонт Apple > Ремонт iPhone > SE2016 | AI7: 180 | AJ7: дн | AK7: да | AL7: нет | AU7: 530 | AV7: 700
B8: iPhone 6 [BAT] Аккумулятор - Аналог ORIG | C8: 228 700 | D8: 180 | E8: =LEFT(B8,FIND("[",B8) - 2) -> iPhone 6 | F8: Аккумулятор | G8: iPhone 6 - аккумуляторная батарея (АКБ), ORIG | I8: 450 | L8: 380 | M8: 450 | N8: 0.3 | O8: 600 | P8: =O8 -> 600 | Q8: =P8 -> 600 | R8: https://icomponents.ru/catalog/iphone/iphone_6/iphone_6_akkumulyatornaya_batareya_akb_orig/ | S8: 46140.38 | U8: =IF(I8>0, Q8 - I8, "нет з/ч") -> 150 | V8: =IF(L8>0, Q8 - L8, "нет з/ч") -> 220 | X8: 450 | Y8: 380 | AA8: 228 700 | AB8: 228 700 | AD8: 228 700 | AE8: iPhone 6 [BAT] Аккумулятор - Аналог ORIG | AG8: pcs | AH8: Сервис > Ремонт Apple > Ремонт iPhone > 6 | AI8: 180 | AJ8: дн | AK8: да | AL8: нет | AU8: 450 | AV8: 600
B9: iPhone 6 Plus [BAT] Аккумулятор - Аналог ORIG | C9: 202 322 | D9: 180 | E9: =LEFT(B9,FIND("[",B9) - 2) -> iPhone 6 Plus | F9: Аккумулятор | G9: iPhone 6+ - Аккумуляторная батарея (АКБ), ORIG | I9: 490 | L9: 480 | M9: 490 | N9: 0.6 | O9: 800 | P9: =O9 -> 800 | Q9: =P9 -> 800 | R9: https://icomponents.ru/catalog/iphone/iphone_6_2/iphone_6_akkumulyatornaya_batareya_akb_orig_2/ | S9: 46140.38 | U9: =IF(I9>0, Q9 - I9, "нет з/ч") -> 310 | V9: =IF(L9>0, Q9 - L9, "нет з/ч") -> 320 | X9: 490 | Y9: 480 | AA9: 202 322 | AB9: 202 322 | AD9: 202 322 | AE9: iPhone 6 Plus [BAT] Аккумулятор - Аналог ORIG | AG9: pcs | AH9: Сервис > Ремонт Apple > Ремонт iPhone > 6 Plus | AI9: 180 | AJ9: дн | AK9: да | AL9: нет | AU9: 490 | AV9: 800
B10: iPhone 6S [BAT] Аккумулятор - Аналог ORIG | C10: 2342 214 | D10: 180 | E10: =LEFT(B10,FIND("[",B10) - 2) -> iPhone 6S | F10: Аккумулятор | G10: iPhone 6s - Аккумуляторная батарея (АКБ), ORIG | I10: 520 | L10: 480 | M10: 520 | N10: 0.5 | O10: 800 | P10: =O10 -> 800 | Q10: =P10 -> 800 | R10: https://icomponents.ru/catalog/iphone/iphone_6s_2/iphone_6s_akkumulyatornaya_batareya_akb_orig/ | S10: 46140.38 | U10: =IF(I10>0, Q10 - I10, "нет з/ч") -> 280 | V10: =IF(L10>0, Q10 - L10, "нет з/ч") -> 320 | X10: 520 | Y10: 480 | AA10: 2342 214 | AB10: 2342 214 | AD10: 2342 214 | AE10: iPhone 6S [BAT] Аккумулятор - Аналог ORIG | AG10: pcs | AH10: Сервис > Ремонт Apple > Ремонт iPhone > 6S | AI10: 180 | AJ10: дн | AK10: да | AL10: нет | AU10: 520 | AV10: 800
B11: iPhone 6S Plus [BAT] Аккумулятор - Аналог ORIG | C11: 531 290 | D11: 180 | E11: =LEFT(B11,FIND("[",B11) - 2) -> iPhone 6S Plus | F11: Аккумулятор | G11: iPhone 6s+ - Аккумуляторная батарея (АКБ), ORIG | I11: 590 | L11: 550 | M11: 590 | N11: 0.7 | O11: 1000 | P11: =O11 -> 1000 | Q11: =P11 -> 1000 | R11: https://icomponents.ru/catalog/iphone/iphone_6s/iphone_6s_akkumulyatornaya_batareya_akb_orig_2/ | S11: 46140.38 | U11: =IF(I11>0, Q11 - I11, "нет з/ч") -> 410 | V11: =IF(L11>0, Q11 - L11, "нет з/ч") -> 450 | X11: 590 | Y11: 550 | AA11: 531 290 | AB11: 531 290 | AD11: 531 290 | AE11: iPhone 6S Plus [BAT] Аккумулятор - Аналог ORIG | AG11: pcs | AH11: Сервис > Ремонт Apple > Ремонт iPhone > 6S Plus | AI11: 180 | AJ11: дн | AK11: да | AL11: нет | AU11: 590 | AV11: 1000
B12: iPhone 7 [BAT] Аккумулятор - Аналог ORIG | C12: 5032 428 | D12: 180 | E12: =LEFT(B12,FIND("[",B12) - 2) -> iPhone 7 | F12: Аккумулятор | G12: iPhone 7 - Аккумуляторная батарея (АКБ), ORIG | I12: 450 | L12: 480 | M12: 480 | N12: 0.5 | O12: 700 | P12: =O12 -> 700 | Q12: =P12 -> 700 | R12: https://icomponents.ru/catalog/iphone/iphone_7_2/iphone_7_akkumulyatornaya_batareya_akb_orig/ | S12: 46140.38 | U12: =IF(I12>0, Q12 - I12, "нет з/ч") -> 250 | V12: =IF(L12>0, Q12 - L12, "нет з/ч") -> 220 | X12: 450 | Y12: 480 | AA12: 5032 428 | AB12: 5032 428 | AD12: 5032 428 | AE12: iPhone 7 [BAT] Аккумулятор - Аналог ORIG | AG12: pcs | AH12: Сервис > Ремонт Apple > Ремонт iPhone > 7 | AI12: 180 | AJ12: дн | AK12: да | AL12: нет | AU12: 480 | AV12: 700
B13: iPhone 7 Plus [BAT] Аккумулятор - Аналог ORIG | C13: 5032 427 | D13: 180 | E13: =LEFT(B13,FIND("[",B13) - 2) -> iPhone 7 Plus | F13: Аккумулятор | G13: iPhone 7+ - Аккумуляторная батарея (АКБ), ORIG | I13: 620 | L13: 570 | M13: 620 | N13: 0.45 | O13: 900 | P13: =O13 -> 900 | Q13: =P13 -> 900 | R13: https://icomponents.ru/catalog/iphone/iphone_7/iphone_7_akkumulyatornaya_batareya_akb_orig_2/ | S13: 46140.38 | U13: =IF(I13>0, Q13 - I13, "нет з/ч") -> 280 | V13: =IF(L13>0, Q13 - L13, "нет з/ч") -> 330 | X13: 620 | Y13: 570 | AA13: 5032 427 | AB13: 5032 427 | AD13: 5032 427 | AE13: iPhone 7 Plus [BAT] Аккумулятор - Аналог ORIG | AG13: pcs | AH13: Сервис > Ремонт Apple > Ремонт iPhone > 7 Plus | AI13: 180 | AJ13: дн | AK13: да | AL13: нет | AU13: 620 | AV13: 900
B14: iPhone 8 [BAT] Аккумулятор - Аналог ORIG | C14: 9340 394 | D14: 180 | E14: =LEFT(B14,FIND("[",B14) - 2) -> iPhone 8 | F14: Аккумулятор | G14: iPhone 8 - Аккумуляторная батарея (АКБ), ORIG | I14: 590 | L14: 550 | M14: 590 | N14: 0.5 | O14: 900 | P14: =O14 -> 900 | Q14: =P14 -> 900 | R14: https://icomponents.ru/catalog/iphone/iphone_8_se2020/iphone_8_akkumulyatornaya_batareya_akb_orig/ | S14: 46140.38 | U14: =IF(I14>0, Q14 - I14, "нет з/ч") -> 310 | V14: =IF(L14>0, Q14 - L14, "нет з/ч") -> 350 | X14: 590 | Y14: 550 | AA14: 9340 394 | AB14: 9340 394 | AD14: 9340 394 | AE14: iPhone 8 [BAT] Аккумулятор - Аналог ORIG | AG14: pcs | AH14: Сервис > Ремонт Apple > Ремонт iPhone > 8 | AI14: 180 | AJ14: дн | AK14: да | AL14: нет | AU14: 590 | AV14: 900
B15: iPhone 8 Plus [BAT] Аккумулятор - Аналог ORIG | C15: 9340 395 | D15: 180 | E15: =LEFT(B15,FIND("[",B15) - 2) -> iPhone 8 Plus | F15: Аккумулятор | G15: iPhone 8+ - Аккумуляторная батарея (АКБ), ORIG | I15: 620 | L15: 610 | M15: 620 | N15: 0.75 | O15: 1100 | P15: =O15 -> 1100 | Q15: =P15 -> 1100 | R15: https://icomponents.ru/catalog/iphone/iphone_8/iphone_8_akkumulyatornaya_batareya_akb_orig_2/ | S15: 46140.38 | U15: =IF(I15>0, Q15 - I15, "нет з/ч") -> 480 | V15: =IF(L15>0, Q15 - L15, "нет з/ч") -> 490 | X15: 620 | Y15: 610 | AA15: 9340 395 | AB15: 9340 395 | AD15: 9340 395 | AE15: iPhone 8 Plus [BAT] Аккумулятор - Аналог ORIG | AG15: pcs | AH15: Сервис > Ремонт Apple > Ремонт iPhone > 8 Plus | AI15: 180 | AJ15: дн | AK15: да | AL15: нет | AU15: 620 | AV15: 1100
B16: iPhone SE 2020 [BAT] Аккумулятор - Аналог ORIG (неизвестная деталь) | C16: 20630 753 | D16: 180 | E16: =LEFT(B16,FIND("[",B16) - 2) -> iPhone SE 2020 | F16: Аккумулятор | G16: iPhone SE 2020 - Аккумуляторная батарея (АКБ), ORIG | I16: 500 | L16: 550 | M16: 550 | N16: 1.4 | O16: 1300 | P16: =O16 -> 1300 | Q16: =P16 -> 1300 | R16: https://icomponents.ru/catalog/iphone/iphone_8_se2020/iphone_se_2020_akkumulyatornaya_batareya_akb_orig/ | S16: 46140.38 | U16: =IF(I16>0, Q16 - I16, "нет з/ч") -> 800 | V16: =IF(L16>0, Q16 - L16, "нет з/ч") -> 750 | X16: 500 | Y16: 550 | AA16: 20630 753 | AB16: 20630 753 | AD16: 20630 753 | AE16: iPhone SE 2020 [BAT] Аккумулятор - Аналог ORIG (неизвестная деталь) | AG16: pcs | AH16: Сервис > Ремонт Apple > Ремонт iPhone > SE 2020 | AI16: 180 | AJ16: дн | AK16: да | AL16: нет | AU16: 550 | AV16: 1300
... B18: iPhone XR [BAT] Аккумулятор - Аналог ORIG (неизвестная деталь) | C18: 14471 928 | D18: 180 | E18: =LEFT(B18,FIND("[",B18) - 2) -> iPhone XR | F18: Аккумулятор | G18: iPhone XR - Аккумуляторная батарея + скотч (АКБ), ORIG | I18: 700 | L18: 710 | M18: 710 | N18: 0.7 | O18: 1200 | P18: =O18 -> 1200 | Q18: =P18 -> 1200 | R18: https://icomponents.ru/catalog/iphone/iphone_xr/iphone_xr_akkumulyatornaya_batareya_skotch_akb_orig/ | S18: 46140.38 | U18: =IF(I18>0, Q18 - I18, "нет з/ч") -> 500 | V18: =IF(L18>0, Q18 - L18, "нет з/ч") -> 490 | X18: 700 | Y18: 710 | AA18: 14471 928 | AB18: 14471 928 | AD18: 14471 928 | AE18: iPhone XR [BAT] Аккумулятор - Аналог ORIG (неизвестная деталь) | AG18: pcs | AH18: Сервис > Ремонт Apple > Ремонт iPhone > XR | AI18: 180 | AJ18: дн | AK18: да | AL18: нет | AU18: 710 | AV18: 1200
B19: iPhone XR [BAT] Аккумулятор - Банка ORIG | C19: 25421 837 | D19: 180 | E19: =LEFT(B19,FIND("[",B19) - 2) -> iPhone XR | F19: Аккумулятор | G19: iPhone XR - Банка АКБ с комплектом наклеек без шлейфа | I19: 390 | M19: 390 | N19: 0.12 | O19: 450 | Q19: =P18 -> 1200 | R19: https://icomponents.ru/catalog/iphone/iphone_xr/iphone_xr_banka_akb_s_komplektom_nakleek_bez_shleyfa/ | S19: 46140.38 | U19: =IF(I19>0, Q19 - I19, "нет з/ч") -> 810 | V19: =IF(L19>0, Q19 - L19, "нет з/ч") -> нет з/ч | X19: 390 | AA19: 25421 837 | AB19: 25421 837 | AD19: 25421 837 | AE19: iPhone XR [BAT] Аккумулятор - Банка ORIG | AG19: pcs | AH19: Сервис > Ремонт Apple > Ремонт iPhone > XR | AI19: 180 | AJ19: дн | AK19: да | AL19: нет | AU19: 390 | AV19: 1200
B20: iPhone X [BAT] Аккумулятор - Аналог ORIG | C20: 9109 216 | D20: 180 | E20: =LEFT(B20,FIND("[",B20) - 2) -> iPhone X | F20: Аккумулятор | G20: iPhone X - Аккумуляторная батарея + скотч (АКБ), ORIG | I20: 750 | L20: 750 | M20: 750 | N20: 0.6 | O20: 1200 | P20: =O20 -> 1200 | Q20: =P20 -> 1200 | R20: https://icomponents.ru/catalog/iphone/iphone_x/iphone_x_akkumulyatornaya_batareya_skotch_akb_orig/ | S20: 46140.38 | U20: =IF(I20>0, Q20 - I20, "нет з/ч") -> 450 | V20: =IF(L20>0, Q20 - L20, "нет з/ч") -> 450 | X20: 750 | Y20: 750 | AA20: 9109 216 | AB20: 9109 216 | AD20: 9109 216 | AE20: iPhone X [BAT] Аккумулятор - Аналог ORIG | AG20: pcs | AH20: Сервис > Ремонт Apple > Ремонт iPhone > X | AI20: 180 | AJ20: дн | AK20: да | AL20: нет | AU20: 750 | AV20: 1200
B21: iPhone XS [BAT] Аккумулятор - Аналог ORIG (неизвестная деталь) | C21: 14197 590 | D21: 180 | E21: =LEFT(B21,FIND("[",B21) - 2) -> iPhone XS | F21: Аккумулятор | G21: iPhone XS - Аккумуляторная батарея + скотч (АКБ), ORIG | I21: 800 | L21: 750 | M21: 800 | N21: 0.5 | O21: 1200 | P21: =O21 -> 1200 | Q21: =P21 -> 1200 | R21: https://icomponents.ru/catalog/iphone/iphone_xs/iphone_xs_akkumulyatornaya_batareya_skotch_akb_orig/ | S21: 46140.38 | U21: =IF(I21>0, Q21 - I21, "нет з/ч") -> 400 | V21: =IF(L21>0, Q21 - L21, "нет з/ч") -> 450 | X21: 800 | Y21: 750 | AA21: 14197 590 | AB21: 14197 590 | AD21: 14197 590 | AE21: iPhone XS [BAT] Аккумулятор - Аналог ORIG (неизвестная деталь) | AG21: pcs | AH21: Сервис > Ремонт Apple > Ремонт iPhone > XS | AI21: 180 | AJ21: дн | AK21: да | AL21: нет | AU21: 800 | AV21: 1200
B22: iPhone XS [BAT] Аккумулятор - Банка ORIG | C22: 25245 934 | D22: 180 | E22: =LEFT(B22,FIND("[",B22) - 2) -> iPhone XS | F22: Аккумулятор | G22: iPhone XS - Банка АКБ с комплектом наклеек без шлейфа | I22: 530 | M22: 530 | N22: 0.12 | O22: 600 | Q22: =P21 -> 1200 | R22: https://icomponents.ru/catalog/iphone/iphone_xs/iphone_xs_banka_akb_s_komplektom_nakleek_bez_shleyfa/ | S22: 46140.38 | U22: =IF(I22>0, Q22 - I22, "нет з/ч") -> 670 | V22: =IF(L22>0, Q22 - L22, "нет з/ч") -> нет з/ч | X22: 530 | AA22: 25245 934 | AB22: 25245 934 | AD22: 25245 934 | AE22: iPhone XS [BAT] Аккумулятор - Банка ORIG | AG22: pcs | AH22: Сервис > Ремонт Apple > Ремонт iPhone > XS | AI22: 180 | AJ22: дн | AK22: да | AL22: нет | AU22: 530 | AV22: 1200
B23: iPhone XS Max [BAT] Аккумулятор - Аналог ORIG (неизвестная деталь) | C23: 14197 591 | D23: 180 | E23: =LEFT(B23,FIND("[",B23) - 2) -> iPhone XS Max | F23: Аккумулятор | G23: iPhone XS MAX - Аккумуляторная батарея + скотч (АКБ), ORIG | I23: 850 | L23: 750 | M23: 850 | N23: 1 | O23: 1700 | P23: =O23 -> 1700 | Q23: =P23 -> 1700 | R23: https://icomponents.ru/catalog/iphone/iphone_xs_max/iphone_xs_max_akkumulyatornaya_batareya_skotch_akb_orig/ | S23: 46140.38 | U23: =IF(I23>0, Q23 - I23, "нет з/ч") -> 850 | V23: =IF(L23>0, Q23 - L23, "нет з/ч") -> 950 | X23: 850 | Y23: 750 | AA23: 14197 591 | AB23: 14197 591 | AD23: 14197 591 | AE23: iPhone XS Max [BAT] Аккумулятор - Аналог ORIG (неизвестная деталь) | AG23: pcs | AH23: Сервис > Ремонт Apple > Ремонт iPhone > XS Max | AI23: 180 | AJ23: дн | AK23: да | AL23: нет | AU23: 850 | AV23: 1700
B24: iPhone XS Max [BAT] Аккумулятор - Банка ORIG | C24: 25245 979 | D24: 180 | E24: =LEFT(B24,FIND("[",B24) - 2) -> iPhone XS Max | F24: Аккумулятор | G24: iPhone XS Max - Банка АКБ с комплектом наклеек без шлейфа | I24: 550 | M24: 550 | N24: 0.12 | O24: 600 | Q24: =P23 -> 1700 | R24: https://icomponents.ru/catalog/iphone/iphone_xs_max/iphone_xs_max_banka_akb_s_komplektom_nakleek_bez_shleyfa/ | S24: 46140.38 | U24: =IF(I24>0, Q24 - I24, "нет з/ч") -> 1150 | V24: =IF(L24>0, Q24 - L24, "нет з/ч") -> нет з/ч | X24: 550 | AA24: 25245 979 | AB24: 25245 979 | AD24: 25245 979 | AE24: iPhone XS Max [BAT] Аккумулятор - Банка ORIG | AG24: pcs | AH24: Сервис > Ремонт Apple > Ремонт iPhone > XS Max | AI24: 180 | AJ24: дн | AK24: да | AL24: нет | AU24: 550 | AV24: 1700
B25: iPhone 11 [BAT] Аккумулятор - Аналог ORIG (неизвестная деталь) | C25: 24010 460 | D25: 180 | E25: =LEFT(B25,FIND("[",B25) - 2) -> iPhone 11 | F25: Аккумулятор | G25: iPhone 11 - Аккумуляторная батарея + скотч (АКБ), ORIG | I25: 700 | L25: 790 | M25: 790 | N25: 0.12 | O25: 900 | P25: =O25 -> 900 | Q25: =P25 -> 900 | R25: https://icomponents.ru/catalog/iphone/iphone_11/iphone_11_akkumulyatornaya_batareya_skotch_akb_orig/ | S25: 46140.381 | U25: =IF(I25>0, Q25 - I25, "нет з/ч") -> 200 | V25: =IF(L25>0, Q25 - L25, "нет з/ч") -> 110 | X25: 700 | Y25: 790 | AA25: 24010 460 | AB25: 24010 460 | AD25: 24010 460 | AE25: iPhone 11 [BAT] Аккумулятор - Аналог ORIG (неизвестная деталь) | AG25: pcs | AH25: Сервис > Ремонт Apple > Ремонт iPhone > 11 | AI25: 180 | AJ25: дн | AK25: да | AL25: нет | AU25: 790 | AV25: 900
B26: iPhone 11 [BAT] Аккумулятор - Банка ORIG | C26: 37706 712 | D26: 180 | E26: =LEFT(B26,FIND("[",B26) - 2) -> iPhone 11 | F26: Аккумулятор | G26: iPhone 11 - Банка АКБ с комплектом наклеек без шлейфа | I26: 399 | M26: 399 | N26: 0.12 | O26: 450 | Q26: =P25 -> 900 | R26: https://icomponents.ru/catalog/iphone/iphone_11/iphone_11_banka_akb_s_komplektom_nakleek_bez_shleyfa/ | S26: 46140.381 | U26: =IF(I26>0, Q26 - I26, "нет з/ч") -> 501 | V26: =IF(L26>0, Q26 - L26, "нет з/ч") -> нет з/ч | X26: 399 | AA26: 37706 712 | AB26: 37706 712 | AD26: 37706 712 | AE26: iPhone 11 [BAT] Аккумулятор - Банка ORIG | AG26: pcs | AH26: Сервис > Ремонт Apple > Ремонт iPhone > 11 | AI26: 180 | AJ26: дн | AK26: да | AL26: нет | AU26: 399 | AV26: 900
B27: iPhone 11 Pro [BAT] Аккумулятор - Аналог ORIG (неизвестная деталь) | C27: 22608 232 | D27: 180 | E27: =LEFT(B27,FIND("[",B27) - 2) -> iPhone 11 Pro | F27: Аккумулятор | G27: iPhone 11 Pro - Аккумуляторная батарея + скотч (АКБ), ORIG | I27: 950 | L27: 950 | M27: 950 | N27: 0.48 | O27: 1400 | P27: =O27 -> 1400 | Q27: =P27 -> 1400 | R27: https://icomponents.ru/catalog/iphone/iphone_11_pro/iphone_11_pro_akkumulyatornaya_batareya_skotch_akb_orig/ | S27: 46140.381 | U27: =IF(I27>0, Q27 - I27, "нет з/ч") -> 450 | V27: =IF(L27>0, Q27 - L27, "нет з/ч") -> 450 | X27: 950 | Y27: 950 | AA27: 22608 232 | AB27: 22608 232 | AD27: 22608 232 | AE27: iPhone 11 Pro [BAT] Аккумулятор - Аналог ORIG (неизвестная деталь) | AG27: pcs | AH27: Сервис > Ремонт Apple > Ремонт iPhone > 11 Pro | AI27: 180 | AJ27: дн | AK27: да | AL27: нет | AU27: 950 | AV27: 1400
B28: iPhone 11 Pro [BAT] Аккумулятор - Банка ORIG | C28: 25246 105 | D28: 180 | E28: =LEFT(B28,FIND("[",B28) - 2) -> iPhone 11 Pro | F28: Аккумулятор | G28: iPhone 11 Pro - Банка АКБ с комплектом наклеек без шлейфа | I28: 650 | M28: 650 | N28: 0.12 | O28: 750 | Q28: =P27 -> 1400 | R28: https://icomponents.ru/catalog/iphone/iphone_11_pro/iphone_11_pro_banka_akb_s_komplektom_nakleek_bez_shleyfa/ | S28: 46140.381 | U28: =IF(I28>0, Q28 - I28, "нет з/ч") -> 750 | V28: =IF(L28>0, Q28 - L28, "нет з/ч") -> нет з/ч | X28: 650 | AA28: 25246 105 | AB28: 25246 105 | AD28: 25246 105 | AE28: iPhone 11 Pro [BAT] Аккумулятор - Банка ORIG | AG28: pcs | AH28: Сервис > Ремонт Apple > Ремонт iPhone > 11 Pro | AI28: 180 | AJ28: дн | AK28: да | AL28: нет | AU28: 650 | AV28: 1400
B29: iPhone 11 Pro Max [BAT] Аккумулятор - Аналог ORIG (неизвестная деталь) | C29: 25246 314 | D29: 180 | E29: =LEFT(B29,FIND("[",B29) - 2) -> iPhone 11 Pro Max | F29: Аккумулятор | G29: iPhone 11 Pro Max - Аккумуляторная батарея + скотч (АКБ), ORIG | I29: 990 | L29: 990 | M29: 990 | N29: 0.43 | O29: 1400 | P29: =O29 -> 1400 | Q29: =P29 -> 1400 | R29: https://icomponents.ru/catalog/iphone/iphone_11_pro_max/iphone_11_pro_max_akkumulyatornaya_batareya_skotch_akb_orig/ | S29: 46140.381 | U29: =IF(I29>0, Q29 - I29, "нет з/ч") -> 410 | V29: =IF(L29>0, Q29 - L29, "нет з/ч") -> 410 | X29: 990 | Y29: 990 | AA29: 25246 314 | AB29: 25246 314 | AD29: 25246 314 | AE29: iPhone 11 Pro Max [BAT] Аккумулятор - Аналог ORIG (неизвестная деталь) | AG29: pcs | AH29: Сервис > Ремонт Apple > Ремонт iPhone > 11 Pro Max | AI29: 180 | AJ29: дн | AK29: да | AL29: нет | AU29: 990 | AV29: 1400
B30: iPhone 11 Pro Max [BAT] Аккумулятор - Банка ORIG | C30: 25246 276 | D30: 180 | E30: =LEFT(B30,FIND("[",B30) - 2) -> iPhone 11 Pro Max | F30: Аккумулятор | G30: iPhone 11 Pro Max - Банка АКБ с комплектом наклеек без шлейфа | I30: 650 | M30: 650 | N30: 0.12 | O30: 750 | Q30: =P29 -> 1400 | R30: https://icomponents.ru/catalog/iphone/iphone_11_pro_max/iphone_11_pro_max_banka_akb_s_komplektom_nakleek_bez_shleyfa/ | S30: 46140.381 | U30: =IF(I30>0, Q30 - I30, "нет з/ч") -> 750 | V30: =IF(L30>0, Q30 - L30, "нет з/ч") -> нет з/ч | X30: 650 | AA30: 25246 276 | AB30: 25246 276 | AD30: 25246 276 | AE30: iPhone 11 Pro Max [BAT] Аккумулятор - Банка ORIG | AG30: pcs | AH30: Сервис > Ремонт Apple > Ремонт iPhone > 11 Pro Max | AI30: 180 | AJ30: дн | AK30: да | AL30: нет | AU30: 650 | AV30: 1400
B31: iPhone 12 / 12 Pro [BAT] Аккумулятор - Сервисный оригинал (подлинное) | C31: 56218 909 | D31: 180 | E31: =LEFT(B31,FIND("[",B31) - 2) -> iPhone 12 / 12 Pro | F31: Аккумулятор | G31: iPhone 12 / 12 Pro - Аккумуляторная батарея (АКБ) Service Pack ORIG | I31: 5500 | M31: 5500 | N31: 0.2 | O31: 6600 | P31: =O31 -> 6600 | Q31: =P31 -> 6600 | R31: https://icomponents.ru/catalog/iphone/iphone_12_pro/iphone_12_12_pro_akkumulyatornaya_batareya_akb_service_pack_orig/ | S31: 46140.381 | U31: =IF(I31>0, Q31 - I31, "нет з/ч") -> 1100 | V31: =IF(L31>0, Q31 - L31, "нет з/ч") -> нет з/ч | X31: 5500 | AA31: 56218 909 | AB31: 56218 909 | AD31: 56218 909 | AE31: iPhone 12 / 12 Pro [BAT] Аккумулятор - Сервисный оригинал (подлинное) | AG31: pcs | AH31: Сервис > Ремонт Apple > Ремонт iPhone > 12 | AI31: 180 | AJ31: дн | AK31: да | AL31: нет | AU31: 5500 | AV31: 6600
B32: iPhone 12 / 12 Pro [BAT] Аккумулятор - Снятый оригинал (бу) | C32: 50284 788 | D32: 180 | E32: =LEFT(B32,FIND("[",B32) - 2) -> iPhone 12 / 12 Pro | F32: Аккумулятор | G32: iPhone 12/12 Pro - Аккумулятор снятый ORIG (привязка б/у, 100% емкость) | I32: 2300 | M32: 2300 | N32: 0.3 | O32: 3000 | P32: =O32 -> 3000 | Q32: =P32 -> 3000 | R32: https://icomponents.ru/catalog/iphone/iphone_12_pro/iphone_12_12_pro_akkumulyator_snyatyy_orig_privyazka_b_u_100_emkost/ | S32: 46140.381 | U32: =IF(I32>0, Q32 - I32, "нет з/ч") -> 700 | V32: =IF(L32>0, Q32 - L32, "нет з/ч") -> нет з/ч | X32: 2300 | AA32: 50284 788 | AB32: 50284 788 | AD32: 50284 788 | AE32: iPhone 12 / 12 Pro [BAT] Аккумулятор - Снятый оригинал (бу) | AG32: pcs | AH32: Сервис > Ремонт Apple > Ремонт iPhone > 12 | AI32: 180 | AJ32: дн | AK32: да | AL32: нет | AU32: 2300 | AV32: 3000
B33: iPhone 12 / 12 Pro [BAT] Аккумулятор - Аналог ORIG (подлинное) | D33: 180 | E33: =LEFT(B33,FIND("[",B33) - 2) -> iPhone 12 / 12 Pro | F33: Аккумулятор | G33: iPhone 12 / 12 Pro - Аккумулятор (Подлинная деталь / GENUINE NEW) повышенная емкость 3320 mAh | I33: 1850 | L33: 1950 | M33: 1950 | N33: 0.27 | O33: 2500 | P33: =O33 -> 2500 | Q33: =P33 -> 2500 | R33: https://icomponents.ru/catalog/iphone/iphone_12/iphone_12_12_pro_akkumulyator_podlinnaya_detal_genuine_new_povyshennaya_emkost_3320_mah/ | S33: 46140.381 | U33: =IF(I33>0, Q33 - I33, "нет з/ч") -> 650 | V33: =IF(L33>0, Q33 - L33, "нет з/ч") -> 550 | X33: 1850 | Y33: 1950 | AE33: iPhone 12 / 12 Pro [BAT] Аккумулятор - Аналог ORIG (подлинное) | AG33: pcs | AH33: Сервис > Ремонт Apple > Ремонт iPhone > 12 | AI33: 180 | AJ33: дн | AK33: да | AL33: нет | AU33: 1950 | AV33: 2500
B34: iPhone 12 / 12 Pro [BAT] Аккумулятор - Аналог ORIG (бу) | C34: 53722 989 | D34: 180 | E34: =LEFT(B34,FIND("[",B34) - 2) -> iPhone 12 / 12 Pro | F34: Аккумулятор | G34: iPhone 12 / 12 Pro - Аккумулятор (АКБ) PREMIUM CLEAN (iOS 18-26) | I34: 1000 | L34: 1090 | M34: 1090 | N34: 0.38 | O34: 1500 | P34: =O34 -> 1500 | Q34: =P34 -> 1500 | R34: https://icomponents.ru/catalog/iphone/iphone_12_pro/iphone_12_12_pro_akkumulyator_akb_premium_clean_ios_18_26/ | S34: 46140.381 | U34: =IF(I34>0, Q34 - I34, "нет з/ч") -> 500 | V34: =IF(L34>0, Q34 - L34, "нет з/ч") -> 410 | X34: 1000 | Y34: 1090 | AA34: 53722 989 | AB34: 53722 989 | AD34: 53722 989 | AE34: iPhone 12 / 12 Pro [BAT] Аккумулятор - Аналог ORIG (бу) | AG34: pcs | AH34: Сервис > Ремонт Apple > Ремонт iPhone > 12 | AI34: 180 | AJ34: дн | AK34: да | AL34: нет | AU34: 1090 | AV34: 1500
B35: iPhone 12 / 12 Pro [BAT] Аккумулятор - Аналог ORIG (неизвестная деталь) | C35: 25533 073 | D35: 180 | E35: =LEFT(B35,FIND("[",B35) - 2) -> iPhone 12 / 12 Pro | F35: Аккумулятор | G35: iPhone 12/12 Pro - Аккумуляторная батарея + скотч (АКБ), ORIG | I35: 800 | L35: 850 | M35: 850 | N35: 0.2 | O35: 1000 | P35: =O35 -> 1000 | Q35: =P35 -> 1000 | R35: https://icomponents.ru/catalog/iphone/iphone_12_pro/iphone_12_12_pro_akkumulyatornaya_batareya_skotch_akb_orig/ | S35: 46140.381 | U35: =IF(I35>0, Q35 - I35, "нет з/ч") -> 200 | V35: =IF(L35>0, Q35 - L35, "нет з/ч") -> 150 | X35: 800 | Y35: 850 | AA35: 25533 073 | AB35: 25533 073 | AD35: 25533 073 | AE35: iPhone 12 / 12 Pro [BAT] Аккумулятор - Аналог ORIG (неизвестная деталь) | AG35: pcs | AH35: Сервис > Ремонт Apple > Ремонт iPhone > 12 | AI35: 180 | AJ35: дн | AK35: да | AL35: нет | AU35: 850 | AV35: 1000
B36: iPhone 12 / 12 Pro [BAT] Аккумулятор - Банка ORIG | C36: 34675 484 | D36: 180 | E36: =LEFT(B36,FIND("[",B36) - 2) -> iPhone 12 / 12 Pro | F36: Аккумулятор | G36: iPhone 12/12 Pro - Банка АКБ с комплектом наклеек без шлейфа | I36: 499 | M36: 499 | N36: 0.12 | O36: 550 | Q36: =P35 -> 1000 | R36: https://icomponents.ru/catalog/iphone/iphone_12/iphone_12_12_pro_banka_akb_s_komplektom_nakleek_bez_shleyfa/ | S36: 46140.381 | U36: =IF(I36>0, Q36 - I36, "нет з/ч") -> 501 | V36: =IF(L36>0, Q36 - L36, "нет з/ч") -> нет з/ч | X36: 499 | AA36: 34675 484 | AB36: 34675 484 | AD36: 34675 484 | AE36: iPhone 12 / 12 Pro [BAT] Аккумулятор - Банка ORIG | AG36: pcs | AH36: Сервис > Ремонт Apple > Ремонт iPhone > 12 | AI36: 180 | AJ36: дн | AK36: да | AL36: нет | AU36: 499 | AV36: 1000
B37: iPhone 12 Mini [BAT] Аккумулятор - Сервисный оригинал (подлинное) | C37: 56218 967 | D37: 180 | E37: =LEFT(B37,FIND("[",B37) - 2) -> iPhone 12 Mini | F37: Аккумулятор | G37: iPhone 12 mini - Аккумуляторная батарея (АКБ) Service Pack ORIG | I37: 4800 | M37: 4800 | N37: 0.2 | O37: 5750 | P37: =O37 -> 5750 | Q37: =P37 -> 5750 | R37: https://icomponents.ru/catalog/iphone/iphone_12_mini/iphone_12_mini_akkumulyatornaya_batareya_akb_service_pack_orig/ | S37: 46140.381 | U37: =IF(I37>0, Q37 - I37, "нет з/ч") -> 950 | V37: =IF(L37>0, Q37 - L37, "нет з/ч") -> нет з/ч | X37: 4800 | AA37: 56218 967 | AB37: 56218 967 | AD37: 56218 967 | AE37: iPhone 12 Mini [BAT] Аккумулятор - Сервисный оригинал (подлинное) | AG37: pcs | AH37: Сервис > Ремонт Apple > Ремонт iPhone > 12 Mini | AI37: 180 | AJ37: дн | AK37: да | AL37: нет | AU37: 4800 | AV37: 5750
B38: iPhone 12 Mini [BAT] Аккумулятор - Аналог ORIG (подлинное) | D38: 180 | E38: =LEFT(B38,FIND("[",B38) - 2) -> iPhone 12 Mini | F38: Аккумулятор | G38: iPhone 12 mini - Аккумулятор (Подлинная деталь / GENUINE NEW) повышенная емкость 2520 mAh | I38: 2000 | L38: 1890 | M38: 2000 | N38: 0.2 | O38: 2400 | P38: =O38 -> 2400 | Q38: =P38 -> 2400 | R38: https://icomponents.ru/catalog/iphone/iphone_12_mini/iphone_12_mini_akkumulyator_podlinnaya_detal_genuine_new_povyshennaya_emkost_2520_mah/ | S38: 46140.381 | U38: =IF(I38>0, Q38 - I38, "нет з/ч") -> 400 | V38: =IF(L38>0, Q38 - L38, "нет з/ч") -> 510 | X38: 2000 | Y38: 1890 | AE38: iPhone 12 Mini [BAT] Аккумулятор - Аналог ORIG (подлинное) | AG38: pcs | AH38: Сервис > Ремонт Apple > Ремонт iPhone > 12 Mini | AI38: 180 | AJ38: дн | AK38: да | AL38: нет | AU38: 2000 | AV38: 2400
B39: iPhone 12 Mini [BAT] Аккумулятор - Аналог ORIG (бу) | C39: 55547 035 | D39: 180 | E39: =LEFT(B39,FIND("[",B39) - 2) -> iPhone 12 Mini | F39: Аккумулятор | G39: iPhone 12 mini - Аккумулятор (АКБ) PREMIUM CLEAN (iOS 18-26) | I39: 1000 | L39: 1050 | M39: 1050 | N39: 0.35 | O39: 1400 | P39: =O39 -> 1400 | Q39: =P39 -> 1400 | R39: https://icomponents.ru/catalog/iphone/iphone_12_mini/iphone_12_mini_akkumulyator_akb_premium_clean_ios_18_26/ | S39: 46140.381 | U39: =IF(I39>0, Q39 - I39, "нет з/ч") -> 400 | V39: =IF(L39>0, Q39 - L39, "нет з/ч") -> 350 | X39: 1000 | Y39: 1050 | AA39: 55547 035 | AB39: 55547 035 | AD39: 55547 035 | AE39: iPhone 12 Mini [BAT] Аккумулятор - Аналог ORIG (бу) | AG39: pcs | AH39: Сервис > Ремонт Apple > Ремонт iPhone > 12 Mini | AI39: 180 | AJ39: дн | AK39: да | AL39: нет | AU39: 1050 | AV39: 1400
B40: iPhone 12 Mini [BAT] Аккумулятор - Аналог ORIG (неизвестная деталь) | C40: 25533007 | D40: 180 | E40: =LEFT(B40,FIND("[",B40) - 2) -> iPhone 12 Mini | F40: Аккумулятор | G40: iPhone 12 mini - Аккумуляторная батарея + скотч (АКБ), ORIG | I40: 800 | L40: 750 | M40: 800 | N40: 0.15 | O40: 900 | P40: =O40 -> 900 | Q40: =P40 -> 900 | R40: https://icomponents.ru/catalog/iphone/iphone_12_mini/iphone_12_mini_akkumulyatornaya_batareya_skotch_akb_orig/ | S40: 46140.381 | U40: =IF(I40>0, Q40 - I40, "нет з/ч") -> 100 | V40: =IF(L40>0, Q40 - L40, "нет з/ч") -> 150 | X40: 800 | Y40: 750 | AA40: 25533007 | AB40: 25533007 | AD40: 25533007 | AE40: iPhone 12 Mini [BAT] Аккумулятор - Аналог ORIG (неизвестная деталь) | AG40: pcs | AH40: Сервис > Ремонт Apple > Ремонт iPhone > 12 Mini | AI40: 180 | AJ40: дн | AK40: да | AL40: нет | AU40: 800 | AV40: 900
B41: iPhone 12 Mini [BAT] Аккумулятор - Банка ORIG | C41: 34675 511 | D41: 180 | E41: =LEFT(B41,FIND("[",B41) - 2) -> iPhone 12 Mini | F41: Аккумулятор | G41: iPhone 12 mini - Банка АКБ с комплектом наклеек без шлейфа | I41: 440 | M41: 440 | N41: 0.12 | O41: 500 | Q41: =P40 -> 900 | R41: https://icomponents.ru/catalog/iphone/iphone_12_mini/iphone_12_mini_banka_akb_s_komplektom_nakleek_bez_shleyfa/ | S41: 46140.381 | U41: =IF(I41>0, Q41 - I41, "нет з/ч") -> 460 | V41: =IF(L41>0, Q41 - L41, "нет з/ч") -> нет з/ч | X41: 440 | AA41: 34675 511 | AB41: 34675 511 | AD41: 34675 511 | AE41: iPhone 12 Mini [BAT] Аккумулятор - Банка ORIG | AG41: pcs | AH41: Сервис > Ремонт Apple > Ремонт iPhone > 12 Mini | AI41: 180 | AJ41: дн | AK41: да | AL41: нет | AU41: 440 | AV41: 900
B42: iPhone 12 Pro Max [BAT] Аккумулятор - Сервисный оригинал (подлинное) | C42: 50284 805 | D42: 180 | E42: =LEFT(B42,FIND("[",B42) - 2) -> iPhone 12 Pro Max | F42: Аккумулятор | G42: iPhone 12 Pro Max - Аккумуляторная батарея (АКБ) Service Pack ORIG | I42: 6100 | M42: 6100 | N42: 0.2 | O42: 7300 | P42: =O42 -> 7300 | Q42: =P42 -> 7300 | R42: https://icomponents.ru/catalog/iphone/iphone_12_pro_max/iphone_12_pro_max_akkumulyatornaya_batareya_akb_service_pack_orig/ | S42: 46147.608 | U42: =IF(I42>0, Q42 - I42, "нет з/ч") -> 1200 | V42: =IF(L42>0, Q42 - L42, "нет з/ч") -> нет з/ч | X42: 6100 | AA42: 50284 805 | AB42: 50284 805 | AD42: 50284 805 | AE42: iPhone 12 Pro Max [BAT] Аккумулятор - Сервисный оригинал (подлинное) | AG42: pcs | AH42: Сервис > Ремонт Apple > Ремонт iPhone > 12 Pro Max | AI42: 180 | AJ42: дн | AK42: да | AL42: нет | AU42: 6100 | AV42: 7300
B43: iPhone 12 Pro Max [BAT] Аккумулятор - Снятый оригинал (бу) | C43: 56226 358 | D43: 180 | E43: =LEFT(B43,FIND("[",B43) - 2) -> iPhone 12 Pro Max | F43: Аккумулятор | G43: iPhone 12 Pro Max - Аккумулятор снятый ORIG (привязка б/у, 100% емкость) | I43: 1990 | M43: 1990 | N43: 0.8 | O43: 3600 | P43: =O43 -> 3600 | Q43: =P43 -> 3600 | R43: https://icomponents.ru/catalog/iphone/iphone_12_pro_max/iphone_12_pro_max_akkumulyator_snyatyy_orig_privyazka_b_u_100_emkost/ | S43: 46147.608 | U43: =IF(I43>0, Q43 - I43, "нет з/ч") -> 1610 | V43: =IF(L43>0, Q43 - L43, "нет з/ч") -> нет з/ч | X43: 1990 | AA43: 56226 358 | AB43: 56226 358 | AD43: 56226 358 | AE43: iPhone 12 Pro Max [BAT] Аккумулятор - Снятый оригинал (бу) | AG43: pcs | AH43: Сервис > Ремонт Apple > Ремонт iPhone > 12 Pro Max | AI43: 180 | AJ43: дн | AK43: да | AL43: нет | AU43: 1990 | AV43: 3600
B44: iPhone 12 Pro Max [BAT] Аккумулятор - Аналог ORIG (подлинное) | D44: 180 | E44: =LEFT(B44,FIND("[",B44) - 2) -> iPhone 12 Pro Max | F44: Аккумулятор | G44: iPhone 12 Pro Max - Аккумулятор (Подлинная деталь / GENUINE NEW) повышенная емкость 4420 mAh | I44: 2400 | L44: 2390 | M44: 2400 | N44: 0.3 | O44: 3100 | P44: =O44 -> 3100 | Q44: =P44 -> 3100 | R44: https://icomponents.ru/catalog/iphone/iphone_12_pro_max/iphone_12_pro_max_akkumulyator_podlinnaya_detal_genuine_new_povyshennaya_emkost_4420_mah/ | S44: 46147.608 | U44: =IF(I44>0, Q44 - I44, "нет з/ч") -> 700 | V44: =IF(L44>0, Q44 - L44, "нет з/ч") -> 710 | X44: 2400 | Y44: 2390 | AE44: iPhone 12 Pro Max [BAT] Аккумулятор - Аналог ORIG (подлинное) | AG44: pcs | AH44: Сервис > Ремонт Apple > Ремонт iPhone > 12 Pro Max | AI44: 180 | AJ44: дн | AK44: да | AL44: нет | AU44: 2400 | AV44: 3100
B45: iPhone 12 Pro Max [BAT] Аккумулятор - Аналог ORIG (бу) | C45: 56226 385 | D45: 180 | E45: =LEFT(B45,FIND("[",B45) - 2) -> iPhone 12 Pro Max | F45: Аккумулятор | G45: iPhone 12 Pro Max - Аккумулятор (АКБ) PREMIUM CLEAN (iOS 18-26) | I45: 1200 | L45: 1350 | M45: 1350 | N45: 0.55 | O45: 2100 | P45: =O45 -> 2100 | Q45: =P45 -> 2100 | R45: https://icomponents.ru/catalog/iphone/iphone_12_pro_max/iphone_12_pro_max_akkumulyator_akb_premium_clean_ios_18_26/ | S45: 46147.608 | U45: =IF(I45>0, Q45 - I45, "нет з/ч") -> 900 | V45: =IF(L45>0, Q45 - L45, "нет з/ч") -> 750 | X45: 1200 | Y45: 1350 | AA45: 56226 385 | AB45: 56226 385 | AD45: 56226 385 | AE45: iPhone 12 Pro Max [BAT] Аккумулятор - Аналог ORIG (бу) | AG45: pcs | AH45: Сервис > Ремонт Apple > Ремонт iPhone > 12 Pro Max | AI45: 180 | AJ45: дн | AK45: да | AL45: нет | AU45: 1350 | AV45: 2100
B46: iPhone 12 Pro Max [BAT] Аккумулятор - Аналог ORIG (неизвестная деталь) | C46: 25532 906 | D46: 180 | E46: =LEFT(B46,FIND("[",B46) - 2) -> iPhone 12 Pro Max | F46: Аккумулятор | G46: iPhone 12 Pro Max - Аккумуляторная батарея + скотч (АКБ), ORIG | I46: 1000 | L46: 990 | M46: 1000 | N46: 0.6 | O46: 1600 | P46: =O46 -> 1600 | Q46: =P46 -> 1600 | R46: https://icomponents.ru/catalog/iphone/iphone_12_pro_max/iphone_12_pro_max_akkumulyatornaya_batareya_skotch_akb_orig/ | S46: 46147.608 | U46: =IF(I46>0, Q46 - I46, "нет з/ч") -> 600 | V46: =IF(L46>0, Q46 - L46, "нет з/ч") -> 610 | X46: 1000 | Y46: 990 | AA46: 25532 906 | AB46: 25532 906 | AD46: 25532 906 | AE46: iPhone 12 Pro Max [BAT] Аккумулятор - Аналог ORIG (неизвестная деталь) | AG46: pcs | AH46: Сервис > Ремонт Apple > Ремонт iPhone > 12 Pro Max | AI46: 180 | AJ46: дн | AK46: да | AL46: нет | AU46: 1000 | AV46: 1600
B47: iPhone 12 Pro Max [BAT] Аккумулятор - Банка ORIG | C47: 34675 452 | D47: 180 | E47: =LEFT(B47,FIND("[",B47) - 2) -> iPhone 12 Pro Max | F47: Аккумулятор | G47: iPhone 12 Pro Max - Банка АКБ с комплектом наклеек без шлейфа | I47: 690 | M47: 690 | N47: 0.12 | O47: 750 | Q47: =P46 -> 1600 | R47: https://icomponents.ru/catalog/iphone/iphone_12_pro_max/iphone_12_pro_max_banka_akb_s_komplektom_nakleek_bez_shleyfa/ | S47: 46147.608 | U47: =IF(I47>0, Q47 - I47, "нет з/ч") -> 910 | V47: =IF(L47>0, Q47 - L47, "нет з/ч") -> нет з/ч | X47: 690 | AA47: 34675 452 | AB47: 34675 452 | AD47: 34675 452 | AE47: iPhone 12 Pro Max [BAT] Аккумулятор - Банка ORIG | AG47: pcs | AH47: Сервис > Ремонт Apple > Ремонт iPhone > 12 Pro Max | AI47: 180 | AJ47: дн | AK47: да | AL47: нет | AU47: 690 | AV47: 1600
B48: iPhone 13 [BAT] Аккумулятор - Сервисный оригинал (подлинное) | C48: 50305 127 | D48: 180 | E48: =LEFT(B48,FIND("[",B48) - 2) -> iPhone 13 | F48: Аккумулятор | G48: iPhone 13 - Аккумуляторная батарея (АКБ) Service Pack ORIG | I48: 6000 | M48: 6000 | N48: 0.2 | O48: 7200 | P48: =O48 -> 7200 | Q48: =P48 -> 7200 | R48: https://icomponents.ru/catalog/iphone/iphone_13/iphone_13_akkumulyatornaya_batareya_akb_service_pack_orig/ | S48: 46140.381 | U48: =IF(I48>0, Q48 - I48, "нет з/ч") -> 1200 | V48: =IF(L48>0, Q48 - L48, "нет з/ч") -> нет з/ч | X48: 6000 | AA48: 50305 127 | AB48: 50305 127 | AD48: 50305 127 | AE48: iPhone 13 [BAT] Аккумулятор - Сервисный оригинал (подлинное) | AG48: pcs | AH48: Сервис > Ремонт Apple > Ремонт iPhone > 13 | AI48: 180 | AJ48: дн | AK48: да | AL48: нет | AU48: 6000 | AV48: 7200
B49: iPhone 13 [BAT] Аккумулятор - Снятый оригинал (бу) | C49: 56228 247 | D49: 180 | E49: =LEFT(B49,FIND("[",B49) - 2) -> iPhone 13 | F49: Аккумулятор | G49: iPhone 13 - Аккумулятор снятый ORIG (привязка б/у, 100% емкость) | I49: 2600 | M49: 2600 | N49: 0.15 | O49: 3000 | P49: =O49 -> 3000 | Q49: =P49 -> 3000 | R49: https://icomponents.ru/catalog/iphone/iphone_13/iphone_13_akkumulyator_snyatyy_orig_privyazka_b_u_100_emkost/ | S49: 46140.381 | U49: =IF(I49>0, Q49 - I49, "нет з/ч") -> 400 | V49: =IF(L49>0, Q49 - L49, "нет з/ч") -> нет з/ч | X49: 2600 | AA49: 56228 247 | AB49: 56228 247 | AD49: 56228 247 | AE49: iPhone 13 [BAT] Аккумулятор - Снятый оригинал (бу) | AG49: pcs | AH49: Сервис > Ремонт Apple > Ремонт iPhone > 13 | AI49: 180 | AJ49: дн | AK49: да | AL49: нет | AU49: 2600 | AV49: 3000
B50: iPhone 13 [BAT] Аккумулятор - Аналог ORIG (подлинное) | D50: 180 | E50: =LEFT(B50,FIND("[",B50) - 2) -> iPhone 13 | F50: Аккумулятор | G50: iPhone 13 - Аккумулятор (Подлинная деталь / GENUINE NEW) повышенная емкость 3530 mAh | I50: 1900 | L50: 1990 | M50: 1990 | N50: 0.25 | O50: 2500 | P50: =O50 -> 2500 | Q50: =P50 -> 2500 | R50: https://icomponents.ru/catalog/iphone/iphone_13/iphone_13_akkumulyator_podlinnaya_detal_genuine_new_povyshennaya_emkost_3530_mah/ | S50: 46140.381 | U50: =IF(I50>0, Q50 - I50, "нет з/ч") -> 600 | V50: =IF(L50>0, Q50 - L50, "нет з/ч") -> 510 | X50: 1900 | Y50: 1990 | AE50: iPhone 13 [BAT] Аккумулятор - Аналог ORIG (подлинное) | AG50: pcs | AH50: Сервис > Ремонт Apple > Ремонт iPhone > 13 | AI50: 180 | AJ50: дн | AK50: да | AL50: нет | AU50: 1990 | AV50: 2500
B51: iPhone 13 [BAT] Аккумулятор - Аналог ORIG (бу) | C51: 55547 200 | D51: 180 | E51: =LEFT(B51,FIND("[",B51) - 2) -> iPhone 13 | F51: Аккумулятор | G51: iPhone 13 - Аккумулятор (АКБ) PREMIUM CLEAN (iOS 18-26) | I51: 1100 | L51: 1150 | M51: 1150 | N51: 0.3 | O51: 1500 | P51: =O51 -> 1500 | Q51: =P51 -> 1500 | R51: https://icomponents.ru/catalog/iphone/iphone_13/iphone_13_akkumulyator_akb_premium_clean_ios_18_26/ | S51: 46140.381 | U51: =IF(I51>0, Q51 - I51, "нет з/ч") -> 400 | V51: =IF(L51>0, Q51 - L51, "нет з/ч") -> 350 | X51: 1100 | Y51: 1150 | AA51: 55547 200 | AB51: 55547 200 | AD51: 55547 200 | AE51: iPhone 13 [BAT] Аккумулятор - Аналог ORIG (бу) | AG51: pcs | AH51: Сервис > Ремонт Apple > Ремонт iPhone > 13 | AI51: 180 | AJ51: дн | AK51: да | AL51: нет | AU51: 1150 | AV51: 1500
B52: iPhone 13 [BAT] Аккумулятор - Аналог ORIG (неизвестная деталь) | C52: 35850 950 | D52: 180 | E52: =LEFT(B52,FIND("[",B52) - 2) -> iPhone 13 | F52: Аккумулятор | G52: iPhone 13 - Аккумуляторная батарея + скотч (АКБ), ORIG | I52: 850 | L52: 890 | M52: 890 | N52: 0.15 | O52: 1000 | P52: =O52 -> 1000 | Q52: =P52 -> 1000 | R52: https://icomponents.ru/catalog/iphone/iphone_13/iphone_13_akkumulyatornaya_batareya_skotch_akb_orig/ | S52: 46140.381 | U52: =IF(I52>0, Q52 - I52, "нет з/ч") -> 150 | V52: =IF(L52>0, Q52 - L52, "нет з/ч") -> 110 | X52: 850 | Y52: 890 | AA52: 35850 950 | AB52: 35850 950 | AD52: 35850 950 | AE52: iPhone 13 [BAT] Аккумулятор - Аналог ORIG (неизвестная деталь) | AG52: pcs | AH52: Сервис > Ремонт Apple > Ремонт iPhone > 13 | AI52: 180 | AJ52: дн | AK52: да | AL52: нет | AU52: 890 | AV52: 1000
B53: iPhone 13 [BAT] Аккумулятор - Банка ORIG | C53: 41401 014 | D53: 180 | E53: =LEFT(B53,FIND("[",B53) - 2) -> iPhone 13 | F53: Аккумулятор | G53: iPhone 13 - Банка АКБ с комплектом наклеек без шлейфа | I53: 550 | M53: 550 | N53: 0.12 | O53: 600 | Q53: =P52 -> 1000 | R53: https://icomponents.ru/catalog/iphone/iphone_13/iphone_13_banka_akb_s_komplektom_nakleek_bez_shleyfa/ | S53: 46140.381 | U53: =IF(I53>0, Q53 - I53, "нет з/ч") -> 450 | V53: =IF(L53>0, Q53 - L53, "нет з/ч") -> нет з/ч | X53: 550 | AA53: 41401 014 | AB53: 41401 014 | AD53: 41401 014 | AE53: iPhone 13 [BAT] Аккумулятор - Банка ORIG | AG53: pcs | AH53: Сервис > Ремонт Apple > Ремонт iPhone > 13 | AI53: 180 | AJ53: дн | AK53: да | AL53: нет | AU53: 550 | AV53: 1000
B54: iPhone 13 Mini [BAT] Аккумулятор - Сервисный оригинал (подлинное) | C54: 56219 061 | D54: 180 | E54: =LEFT(B54,FIND("[",B54) - 2) -> iPhone 13 Mini | F54: Аккумулятор | G54: iPhone 13 mini - Аккумуляторная батарея (АКБ) Service Pack ORIG | I54: 6900 | M54: 6900 | N54: 0.2 | O54: 8300 | P54: =O54 -> 8300 | Q54: =P54 -> 8300 | R54: https://icomponents.ru/catalog/iphone/iphone_13_mini/iphone_13_mini_akkumulyatornaya_batareya_akb_service_pack_orig/ | S54: 46140.381 | U54: =IF(I54>0, Q54 - I54, "нет з/ч") -> 1400 | V54: =IF(L54>0, #REF! - L54, "нет з/ч") -> нет з/ч | X54: 6900 | AA54: 56219 061 | AB54: 56219 061 | AD54: 56219 061 | AE54: iPhone 13 Mini [BAT] Аккумулятор - Сервисный оригинал (подлинное) | AG54: pcs | AH54: Сервис > Ремонт Apple > Ремонт iPhone > 13 Mini | AI54: 180 | AJ54: дн | AK54: да | AL54: нет | AU54: 6900 | AV54: 8300
B55: iPhone 13 Mini [BAT] Аккумулятор - Аналог ORIG (подлинное) | D55: 180 | E55: =LEFT(B55,FIND("[",B55) - 2) -> iPhone 13 Mini | F55: Аккумулятор | G55: iPhone 13 mini - Аккумулятор (Подлинная деталь / GENUINE NEW) повышенная емкость 2580 mAh | I55: 1850 | L55: 1950 | M55: 1950 | N55: 0.28 | O55: 2500 | P55: =O55 -> 2500 | Q55: =P55 -> 2500 | R55: https://icomponents.ru/catalog/iphone/iphone_13_mini/iphone_13_mini_akkumulyator_podlinnaya_detal_genuine_new_povyshennaya_emkost_2580_mah/ | S55: 46140.381 | U55: =IF(I55>0, Q55 - I55, "нет з/ч") -> 650 | V55: =IF(L55>0, #REF! - L55, "нет з/ч") -> #REF! | X55: 1850 | Y55: 1950 | AE55: iPhone 13 Mini [BAT] Аккумулятор - Аналог ORIG (подлинное) | AG55: pcs | AH55: Сервис > Ремонт Apple > Ремонт iPhone > 13 Mini | AI55: 180 | AJ55: дн | AK55: да | AL55: нет | AU55: 1950 | AV55: 2500
B56: iPhone 13 Mini [BAT] Аккумулятор - Аналог ORIG (бу) | C56: 55547 110 | D56: 180 | E56: =LEFT(B56,FIND("[",B56) - 2) -> iPhone 13 Mini | F56: Аккумулятор | G56: iPhone 13 mini - Аккумулятор (АКБ) PREMIUM CLEAN (iOS 18-26) | I56: 1050 | L56: 1090 | M56: 1090 | N56: 0.38 | O56: 1500 | P56: =O56 -> 1500 | Q56: =P56 -> 1500 | R56: https://icomponents.ru/catalog/iphone/iphone_13_mini/iphone_13_mini_akkumulyator_akb_premium_clean_ios_18_26/ | S56: 46140.381 | U56: =IF(I56>0, Q56 - I56, "нет з/ч") -> 450 | V56: =IF(L56>0, Q349 - L56, "нет з/ч") -> 910 | X56: 1050 | Y56: 1090 | AA56: 55547 110 | AB56: 55547 110 | AD56: 55547 110 | AE56: iPhone 13 Mini [BAT] Аккумулятор - Аналог ORIG (бу) | AG56: pcs | AH56: Сервис > Ремонт Apple > Ремонт iPhone > 13 Mini | AI56: 180 | AJ56: дн | AK56: да | AL56: нет | AU56: 1090 | AV56: 1500
B57: iPhone 13 Mini [BAT] Аккумулятор - Аналог ORIG (неизвестная деталь) | C57: 41889 442 | D57: 180 | E57: =LEFT(B57,FIND("[",B57) - 2) -> iPhone 13 Mini | F57: Аккумулятор | G57: iPhone 13 mini - Аккумуляторная батарея + скотч (АКБ), ORIG | I57: 850 | L57: 790 | M57: 850 | N57: 0.15 | O57: 1000 | P57: =O57 -> 1000 | Q57: =P57 -> 1000 | R57: https://icomponents.ru/catalog/iphone/iphone_13_mini/iphone_13_mini_akkumulyatornaya_batareya_skotch_akb_orig/ | S57: 46140.381 | U57: =IF(I57>0, Q57 - I57, "нет з/ч") -> 150 | V57: =IF(L57>0, Q353 - L57, "нет з/ч") -> 1210 | X57: 850 | Y57: 790 | AA57: 41889 442 | AB57: 41889 442 | AD57: 41889 442 | AE57: iPhone 13 Mini [BAT] Аккумулятор - Аналог ORIG (неизвестная деталь) | AG57: pcs | AH57: Сервис > Ремонт Apple > Ремонт iPhone > 13 Mini | AI57: 180 | AJ57: дн | AK57: да | AL57: нет | AU57: 850 | AV57: 1000
B58: iPhone 13 Mini [BAT] Аккумулятор - Банка ORIG | C58: 41400 944 | D58: 180 | E58: =LEFT(B58,FIND("[",B58) - 2) -> iPhone 13 Mini | F58: Аккумулятор | G58: iPhone 13 mini - Банка АКБ с комплектом наклеек без шлейфа | I58: 499 | M58: 499 | N58: 0.12 | O58: 550 | Q58: =P57 -> 1000 | R58: https://icomponents.ru/catalog/iphone/iphone_13_mini/iphone_13_mini_banka_akb_s_komplektom_nakleek_bez_shleyfa/ | S58: 46140.381 | U58: =IF(I58>0, Q58 - I58, "нет з/ч") -> 501 | V58: =IF(L58>0, #REF! - L58, "нет з/ч") -> нет з/ч | X58: 499 | AA58: 41400 944 | AB58: 41400 944 | AD58: 41400 944 | AE58: iPhone 13 Mini [BAT] Аккумулятор - Банка ORIG | AG58: pcs | AH58: Сервис > Ремонт Apple > Ремонт iPhone > 13 Mini | AI58: 180 | AJ58: дн | AK58: да | AL58: нет | AU58: 499 | AV58: 1000
B59: iPhone 13 Pro [BAT] Аккумулятор - Сервисный оригинал (подлинное) | C59: 56229 689 | D59: 180 | E59: =LEFT(B59,FIND("[",B59) - 2) -> iPhone 13 Pro | F59: Аккумулятор | G59: iPhone 13 Pro - Аккумуляторная батарея (АКБ) Service Pack ORIG | I59: 6900 | M59: 6900 | N59: 0.2 | O59: 8300 | P59: =O59 -> 8300 | Q59: =P59 -> 8300 | R59: https://icomponents.ru/catalog/iphone/iphone_13_pro/iphone_13_pro_akkumulyatornaya_batareya_akb_service_pack_orig/ | S59: 46140.381 | U59: =IF(I59>0, Q59 - I59, "нет з/ч") -> 1400 | V59: =IF(L59>0, Q357 - L59, "нет з/ч") -> нет з/ч | X59: 6900 | AA59: 56229 689 | AB59: 56229 689 | AD59: 56229 689 | AE59: iPhone 13 Pro [BAT] Аккумулятор - Сервисный оригинал (подлинное) | AG59: pcs | AH59: Сервис > Ремонт Apple > Ремонт iPhone > 13 Pro | AI59: 180 | AJ59: дн | AK59: да | AL59: нет | AU59: 6900 | AV59: 8300
B60: iPhone 13 Pro [BAT] Аккумулятор - Снятый оригинал (бу) | C60: 50305 981 | D60: 180 | E60: =LEFT(B60,FIND("[",B60) - 2) -> iPhone 13 Pro | F60: Аккумулятор | G60: iPhone 13 Pro - Аккумулятор снятый ORIG (привязка б/у, 100% емкость) | I60: 4000 | M60: 4000 | N60: 0.12 | O60: 4500 | P60: =O60 -> 4500 | Q60: =P60 -> 4500 | R60: https://icomponents.ru/catalog/iphone/iphone_13_pro/iphone_13_pro_akkumulyator_snyatyy_orig_privyazka_b_u_100_emkost/ | S60: 46140.381 | U60: =IF(I60>0, Q60 - I60, "нет з/ч") -> 500 | V60: =IF(L60>0, #REF! - L60, "нет з/ч") -> нет з/ч | X60: 4000 | AA60: 50305 981 | AB60: 50305 981 | AD60: 50305 981 | AE60: iPhone 13 Pro [BAT] Аккумулятор - Снятый оригинал (бу) | AG60: pcs | AH60: Сервис > Ремонт Apple > Ремонт iPhone > 13 Pro | AI60: 180 | AJ60: дн | AK60: да | AL60: нет | AU60: 4000 | AV60: 4500
B61: iPhone 13 Pro [BAT] Аккумулятор - Аналог ORIG (подлинное) | D61: 180 | E61: =LEFT(B61,FIND("[",B61) - 2) -> iPhone 13 Pro | F61: Аккумулятор | G61: iPhone 13 Pro - Аккумулятор (Подлинная деталь / GENUINE NEW) повышенная емкость 3300 mAh | I61: 2450 | L61: 2390 | M61: 2450 | N61: 0.15 | O61: 2800 | P61: =O61 -> 2800 | Q61: =P61 -> 2800 | R61: https://icomponents.ru/catalog/iphone/iphone_13_pro/iphone_13_pro_akkumulyator_podlinnaya_detal_genuine_new_povyshennaya_emkost_3300_mah/ | S61: 46140.381 | U61: =IF(I61>0, Q61 - I61, "нет з/ч") -> 350 | V61: =IF(L61>0, #REF! - L61, "нет з/ч") -> #REF! | X61: 2450 | Y61: 2390 | AE61: iPhone 13 Pro [BAT] Аккумулятор - Аналог ORIG (подлинное) | AG61: pcs | AH61: Сервис > Ремонт Apple > Ремонт iPhone > 13 Pro | AI61: 180 | AJ61: дн | AK61: да | AL61: нет | AU61: 2450 | AV61: 2800
B62: iPhone 13 Pro [BAT] Аккумулятор - Аналог ORIG (бу) | C62: 53723 043 | D62: 180 | E62: =LEFT(B62,FIND("[",B62) - 2) -> iPhone 13 Pro | F62: Аккумулятор | G62: iPhone 13 Pro - Аккумулятор (АКБ) PREMIUM CLEAN (iOS 18-26) | I62: 1250 | L62: 1350 | M62: 1350 | N62: 0.25 | O62: 1700 | P62: =O62 -> 1700 | Q62: =P62 -> 1700 | R62: https://icomponents.ru/catalog/iphone/iphone_13_pro/iphone_13_pro_akkumulyator_akb_premium_clean_ios_18_26/ | S62: 46140.381 | U62: =IF(I62>0, Q62 - I62, "нет з/ч") -> 450 | V62: =IF(L62>0, Q359 - L62, "нет з/ч") -> 650 | X62: 1250 | Y62: 1350 | AA62: 53723 043 | AB62: 53723 043 | AD62: 53723 043 | AE62: iPhone 13 Pro [BAT] Аккумулятор - Аналог ORIG (бу) | AG62: pcs | AH62: Сервис > Ремонт Apple > Ремонт iPhone > 13 Pro | AI62: 180 | AJ62: дн | AK62: да | AL62: нет | AU62: 1350 | AV62: 1700
B63: iPhone 13 Pro [BAT] Аккумулятор - Аналог ORIG (неизвестная деталь) | C63: 32000 715 | D63: 180 | E63: =LEFT(B63,FIND("[",B63) - 2) -> iPhone 13 Pro | F63: Аккумулятор | G63: iPhone 13 Pro - Аккумуляторная батарея + скотч (АКБ), ORIG | I63: 990 | L63: 1050 | M63: 1050 | N63: 0.12 | O63: 1200 | P63: =O63 -> 1200 | Q63: =P63 -> 1200 | R63: https://icomponents.ru/catalog/iphone/iphone_13_pro/iphone_13_pro_akkumulyatornaya_batareya_skotch_akb_orig/ | S63: 46140.381 | U63: =IF(I63>0, Q63 - I63, "нет з/ч") -> 210 | V63: =IF(L63>0, #REF! - L63, "нет з/ч") -> #REF! | X63: 990 | Y63: 1050 | AA63: 32000 715 | AB63: 32000 715 | AD63: 32000 715 | AE63: iPhone 13 Pro [BAT] Аккумулятор - Аналог ORIG (неизвестная деталь) | AG63: pcs | AH63: Сервис > Ремонт Apple > Ремонт iPhone > 13 Pro | AI63: 180 | AJ63: дн | AK63: да | AL63: нет | AU63: 1050 | AV63: 1200
B64: iPhone 13 Pro [BAT] Аккумулятор - Банка ORIG | C64: 41400 904 | D64: 180 | E64: =LEFT(B64,FIND("[",B64) - 2) -> iPhone 13 Pro | F64: Аккумулятор | G64: iPhone 13 Pro - Банка АКБ с комплектом наклеек без шлейфа | I64: 699 | M64: 699 | N64: 0.12 | O64: 800 | Q64: =P63 -> 1200 | R64: https://icomponents.ru/catalog/iphone/iphone_13_pro/iphone_13_pro_banka_akb_s_komplektom_nakleek_bez_shleyfa/ | S64: 46140.381 | U64: =IF(I64>0, Q64 - I64, "нет з/ч") -> 501 | V64: =IF(L64>0, #REF! - L64, "нет з/ч") -> нет з/ч | X64: 699 | AA64: 41400 904 | AB64: 41400 904 | AD64: 41400 904 | AE64: iPhone 13 Pro [BAT] Аккумулятор - Банка ORIG | AG64: pcs | AH64: Сервис > Ремонт Apple > Ремонт iPhone > 13 Pro | AI64: 180 | AJ64: дн | AK64: да | AL64: нет | AU64: 699 | AV64: 1200
B65: iPhone 13 Pro Max [BAT] Аккумулятор - Сервисный оригинал (подлинное) | C65: 56229 857 | D65: 180 | E65: =LEFT(B65,FIND("[",B65) - 2) -> iPhone 13 Pro Max | F65: Аккумулятор | G65: iPhone 13 Pro Max - Аккумуляторная батарея (АКБ) Service Pack ORIG | I65: 6900 | M65: 6900 | N65: 0.2 | O65: 8300 | P65: =O65 -> 8300 | Q65: =P65 -> 8300 | R65: https://icomponents.ru/catalog/iphone/iphone_13_pro_max/iphone_13_pro_max_akkumulyatornaya_batareya_akb_service_pack_orig/ | S65: 46140.381 | U65: =IF(I65>0, Q65 - I65, "нет з/ч") -> 1400 | V65: =IF(L65>0, Q365 - L65, "нет з/ч") -> нет з/ч | X65: 6900 | AA65: 56229 857 | AB65: 56229 857 | AD65: 56229 857 | AE65: iPhone 13 Pro Max [BAT] Аккумулятор - Сервисный оригинал (подлинное) | AG65: pcs | AH65: Сервис > Ремонт Apple > Ремонт iPhone > 13 Pro Max | AI65: 180 | AJ65: дн | AK65: да | AL65: нет | AU65: 6900 | AV65: 8300
B66: iPhone 13 Pro Max [BAT] Аккумулятор - Снятый оригинал (бу) | C66: 56229 935 | D66: 180 | E66: =LEFT(B66,FIND("[",B66) - 2) -> iPhone 13 Pro Max | F66: Аккумулятор | G66: iPhone 13 Pro Max - Аккумулятор снятый ORIG (привязка б/у, 100% емкость) | I66: 4000 | M66: 4000 | N66: 0.12 | O66: 4500 | P66: =O66 -> 4500 | Q66: =P66 -> 4500 | R66: https://icomponents.ru/catalog/iphone/iphone_13_pro_max/iphone_13_pro_max_akkumulyator_snyatyy_orig_privyazka_b_u_100_emkost/ | S66: 46140.381 | U66: =IF(I66>0, Q66 - I66, "нет з/ч") -> 500 | V66: =IF(L66>0, Q366 - L66, "нет з/ч") -> нет з/ч | X66: 4000 | AA66: 56229 935 | AB66: 56229 935 | AD66: 56229 935 | AE66: iPhone 13 Pro Max [BAT] Аккумулятор - Снятый оригинал (бу) | AG66: pcs | AH66: Сервис > Ремонт Apple > Ремонт iPhone > 13 Pro Max | AI66: 180 | AJ66: дн | AK66: да | AL66: нет | AU66: 4000 | AV66: 4500
B67: iPhone 13 Pro Max [BAT] Аккумулятор - Аналог ORIG (подлинное) | D67: 180 | E67: =LEFT(B67,FIND("[",B67) - 2) -> iPhone 13 Pro Max | F67: Аккумулятор | G67: iPhone 13 Pro Max - Аккумулятор (Подлинная деталь / GENUINE NEW) повышенная емкость 4650 mAh | I67: 2500 | L67: 2590 | M67: 2590 | N67: 0.24 | O67: 3200 | P67: =O67 -> 3200 | Q67: =P67 -> 3200 | R67: https://icomponents.ru/catalog/iphone/iphone_13_pro_max/iphone_13_pro_max_akkumulyator_podlinnaya_detal_genuine_new_povyshennaya_emkost_4650_mah/ | S67: 46140.381 | U67: =IF(I67>0, Q67 - I67, "нет з/ч") -> 700 | V67: =IF(L67>0, Q367 - L67, "нет з/ч") -> -1090 | X67: 2500 | Y67: 2590 | AE67: iPhone 13 Pro Max [BAT] Аккумулятор - Аналог ORIG (подлинное) | AG67: pcs | AH67: Сервис > Ремонт Apple > Ремонт iPhone > 13 Pro Max | AI67: 180 | AJ67: дн | AK67: да | AL67: нет | AU67: 2590 | AV67: 3200
B68: iPhone 13 Pro Max [BAT] Аккумулятор - Аналог ORIG (бу) | C68: 54470 832 | D68: 180 | E68: =LEFT(B68,FIND("[",B68) - 2) -> iPhone 13 Pro Max | F68: Аккумулятор | G68: iPhone 13 Pro Max - Аккумулятор (АКБ) PREMIUM CLEAN (iOS 18-26) | I68: 1300 | L68: 1490 | M68: 1490 | N68: 0.48 | O68: 2200 | P68: =O68 -> 2200 | Q68: =P68 -> 2200 | R68: https://icomponents.ru/catalog/iphone/iphone_13_pro_max/iphone_13_pro_max_akkumulyator_akb_premium_clean_ios_18_26/ | S68: 46140.382 | U68: =IF(I68>0, Q68 - I68, "нет з/ч") -> 900 | V68: =IF(L68>0, #REF! - L68, "нет з/ч") -> #REF! | X68: 1300 | Y68: 1490 | AA68: 54470 832 | AB68: 54470 832 | AD68: 54470 832 | AE68: iPhone 13 Pro Max [BAT] Аккумулятор - Аналог ORIG (бу) | AG68: pcs | AH68: Сервис > Ремонт Apple > Ремонт iPhone > 13 Pro Max | AI68: 180 | AJ68: дн | AK68: да | AL68: нет | AU68: 1490 | AV68: 2200
B69: iPhone 13 Pro Max [BAT] Аккумулятор - Аналог ORIG (неизвестная деталь) | C69: 35850 836 | D69: 180 | E69: =LEFT(B69,FIND("[",B69) - 2) -> iPhone 13 Pro Max | F69: Аккумулятор | G69: iPhone 13 Pro Max - Аккумуляторная батарея + скотч (АКБ), ORIG | I69: 1050 | L69: 1050 | M69: 1050 | N69: 0.6 | O69: 1700 | P69: =O69 -> 1700 | Q69: =P69 -> 1700 | R69: https://icomponents.ru/catalog/iphone/iphone_13_pro_max/iphone_13_pro_max_akkumulyatornaya_batareya_skotch_akb_orig/ | S69: 46140.382 | U69: =IF(I69>0, Q69 - I69, "нет з/ч") -> 650 | V69: =IF(L69>0, Q369 - L69, "нет з/ч") -> 450 | X69: 1050 | Y69: 1050 | AA69: 35850 836 | AB69: 35850 836 | AD69: 35850 836 | AE69: iPhone 13 Pro Max [BAT] Аккумулятор - Аналог ORIG (неизвестная деталь) | AG69: pcs | AH69: Сервис > Ремонт Apple > Ремонт iPhone > 13 Pro Max | AI69: 180 | AJ69: дн | AK69: да | AL69: нет | AU69: 1050 | AV69: 1700
B70: iPhone 13 Pro Max [BAT] Аккумулятор - Банка ORIG | C70: 41307 402 | D70: 180 | E70: =LEFT(B70,FIND("[",B70) - 2) -> iPhone 13 Pro Max | F70: Аккумулятор | G70: iPhone 13 Pro Max - Банка АКБ с комплектом наклеек без шлейфа | I70: 790 | M70: 790 | N70: 0.12 | O70: 900 | Q70: =P69 -> 1700 | R70: https://icomponents.ru/catalog/iphone/iphone_13_pro_max/iphone_13_pro_max_banka_akb_s_komplektom_nakleek_bez_shleyfa/ | S70: 46140.382 | U70: =IF(I70>0, Q70 - I70, "нет з/ч") -> 910 | V70: =IF(L70>0, Q373 - L70, "нет з/ч") -> нет з/ч | X70: 790 | AA70: 41307 402 | AB70: 41307 402 | AD70: 41307 402 | AE70: iPhone 13 Pro Max [BAT] Аккумулятор - Банка ORIG | AG70: pcs | AH70: Сервис > Ремонт Apple > Ремонт iPhone > 13 Pro Max | AI70: 180 | AJ70: дн | AK70: да | AL70: нет | AU70: 790 | AV70: 1700
B71: iPhone 14 [BAT] Аккумулятор - Сервисный оригинал (подлинное) | C71: 56234 439 | D71: 180 | E71: =LEFT(B71,FIND("[",B71) - 2) -> iPhone 14 | F71: Аккумулятор | G71: iPhone 14 - Аккумуляторная батарея (АКБ) Service Pack ORIG | I71: 8000 | M71: 8000 | N71: 0.2 | O71: 9600 | P71: =O71 -> 9600 | Q71: =P71 -> 9600 | R71: https://icomponents.ru/catalog/iphone/iphone_14/iphone_14_akkumulyatornaya_batareya_akb_service_pack_orig/ | S71: 46140.382 | U71: =IF(I71>0, Q71 - I71, "нет з/ч") -> 1600 | V71: =IF(L71>0, #REF! - L71, "нет з/ч") -> нет з/ч | X71: 8000 | AA71: 56234 439 | AB71: 56234 439 | AD71: 56234 439 | AE71: iPhone 14 [BAT] Аккумулятор - Сервисный оригинал (подлинное) | AG71: pcs | AH71: Сервис > Ремонт Apple > Ремонт iPhone > 14 | AI71: 180 | AJ71: дн | AK71: да | AL71: нет | AU71: 8000 | AV71: 9600
B72: iPhone 14 [BAT] Аккумулятор - Снятый оригинал (бу) | C72: 56234 409 | D72: 180 | E72: =LEFT(B72,FIND("[",B72) - 2) -> iPhone 14 | F72: Аккумулятор | G72: iPhone 14 - Аккумулятор снятый ORIG (привязка б/у, 100% емкость) | I72: 2500 | M72: 2500 | N72: 0.68 | O72: 4200 | P72: =O72 -> 4200 | Q72: =P72 -> 4200 | R72: https://icomponents.ru/catalog/iphone/iphone_14/iphone_14_akkumulyator_snyatyy_orig_privyazka_b_u_100_emkost/ | S72: 46140.382 | U72: =IF(I72>0, Q72 - I72, "нет з/ч") -> 1700 | V72: =IF(L72>0, Q374 - L72, "нет з/ч") -> нет з/ч | X72: 2500 | AA72: 56234 409 | AB72: 56234 409 | AD72: 56234 409 | AE72: iPhone 14 [BAT] Аккумулятор - Снятый оригинал (бу) | AG72: pcs | AH72: Сервис > Ремонт Apple > Ремонт iPhone > 14 | AI72: 180 | AJ72: дн | AK72: да | AL72: нет | AU72: 2500 | AV72: 4200
B73: iPhone 14 [BAT] Аккумулятор - Аналог ORIG (подлинное) | D73: 180 | E73: =LEFT(B73,FIND("[",B73) - 2) -> iPhone 14 | F73: Аккумулятор | G73: iPhone 14 - Аккумулятор (Подлинная деталь / GENUINE NEW) повышенная емкость 3670 mAh | I73: 1900 | L73: 2090 | M73: 2090 | N73: 0.78 | O73: 3700 | P73: =O73 -> 3700 | Q73: =P73 -> 3700 | R73: https://icomponents.ru/catalog/iphone/iphone_14/iphone_14_akkumulyator_podlinnaya_detal_genuine_new_povyshennaya_emkost_3670_mah/ | S73: 46140.382 | U73: =IF(I73>0, Q73 - I73, "нет з/ч") -> 1800 | V73: =IF(L73>0, Q375 - L73, "нет з/ч") -> -390 | X73: 1900 | Y73: 2090 | AE73: iPhone 14 [BAT] Аккумулятор - Аналог ORIG (подлинное) | AG73: pcs | AH73: Сервис > Ремонт Apple > Ремонт iPhone > 14 | AI73: 180 | AJ73: дн | AK73: да | AL73: нет | AU73: 2090 | AV73: 3700
B74: iPhone 14 [BAT] Аккумулятор - Аналог ORIG (бу) | C74: 55548 939 | D74: 180 | E74: =LEFT(B74,FIND("[",B74) - 2) -> iPhone 14 | F74: Аккумулятор | G74: iPhone 14 - Аккумулятор (АКБ) PREMIUM CLEAN (iOS 18-26) | I74: 1150 | L74: 1250 | M74: 1250 | N74: 1.15 | O74: 2700 | P74: =O74 -> 2700 | Q74: =P74 -> 2700 | R74: https://icomponents.ru/catalog/iphone/iphone_14/iphone_14_akkumulyator_akb_premium_clean_ios_18_26/ | S74: 46140.382 | U74: =IF(I74>0, Q74 - I74, "нет з/ч") -> 1550 | V74: =IF(L74>0, #REF! - L74, "нет з/ч") -> #REF! | X74: 1150 | Y74: 1250 | AA74: 55548 939 | AB74: 55548 939 | AD74: 55548 939 | AE74: iPhone 14 [BAT] Аккумулятор - Аналог ORIG (бу) | AG74: pcs | AH74: Сервис > Ремонт Apple > Ремонт iPhone > 14 | AI74: 180 | AJ74: дн | AK74: да | AL74: нет | AU74: 1250 | AV74: 2700
B75: iPhone 14 [BAT] Аккумулятор - Аналог ORIG (неизвестная деталь) | C75: 41141 280 | D75: 180 | E75: =LEFT(B75,FIND("[",B75) - 2) -> iPhone 14 | F75: Аккумулятор | G75: iPhone 14 - Аккумуляторная батарея + скотч (АКБ), ORIG | I75: 990 | L75: 950 | M75: 990 | N75: 1.2 | O75: 2200 | P75: =O75 -> 2200 | Q75: =P75 -> 2200 | R75: https://icomponents.ru/catalog/iphone/iphone_14/iphone_14_akkumulyatornaya_batareya_skotch_akb_orig/ | S75: 46140.382 | U75: =IF(I75>0, Q75 - I75, "нет з/ч") -> 1210 | V75: =IF(L75>0, Q379 - L75, "нет з/ч") -> -250 | X75: 990 | Y75: 950 | AA75: 41141 280 | AB75: 41141 280 | AD75: 41141 280 | AE75: iPhone 14 [BAT] Аккумулятор - Аналог ORIG (неизвестная деталь) | AG75: pcs | AH75: Сервис > Ремонт Apple > Ремонт iPhone > 14 | AI75: 180 | AJ75: дн | AK75: да | AL75: нет | AU75: 990 | AV75: 2200
B76: iPhone 14 [BAT] Аккумулятор - Банка ORIG | C76: 41141 281 | D76: 180 | E76: =LEFT(B76,FIND("[",B76) - 2) -> iPhone 14 | F76: Аккумулятор | G76: iPhone 14 - Банка АКБ с комплектом наклеек без шлейфа | I76: 770 | M76: 770 | N76: 0.12 | O76: 850 | Q76: =P75 -> 2200 | R76: https://icomponents.ru/catalog/iphone/iphone_14/iphone_14_banka_akb_s_komplektom_nakleek_bez_shleyfa/ | S76: 46140.382 | U76: =IF(I76>0, Q76 - I76, "нет з/ч") -> 1430 | V76: =IF(L76>0, #REF! - L76, "нет з/ч") -> нет з/ч | X76: 770 | AA76: 41141 281 | AB76: 41141 281 | AD76: 41141 281 | AE76: iPhone 14 [BAT] Аккумулятор - Банка ORIG | AG76: pcs | AH76: Сервис > Ремонт Apple > Ремонт iPhone > 14 | AI76: 180 | AJ76: дн | AK76: да | AL76: нет | AU76: 770 | AV76: 2200
B77: iPhone 14 Plus [BAT] Аккумулятор - Сервисный оригинал (подлинное) | C77: 56234 867 | D77: 180 | E77: =LEFT(B77,FIND("[",B77) - 2) -> iPhone 14 Plus | F77: Аккумулятор | G77: iPhone 14 Plus - Аккумуляторная батарея (АКБ) Service Pack ORIG | I77: 8000 | M77: 8000 | N77: 0.2 | O77: 9600 | P77: =O77 -> 9600 | Q77: =P77 -> 9600 | R77: https://icomponents.ru/catalog/iphone/iphone_14_plus/iphone_14_plus_akkumulyatornaya_batareya_akb_service_pack_orig/ | S77: 46140.382 | U77: =IF(I77>0, Q77 - I77, "нет з/ч") -> 1600 | V77: =IF(L77>0, #REF! - L77, "нет з/ч") -> нет з/ч | X77: 8000 | AA77: 56234 867 | AB77: 56234 867 | AD77: 56234 867 | AE77: iPhone 14 Plus [BAT] Аккумулятор - Сервисный оригинал (подлинное) | AG77: pcs | AH77: Сервис > Ремонт Apple > Ремонт iPhone > 14 Plus | AI77: 180 | AJ77: дн | AK77: да | AL77: нет | AU77: 8000 | AV77: 9600
B78: iPhone 14 Plus [BAT] Аккумулятор - Снятый оригинал (бу) | C78: 56234 931 | D78: 180 | E78: =LEFT(B78,FIND("[",B78) - 2) -> iPhone 14 Plus | F78: Аккумулятор | G78: iPhone 14 Plus - Аккумулятор снятый ORIG (привязка б/у, 100% емкость) | I78: 2990 | M78: 2990 | N78: 0.4 | O78: 4200 | P78: =O78 -> 4200 | Q78: =P78 -> 4200 | R78: https://icomponents.ru/catalog/iphone/iphone_14_plus/iphone_14_plus_akkumulyator_snyatyy_orig_privyazka_b_u_100_emkost/ | S78: 46140.382 | U78: =IF(I78>0, Q78 - I78, "нет з/ч") -> 1210 | V78: =IF(L78>0, Q382 - L78, "нет з/ч") -> нет з/ч | X78: 2990 | AA78: 56234 931 | AB78: 56234 931 | AD78: 56234 931 | AE78: iPhone 14 Plus [BAT] Аккумулятор - Снятый оригинал (бу) | AG78: pcs | AH78: Сервис > Ремонт Apple > Ремонт iPhone > 14 Plus | AI78: 180 | AJ78: дн | AK78: да | AL78: нет | AU78: 2990 | AV78: 4200
B79: iPhone 14 Plus [BAT] Аккумулятор - Аналог ORIG (подлинное) | D79: 180 | E79: =LEFT(B79,FIND("[",B79) - 2) -> iPhone 14 Plus | F79: Аккумулятор | L79: 2190 | M79: 2190 | N79: 0.7 | O79: 3700 | P79: =O79 -> 3700 | Q79: =P79 -> 3700 | S79: 46139.747 | U79: =IF(I79>0, Q79 - I79, "нет з/ч") -> нет з/ч | V79: =IF(L79>0, Q383 - L79, "нет з/ч") -> -1690 | Y79: 2190 | AE79: iPhone 14 Plus [BAT] Аккумулятор - Аналог ORIG (подлинное) | AG79: pcs | AH79: Сервис > Ремонт Apple > Ремонт iPhone > 14 Plus | AI79: 180 | AJ79: дн | AK79: да | AL79: нет | AU79: 2190 | AV79: 3700
B80: iPhone 14 Plus [BAT] Аккумулятор - Аналог ORIG (бу) | C80: 56235 046 | D80: 180 | E80: =LEFT(B80,FIND("[",B80) - 2) -> iPhone 14 Plus | F80: Аккумулятор | G80: iPhone 14 Plus - Аккумулятор (АКБ) PREMIUM CLEAN (iOS 18-26) | I80: 1200 | L80: 1290 | M80: 1290 | N80: 1.11 | O80: 2700 | P80: =O80 -> 2700 | Q80: =P80 -> 2700 | R80: https://icomponents.ru/catalog/iphone/iphone_14_plus/iphone_14_plus_akkumulyator_akb_premium_clean_ios_18_26/ | S80: 46140.382 | U80: =IF(I80>0, Q80 - I80, "нет з/ч") -> 1500 | V80: =IF(L80>0, Q387 - L80, "нет з/ч") -> -790 | X80: 1200 | Y80: 1290 | AA80: 56235 046 | AB80: 56235 046 | AD80: 56235 046 | AE80: iPhone 14 Plus [BAT] Аккумулятор - Аналог ORIG (бу) | AG80: pcs | AH80: Сервис > Ремонт Apple > Ремонт iPhone > 14 Plus | AI80: 180 | AJ80: дн | AK80: да | AL80: нет | AU80: 1290 | AV80: 2700
B81: iPhone 14 Plus [BAT] Аккумулятор - Аналог ORIG (неизвестная деталь) | C81: 41141 217 | D81: 180 | E81: =LEFT(B81,FIND("[",B81) - 2) -> iPhone 14 Plus | F81: Аккумулятор | G81: iPhone 14 Plus - Аккумуляторная батарея + скотч (АКБ), ORIG | I81: 1050 | M81: 1050 | N81: 1.1 | O81: 2200 | P81: =O81 -> 2200 | Q81: =P81 -> 2200 | R81: https://icomponents.ru/catalog/iphone/iphone_14_plus/iphone_14_plus_akkumulyatornaya_batareya_skotch_akb_orig/ | S81: 46140.382 | U81: =IF(I81>0, Q81 - I81, "нет з/ч") -> 1150 | V81: =IF(L81>0, #REF! - L81, "нет з/ч") -> нет з/ч | X81: 1050 | AA81: 41141 217 | AB81: 41141 217 | AD81: 41141 217 | AE81: iPhone 14 Plus [BAT] Аккумулятор - Аналог ORIG (неизвестная деталь) | AG81: pcs | AH81: Сервис > Ремонт Apple > Ремонт iPhone > 14 Plus | AI81: 180 | AJ81: дн | AK81: да | AL81: нет | AU81: 1050 | AV81: 2200
B82: iPhone 14 Plus [BAT] Аккумулятор - Банка ORIG | C82: 41141 218 | D82: 180 | E82: =LEFT(B82,FIND("[",B82) - 2) -> iPhone 14 Plus | F82: Аккумулятор | N82: 0.12 | Q82: =P81 -> 2200 | S82: 46139.747 | U82: =IF(I82>0, Q82 - I82, "нет з/ч") -> нет з/ч | V82: =IF(L82>0, Q389 - L82, "нет з/ч") -> нет з/ч | AA82: 41141 218 | AB82: 41141 218 | AD82: 41141 218 | AE82: iPhone 14 Plus [BAT] Аккумулятор - Банка ORIG | AG82: pcs | AH82: Сервис > Ремонт Apple > Ремонт iPhone > 14 Plus | AI82: 180 | AJ82: дн | AK82: да | AL82: нет | AV82: 2200
B83: iPhone 14 Pro [BAT] Аккумулятор - Сервисный оригинал (подлинное) | C83: 56235 145 | D83: 180 | E83: =LEFT(B83,FIND("[",B83) - 2) -> iPhone 14 Pro | F83: Аккумулятор | G83: iPhone 14 Pro - Аккумуляторная батарея (АКБ) Service Pack ORIG | I83: 8000 | M83: 8000 | N83: 0.2 | O83: 9600 | P83: =O83 -> 9600 | Q83: =P83 -> 9600 | R83: https://icomponents.ru/catalog/iphone/iphone_14_pro/iphone_14_pro_akkumulyatornaya_batareya_akb_service_pack_orig/ | S83: 46140.382 | U83: =IF(I83>0, Q83 - I83, "нет з/ч") -> 1600 | V83: =IF(L83>0, Q393 - L83, "нет з/ч") -> нет з/ч | X83: 8000 | AA83: 56235 145 | AB83: 56235 145 | AD83: 56235 145 | AE83: iPhone 14 Pro [BAT] Аккумулятор - Сервисный оригинал (подлинное) | AG83: pcs | AH83: Сервис > Ремонт Apple > Ремонт iPhone > 14 Pro | AI83: 180 | AJ83: дн | AK83: да | AL83: нет | AU83: 8000 | AV83: 9600
B84: iPhone 14 Pro [BAT] Аккумулятор - Снятый оригинал (бу) | C84: 56235 181 | D84: 180 | E84: =LEFT(B84,FIND("[",B84) - 2) -> iPhone 14 Pro | F84: Аккумулятор | G84: iPhone 14 Pro - Аккумулятор снятый ORIG (привязка б/у, 100% емкость) | I84: 3800 | M84: 3800 | N84: 0.16 | O84: 4400 | P84: =O84 -> 4400 | Q84: =P84 -> 4400 | R84: https://icomponents.ru/catalog/iphone/iphone_14_pro/iphone_14_pro_akkumulyator_snyatyy_orig_privyazka_b_u_100_emkost/ | S84: 46140.382 | U84: =IF(I84>0, Q84 - I84, "нет з/ч") -> 600 | V84: =IF(L84>0, #REF! - L84, "нет з/ч") -> нет з/ч | X84: 3800 | AA84: 56235 181 | AB84: 56235 181 | AD84: 56235 181 | AE84: iPhone 14 Pro [BAT] Аккумулятор - Снятый оригинал (бу) | AG84: pcs | AH84: Сервис > Ремонт Apple > Ремонт iPhone > 14 Pro | AI84: 180 | AJ84: дн | AK84: да | AL84: нет | AU84: 3800 | AV84: 4400
B85: iPhone 14 Pro [BAT] Аккумулятор - Аналог ORIG (подлинное) | D85: 180 | E85: =LEFT(B85,FIND("[",B85) - 2) -> iPhone 14 Pro | F85: Аккумулятор | G85: iPhone 14 Pro - Аккумулятор (Подлинная деталь / GENUINE NEW) повышенная емкость 3480 mAh | I85: 2500 | L85: 2590 | M85: 2590 | N85: 0.5 | O85: 3900 | P85: =O85 -> 3900 | Q85: =P85 -> 3900 | R85: https://icomponents.ru/catalog/iphone/iphone_14_pro/iphone_14_pro_akkumulyator_podlinnaya_detal_genuine_new_povyshennaya_emkost_3480_mah/ | S85: 46140.382 | U85: =IF(I85>0, Q85 - I85, "нет з/ч") -> 1400 | V85: =IF(L85>0, #REF! - L85, "нет з/ч") -> #REF! | X85: 2500 | Y85: 2590 | AE85: iPhone 14 Pro [BAT] Аккумулятор - Аналог ORIG (подлинное) | AG85: pcs | AH85: Сервис > Ремонт Apple > Ремонт iPhone > 14 Pro | AI85: 180 | AJ85: дн | AK85: да | AL85: нет | AU85: 2590 | AV85: 3900
B86: iPhone 14 Pro [BAT] Аккумулятор - Аналог ORIG (бу) | C86: 53723 094 | D86: 180 | E86: =LEFT(B86,FIND("[",B86) - 2) -> iPhone 14 Pro | F86: Аккумулятор | G86: iPhone 14 Pro - Аккумулятор (АКБ) PREMIUM CLEAN (iOS 18-26) | I86: 1350 | L86: 1390 | M86: 1390 | N86: 1.1 | O86: 2900 | P86: =O86 -> 2900 | Q86: =P86 -> 2900 | R86: https://icomponents.ru/catalog/iphone/iphone_14_pro/iphone_14_pro_akkumulyator_akb_premium_clean_ios_18_26/ | S86: 46140.382 | U86: =IF(I86>0, Q86 - I86, "нет з/ч") -> 1550 | V86: =IF(L86>0, Q395 - L86, "нет з/ч") -> -690 | X86: 1350 | Y86: 1390 | AA86: 53723 094 | AB86: 53723 094 | AD86: 53723 094 | AE86: iPhone 14 Pro [BAT] Аккумулятор - Аналог ORIG (бу) | AG86: pcs | AH86: Сервис > Ремонт Apple > Ремонт iPhone > 14 Pro | AI86: 180 | AJ86: дн | AK86: да | AL86: нет | AU86: 1390 | AV86: 2900
B87: iPhone 14 Pro [BAT] Аккумулятор - Аналог ORIG (неизвестная деталь) | C87: 38240 506 | D87: 180 | E87: =LEFT(B87,FIND("[",B87) - 2) -> iPhone 14 Pro | F87: Аккумулятор | G87: iPhone 14 Pro - Аккумуляторная батарея + скотч (АКБ), ORIG | I87: 1070 | L87: 1090 | M87: 1090 | N87: 1.2 | O87: 2400 | P87: =O87 -> 2400 | Q87: =P87 -> 2400 | R87: https://icomponents.ru/catalog/iphone/iphone_14_pro/iphone_14_pro_akkumulyatornaya_batareya_skotch_akb_orig/ | S87: 46140.382 | U87: =IF(I87>0, Q87 - I87, "нет з/ч") -> 1330 | V87: =IF(L87>0, #REF! - L87, "нет з/ч") -> #REF! | X87: 1070 | Y87: 1090 | AA87: 38240 506 | AB87: 38240 506 | AD87: 38240 506 | AE87: iPhone 14 Pro [BAT] Аккумулятор - Аналог ORIG (неизвестная деталь) | AG87: pcs | AH87: Сервис > Ремонт Apple > Ремонт iPhone > 14 Pro | AI87: 180 | AJ87: дн | AK87: да | AL87: нет | AU87: 1090 | AV87: 2400
B88: iPhone 14 Pro [BAT] Аккумулятор - Банка ORIG | C88: 41141 134 | D88: 180 | E88: =LEFT(B88,FIND("[",B88) - 2) -> iPhone 14 Pro | F88: Аккумулятор | G88: iPhone 14 Pro - Банка АКБ с комплектом наклеек без шлейфа | I88: 790 | M88: 790 | N88: 0.12 | O88: 900 | Q88: =P87 -> 2400 | R88: https://icomponents.ru/catalog/iphone/iphone_14_pro/iphone_14_pro_banka_akb_s_komplektom_nakleek_bez_shleyfa/ | S88: 46140.382 | U88: =IF(I88>0, Q88 - I88, "нет з/ч") -> 1610 | V88: =IF(L88>0, Q400 - L88, "нет з/ч") -> нет з/ч | X88: 790 | AA88: 41141 134 | AB88: 41141 134 | AD88: 41141 134 | AE88: iPhone 14 Pro [BAT] Аккумулятор - Банка ORIG | AG88: pcs | AH88: Сервис > Ремонт Apple > Ремонт iPhone > 14 Pro | AI88: 180 | AJ88: дн | AK88: да | AL88: нет | AU88: 790 | AV88: 2400
B89: iPhone 14 Pro Max [BAT] Аккумулятор - Сервисный оригинал (подлинное) | C89: 56236 006 | D89: 180 | E89: =LEFT(B89,FIND("[",B89) - 2) -> iPhone 14 Pro Max | F89: Аккумулятор | G89: iPhone 14 Pro Max - Аккумуляторная батарея (АКБ) Service Pack ORIG | I89: 8000 | M89: 8000 | N89: 0.2 | O89: 9600 | P89: =O89 -> 9600 | Q89: =P89 -> 9600 | R89: https://icomponents.ru/catalog/iphone/iphone_14_pro_max/iphone_14_pro_max_akkumulyatornaya_batareya_akb_service_pack_orig/ | S89: 46140.382 | U89: =IF(I89>0, Q89 - I89, "нет з/ч") -> 1600 | V89: =IF(L89>0, Q405 - L89, "нет з/ч") -> нет з/ч | X89: 8000 | AA89: 56236 006 | AB89: 56236 006 | AD89: 56236 006 | AE89: iPhone 14 Pro Max [BAT] Аккумулятор - Сервисный оригинал (подлинное) | AG89: pcs | AH89: Сервис > Ремонт Apple > Ремонт iPhone > 14 Pro Max | AI89: 180 | AJ89: дн | AK89: да | AL89: нет | AU89: 8000 | AV89: 9600
B90: iPhone 14 Pro Max [BAT] Аккумулятор - Снятый оригинал (бу) | C90: 56237 025 | D90: 180 | E90: =LEFT(B90,FIND("[",B90) - 2) -> iPhone 14 Pro Max | F90: Аккумулятор | G90: iPhone 14 Pro Max - Аккумулятор снятый ORIG (привязка б/у, 100% емкость) | I90: 4000 | M90: 4000 | N90: 0.12 | O90: 4500 | P90: =O90 -> 4500 | Q90: =P90 -> 4500 | R90: https://icomponents.ru/catalog/iphone/iphone_14_pro_max/iphone_14_pro_max_akkumulyator_snyatyy_orig_privyazka_b_u_100_emkost/ | S90: 46140.382 | U90: =IF(I90>0, Q90 - I90, "нет з/ч") -> 500 | V90: =IF(L90>0, Q406 - L90, "нет з/ч") -> нет з/ч | X90: 4000 | AA90: 56237 025 | AB90: 56237 025 | AD90: 56237 025 | AE90: iPhone 14 Pro Max [BAT] Аккумулятор - Снятый оригинал (бу) | AG90: pcs | AH90: Сервис > Ремонт Apple > Ремонт iPhone > 14 Pro Max | AI90: 180 | AJ90: дн | AK90: да | AL90: нет | AU90: 4000 | AV90: 4500
B91: iPhone 14 Pro Max [BAT] Аккумулятор - Аналог ORIG (подлинное) | D91: 180 | E91: =LEFT(B91,FIND("[",B91) - 2) -> iPhone 14 Pro Max | F91: Аккумулятор | G91: iPhone 14 Pro Max - Аккумулятор (Подлинная деталь / GENUINE NEW) повышенная емкость 4770 mAh | I91: 2600 | L91: 2690 | M91: 2690 | N91: 0.45 | O91: 3900 | P91: =O91 -> 3900 | Q91: =P91 -> 3900 | R91: https://icomponents.ru/catalog/iphone/iphone_14_pro_max/iphone_14_pro_max_akkumulyator_podlinnaya_detal_genuine_new_povyshennaya_emkost_4770_mah/ | S91: 46140.382 | U91: =IF(I91>0, Q91 - I91, "нет з/ч") -> 1300 | V91: =IF(L91>0, Q407 - L91, "нет з/ч") -> -2690 | X91: 2600 | Y91: 2690 | AE91: iPhone 14 Pro Max [BAT] Аккумулятор - Аналог ORIG (подлинное) | AG91: pcs | AH91: Сервис > Ремонт Apple > Ремонт iPhone > 14 Pro Max | AI91: 180 | AJ91: дн | AK91: да | AL91: нет | AU91: 2690 | AV91: 3900
B92: iPhone 14 Pro Max [BAT] Аккумулятор - Аналог ORIG (бу) | C92: 56237 050 | D92: 180 | E92: =LEFT(B92,FIND("[",B92) - 2) -> iPhone 14 Pro Max | F92: Аккумулятор | G92: iPhone 14 Pro Max - Аккумулятор (АКБ) PREMIUM CLEAN (iOS 18-26) | I92: 1400 | L92: 1490 | M92: 1490 | N92: 0.95 | O92: 2900 | P92: =O92 -> 2900 | Q92: =P92 -> 2900 | R92: https://icomponents.ru/catalog/iphone/iphone_14_pro_max/iphone_14_pro_max_akkumulyator_akb_premium_clean_ios_18_26/ | S92: 46140.382 | U92: =IF(I92>0, Q92 - I92, "нет з/ч") -> 1500 | V92: =IF(L92>0, Q411 - L92, "нет з/ч") -> 2110 | X92: 1400 | Y92: 1490 | AA92: 56237 050 | AB92: 56237 050 | AD92: 56237 050 | AE92: iPhone 14 Pro Max [BAT] Аккумулятор - Аналог ORIG (бу) | AG92: pcs | AH92: Сервис > Ремонт Apple > Ремонт iPhone > 14 Pro Max | AI92: 180 | AJ92: дн | AK92: да | AL92: нет | AU92: 1490 | AV92: 2900
B93: iPhone 14 Pro Max [BAT] Аккумулятор - Аналог ORIG (неизвестная деталь) | C93: 38240 477 | D93: 180 | E93: =LEFT(B93,FIND("[",B93) - 2) -> iPhone 14 Pro Max | F93: Аккумулятор | G93: iPhone 14 Pro Max - Аккумуляторная батарея + скотч (АКБ), ORIG | I93: 1140 | L93: 1190 | M93: 1190 | N93: 1 | O93: 2400 | P93: =O93 -> 2400 | Q93: =P93 -> 2400 | R93: https://icomponents.ru/catalog/iphone/iphone_14_pro_max/iphone_14_pro_max_akkumulyatornaya_batareya_skotch_akb_orig/ | S93: 46140.382 | U93: =IF(I93>0, Q93 - I93, "нет з/ч") -> 1260 | V93: =IF(L93>0, Q415 - L93, "нет з/ч") -> 2410 | X93: 1140 | Y93: 1190 | AA93: 38240 477 | AB93: 38240 477 | AD93: 38240 477 | AE93: iPhone 14 Pro Max [BAT] Аккумулятор - Аналог ORIG (неизвестная деталь) | AG93: pcs | AH93: Сервис > Ремонт Apple > Ремонт iPhone > 14 Pro Max | AI93: 180 | AJ93: дн | AK93: да | AL93: нет | AU93: 1190 | AV93: 2400
B94: iPhone 14 Pro Max [BAT] Аккумулятор - Банка ORIG | C94: 41139 499 | D94: 180 | E94: =LEFT(B94,FIND("[",B94) - 2) -> iPhone 14 Pro Max | F94: Аккумулятор | G94: iPhone 14 Pro Max - Банка АКБ с комплектом наклеек без шлейфа | I94: 820 | M94: 820 | N94: 0.12 | O94: 900 | Q94: =P93 -> 2400 | R94: https://icomponents.ru/catalog/iphone/iphone_14_pro_max/iphone_14_pro_max_banka_akb_s_komplektom_nakleek_bez_shleyfa/ | S94: 46140.382 | U94: =IF(I94>0, Q94 - I94, "нет з/ч") -> 1580 | V94: =IF(L94>0, Q419 - L94, "нет з/ч") -> нет з/ч | X94: 820 | AA94: 41139 499 | AB94: 41139 499 | AD94: 41139 499 | AE94: iPhone 14 Pro Max [BAT] Аккумулятор - Банка ORIG | AG94: pcs | AH94: Сервис > Ремонт Apple > Ремонт iPhone > 14 Pro Max | AI94: 180 | AJ94: дн | AK94: да | AL94: нет | AU94: 820 | AV94: 2400
B95: iPhone 15 [BAT] Аккумулятор - Сервисный оригинал (подлинное) | C95: 56243 698 | D95: 180 | E95: =LEFT(B95,FIND("[",B95) - 2) -> iPhone 15 | F95: Аккумулятор | G95: iPhone 15 - Аккумуляторная батарея (АКБ) Service Pack ORIG | I95: 8200 | M95: 8200 | N95: 0.2 | O95: 9850 | P95: =O95 -> 9850 | Q95: =P95 -> 9850 | R95: https://icomponents.ru/catalog/iphone/iphone_15/iphone_15_akkumulyatornaya_batareya_akb_service_pack_orig/ | S95: 46140.382 | U95: =IF(I95>0, Q95 - I95, "нет з/ч") -> 1650 | V95: =IF(L95>0, Q423 - L95, "нет з/ч") -> нет з/ч | X95: 8200 | AA95: 56243 698 | AB95: 56243 698 | AD95: 56243 698 | AE95: iPhone 15 [BAT] Аккумулятор - Сервисный оригинал (подлинное) | AG95: pcs | AH95: Сервис > Ремонт Apple > Ремонт iPhone > 15 | AI95: 180 | AJ95: дн | AK95: да | AL95: нет | AU95: 8200 | AV95: 9850
B96: iPhone 15 [BAT] Аккумулятор - Снятый оригинал (бу) | C96: 56243 714 | D96: 180 | E96: =LEFT(B96,FIND("[",B96) - 2) -> iPhone 15 | F96: Аккумулятор | G96: iPhone 15 - Аккумулятор снятый ORIG (привязка б/у, 100% емкость) | I96: 2600 | M96: 2600 | N96: 1 | O96: 5200 | P96: =O96 -> 5200 | Q96: =P96 -> 5200 | R96: https://icomponents.ru/catalog/iphone/iphone_15/iphone_15_akkumulyator_snyatyy_orig_privyazka_b_u_100_emkost/ | S96: 46140.382 | U96: =IF(I96>0, Q96 - I96, "нет з/ч") -> 2600 | V96: =IF(L96>0, Q424 - L96, "нет з/ч") -> нет з/ч | X96: 2600 | AA96: 56243 714 | AB96: 56243 714 | AD96: 56243 714 | AE96: iPhone 15 [BAT] Аккумулятор - Снятый оригинал (бу) | AG96: pcs | AH96: Сервис > Ремонт Apple > Ремонт iPhone > 15 | AI96: 180 | AJ96: дн | AK96: да | AL96: нет | AU96: 2600 | AV96: 5200
B97: iPhone 15 [BAT] Аккумулятор - Аналог ORIG (подлинное) | D97: 180 | E97: =LEFT(B97,FIND("[",B97) - 2) -> iPhone 15 | F97: Аккумулятор | G97: iPhone 15 - Аккумулятор (Подлинная деталь / GENUINE NEW) повышенная емкость 3600 mAh | I97: 2200 | L97: 2190 | M97: 2200 | N97: 1.13 | O97: 4700 | P97: =O97 -> 4700 | Q97: =P97 -> 4700 | R97: https://icomponents.ru/catalog/iphone/iphone_15/iphone_15_akkumulyator_podlinnaya_detal_genuine_new_povyshennaya_emkost_3600_mah/ | S97: 46140.382 | U97: =IF(I97>0, Q97 - I97, "нет з/ч") -> 2500 | V97: =IF(L97>0, Q425 - L97, "нет з/ч") -> 1410 | X97: 2200 | Y97: 2190 | AE97: iPhone 15 [BAT] Аккумулятор - Аналог ORIG (подлинное) | AG97: pcs | AH97: Сервис > Ремонт Apple > Ремонт iPhone > 15 | AI97: 180 | AJ97: дн | AK97: да | AL97: нет | AU97: 2200 | AV97: 4700
B98: iPhone 15 [BAT] Аккумулятор - Аналог ORIG (бу) | C98: 56243 722 | D98: 180 | E98: =LEFT(B98,FIND("[",B98) - 2) -> iPhone 15 | F98: Аккумулятор | G98: iPhone 15 - Аккумулятор (АКБ) PREMIUM CLEAN (iOS 18-26) | I98: 1200 | L98: 1190 | M98: 1200 | N98: 2.1 | O98: 3700 | P98: =O98 -> 3700 | Q98: =P98 -> 3700 | R98: https://icomponents.ru/catalog/iphone/iphone_15/iphone_15_akkumulyator_akb_premium_clean_ios_18_26/ | S98: 46140.382 | U98: =IF(I98>0, Q98 - I98, "нет з/ч") -> 2500 | V98: =IF(L98>0, #REF! - L98, "нет з/ч") -> #REF! | X98: 1200 | Y98: 1190 | AA98: 56243 722 | AB98: 56243 722 | AD98: 56243 722 | AE98: iPhone 15 [BAT] Аккумулятор - Аналог ORIG (бу) | AG98: pcs | AH98: Сервис > Ремонт Apple > Ремонт iPhone > 15 | AI98: 180 | AJ98: дн | AK98: да | AL98: нет | AU98: 1200 | AV98: 3700
B99: iPhone 15 [BAT] Аккумулятор - Аналог ORIG (неизвестная деталь) | C99: 41130 824 | D99: 180 | E99: =LEFT(B99,FIND("[",B99) - 2) -> iPhone 15 | F99: Аккумулятор | G99: iPhone 15 - Аккумуляторная батарея + скотч (АКБ), ORIG | I99: 1200 | L99: 990 | M99: 1200 | N99: 1.65 | O99: 3200 | P99: =O99 -> 3200 | Q99: =P99 -> 3200 | R99: https://icomponents.ru/catalog/iphone/iphone_15/iphone_15_akkumulyatornaya_batareya_skotch_akb_orig/ | S99: 46140.382 | U99: =IF(I99>0, Q99 - I99, "нет з/ч") -> 2000 | V99: =IF(L99>0, Q429 - L99, "нет з/ч") -> -140 | X99: 1200 | Y99: 990 | AA99: 41130 824 | AB99: 41130 824 | AD99: 41130 824 | AE99: iPhone 15 [BAT] Аккумулятор - Аналог ORIG (неизвестная деталь) | AG99: pcs | AH99: Сервис > Ремонт Apple > Ремонт iPhone > 15 | AI99: 180 | AJ99: дн | AK99: да | AL99: нет | AU99: 1200 | AV99: 3200
B100: iPhone 15 [BAT] Аккумулятор - Банка ORIG | C100: 41130 825 | D100: 180 | E100: =LEFT(B100,FIND("[",B100) - 2) -> iPhone 15 | F100: Аккумулятор | G100: iPhone 15 - Банка АКБ с комплектом наклеек без шлейфа | I100: 790 | M100: 790 | N100: 0.12 | O100: 900 | Q100: =P99 -> 3200 | R100: https://icomponents.ru/catalog/iphone/iphone_15/iphone_15_banka_akb_s_komplektom_nakleek_bez_shleyfa/ | S100: 46140.382 | U100: =IF(I100>0, Q100 - I100, "нет з/ч") -> 2410 | V100: =IF(L100>0, #REF! - L100, "нет з/ч") -> нет з/ч | X100: 790 | AA100: 41130 825 | AB100: 41130 825 | AD100: 41130 825 | AE100: iPhone 15 [BAT] Аккумулятор - Банка ORIG | AG100: pcs | AH100: Сервис > Ремонт Apple > Ремонт iPhone > 15 | AI100: 180 | AJ100: дн | AK100: да | AL100: нет | AU100: 790 | AV100: 3200
B101: iPhone 15 Plus [BAT] Аккумулятор - Сервисный оригинал (подлинное) | C101: 56243 750 | D101: 180 | E101: =LEFT(B101,FIND("[",B101) - 2) -> iPhone 15 Plus | F101: Аккумулятор | G101: iPhone 15 Plus - Аккумуляторная батарея (АКБ) Service Pack ORIG | I101: 8200 | M101: 8200 | N101: 0.2 | O101: 9850 | P101: =O101 -> 9850 | Q101: =P101 -> 9850 | R101: https://icomponents.ru/catalog/iphone/iphone_15_plus/iphone_15_plus_akkumulyatornaya_batareya_akb_service_pack_orig/ | S101: 46140.382 | U101: =IF(I101>0, Q101 - I101, "нет з/ч") -> 1650 | V101: =IF(L101>0, Q433 - L101, "нет з/ч") -> нет з/ч | X101: 8200 | AA101: 56243 750 | AB101: 56243 750 | AD101: 56243 750 | AE101: iPhone 15 Plus [BAT] Аккумулятор - Сервисный оригинал (подлинное) | AG101: pcs | AH101: Сервис > Ремонт Apple > Ремонт iPhone > 15 Plus | AI101: 180 | AJ101: дн | AK101: да | AL101: нет | AU101: 8200 | AV101: 9850
B102: iPhone 15 Plus [BAT] Аккумулятор - Снятый оригинал (бу) | C102: 56243 779 | D102: 180 | E102: =LEFT(B102,FIND("[",B102) - 2) -> iPhone 15 Plus | F102: Аккумулятор | N102: 0.12 | P102: =O102 | Q102: =P102 | U102: =IF(I102>0, Q102 - I102, "нет з/ч") -> нет з/ч | V102: =IF(L102>0, Q434 - L102, "нет з/ч") -> нет з/ч | AA102: 56243 779 | AB102: 56243 779 | AD102: 56243 779 | AE102: iPhone 15 Plus [BAT] Аккумулятор - Снятый оригинал (бу) | AG102: pcs | AH102: Сервис > Ремонт Apple > Ремонт iPhone > 15 Plus | AI102: 180 | AJ102: дн | AK102: да | AL102: нет
...

Sheet Лист19
C2: Изменения в РО. Изменены сроки гарантии для услуг. Процесс добавления услуги "Дисплей - замена (переклей) разбитого стекла". В услуге выставлена розничная цена. Добавляется услуга в заказ, в себестоимость указывается стоимость услуг УСЦ (дополнительных работ указывать НЕ НАДО, напирмер "сопровождение ремонта"). Так же, в случае замены тачскрина указываем услугу "Дисплей - замена (переклей) разбитого стекла с тачскрином. Цена розницы проставлена 1р. - уточняем себестоимость у Яблок и делаем произвольную цену - не должна быть ниже стоимости "переклея стекла". Замена тача применима к моделям от Х до 13PM. Переименовано: 1. Восстановление цепей питания —> Ремонт платы 2. Восстановление линий / контактов в слоях платы... —> Ремонт платы (распайка половинок) Цены на них указаны "от" - окончательная цена после диагностики. Удалены услуги: 1. Беспроводная зарядка 2. Вибромотор 3. Вспышка 4. Разъем на плате 5. Контроллер ЮСБ 6. Датчик приближения лица 7. Датчик освещения 8. Изображение - замена микросхемы 9. Аудиокодек 10. Трутон - программное восстановление Вместо них, в случае, если таковые когда-нибудь будут - использовать обобщенные услуги - Компонентный ремонт, Модульный ремонт и тд. с указанием характера выполняемой работы. Пока не закидывай этой в группу - доделаем для всех моделей и общие услуги - осталось не много
B6: 1. | C6: УДАЛЕНЫ УСЛУГИ
C7: Беспроводная зарядка | D7: Вместо них, в случае, если таковые когда-нибудь будут - использовать обобщенные услуги - iPhone Компонентный ремонт / iPhone Модульный ремонт и тп. с указанием характера выполняемой работы в комментарии к работе / услуге. ЦЕНА НА ЭТИ УСЛУГИ ПРОСТАВЛЕНА 1Р. - выставляем согласованную с клиентом цену самостоятельно.
C8: Вибромотор
C9: Вспышка - замена драйвера
C10: Контроллер ЮСБ
C11: Датчик приближения лица
C12: Датчик освещения
C13: Изображение - замена микросхемы
C14: Аудиокодек
C15: Трутон - программное восстановление
B17: 2. | C17: К iPhone для каждой модели добавлена услуга "Диагностика (с пайкой компонентов) - цена так же 1Р. Проставляем и согласовываем самостоятельно.
B19: 3. | C19: Изменили специфику добавления услуг по ПЕРКЛЕЙКЕ ДИСПЛЕЕВ. Теперь при добавлении услуги в заказ выбираем нужную: замена (переклейка) стекла / замена (переклейка) стекла с тачскрином. В стоимость проставлена сумма - остается добавить себестоимость работы УСЦ. - к этим услугам применено правило вознагриаждения аналогично услуге "Сопровождение ремонта" ***** Прайс у Ремонта Яблок прописан не на все модели - местами стоит ценник в услуге 1Р. - такие моменты согласовываем и проставляем самостоятельно.
B21: 4. | C21: ПЕРЕИМЕНОВАНЫ УСЛУГИ
C22: Восстановление цепей питания —> Ремонт платы
C23: Восстановление линий / контактов в слоях платы... —> Ремонт платы (распайка половинок)
B25: 5. | C25: Все услуги, в которых присутствует фраза "требуется диагностика" означает цену "от" - инженер сам оценивает ситуацию и предлагает цену к согласованию менеджеру.
B27: 6. | C27: На модели айфонов, у которых корпус состоит из задней крышки и средней части - добавлена услуга "Корпус (средняя часть) - замена". ***Так же в этих моделях присутсвует услуга "Корпус - замена" - цена состоит из замены средней части + замена крышки (со скидкой 50% от наименьшей стоимости из них).
B29: 7. | C29: Так же изменены сроки гарантии для работ - ознакомиться можно на скрине. В базе все гарантии к ремонтам проставлены.

Sheet ДЛЯ МАКСИМА А.
B2: БЛОК 1 ФОРМИРОВАНИЕ ЦЕНЫ ДЛЯ МЕНЕДЖЕРА | AJ2: дн | AL2: нет
B3: Лист БД_ЗАПЧАСТИ СТОЛБЕЦ B В ручную прописываем наименование запчасти | C3: Лист БД_ЗАПЧАСТИ СТОЛБЕЦ C НЕ ИСПОЛЬЗУЕТСЯ | D3: Лист БД_ЗАПЧАСТИ СТОЛБЕЦ D В ручную прописываем срок гарантии | E3: Лист БД_ЗАПЧАСТИ СТОЛБЕЦ E В ручную прописываем наименование услуги с использованием конкретной запчасти или же услуги без запчасти | F3: Лист БД_ЗАПЧАСТИ СТОЛБЕЦ F Формула обращается к странице БД_УСЛУГИ_РО в столбец P, а так же если к услуге предусмотрена запчасть плюсует стоимосчть запчасти со страницы БД_ЗАПЧАСТИ из столбца P | G3: Лист БД_ЗАПЧАСТИ СТОЛБЕЦ G В ручную прописвается формула в выборочные ячейки, где есть вариативность окзания услуги или вариативность используемых запчастей - образение происходит в диапозоне этих услуг из столбца F на странице ПРАЙС_ЛИСТ | AA3: Лист БД_ЗАПЧАСТИ СТОЛБЕЦ C НЕ ИСПОЛЬЗУЕТСЯ | AI3: Лист БД_ЗАПЧАСТИ СТОЛБЕЦ D В ручную прописываем срок гарантии | AJ3: дн | AL3: нет
B4: МОДЕЛЬ | C4: КОД УСЛУГИ | D4: ГАРАНТИЯ, дн. | E4: УСЛУГА | F4: РОЗНИЧНАЯ ЦЕНА | G4: ДИАПОЗОН ЦЕНЫ | AA4: КОД УСЛУГИ | AB4: МОДЕЛЬ | AC4: КОД УСЛУГИ | AD4: ГАРАНТИЯ, дн. | AE4: УСЛУГА | AF4: РОЗНИЧНАЯ ЦЕНА | AG4: ДИАПОЗОН ЦЕНЫ | AI4: ГАРАНТИЯ, дн. | AJ4: дн | AL4: нет
AJ5: дн | AL5: нет
AJ6: дн | AL6: нет
B7: БЛОК 2 ПОПАДАНИЕ ЦЕНЫ НА САЙТ | AJ7: дн | AL7: нет
B8: Лист БД_МОЙ СКЛАД СТОЛБЕЦ B Не учавствует | C8: Лист БД_МОЙ СКЛАД СТОЛБЕЦ C Прописывается руками после добавления товара в МойСклад | D8: Лист БД_МОЙ СКЛАД СТОЛБЕЦ D Ссылкается на страницу ПРАЙС_ЛИСТ в столбец F - для забора цены, а так же проверяет это значение со столбцом H на том же листе ПРАЙС_ЛИСТ и если оба значения равны - заменяет на 0. 0 значит = уточняйте цену | E8: Лист БД_МОЙ СКЛАД СТОЛБЕЦ E Прописывается руками | F8: Лист БД_МОЙ СКЛАД СТОЛБЕЦ F Прописывается руками | G8: Лист БД_МОЙ СКЛАД СТОЛБЕЦ G Прописывается руками | H8: Лист БД_МОЙ СКЛАД СТОЛБЕЦ H Прописывается руками | I8: Лист БД_МОЙ СКЛАД СТОЛБЕЦ I Прописывается руками, нужна для того, что бы кликнув по названию - можно было перейти в услугу | J8: Лист БД_МОЙ СКЛАД СТОЛБЕЦ J Прописывается руками | K8: Лист БД_МОЙ СКЛАД СТОЛБЕЦ K ПУСТОЙ СТОЛБЕЦ | L8: Лист БД_МОЙ СКЛАД СТОЛБЕЦ L Не учавствует | X8: Лист БД_МОЙ СКЛАД СТОЛБЕЦ I Не учавствует | Y8: Лист БД_МОЙ СКЛАД СТОЛБЕЦ L Не учавствует | AA8: Лист БД_МОЙ СКЛАД СТОЛБЕЦ C Прописывается руками после добавления товара в МойСклад | AI8: Лист БД_МОЙ СКЛАД СТОЛБЕЦ D Ссылкается на страницу ПРАЙС_ЛИСТ в столбец F - для забора цены, а так же проверяет это значение со столбцом H на том же листе ПРАЙС_ЛИСТ и если оба значения равны - заменяет на 0. 0 для сайта значит = уточняйте цену | AJ8: дн | AL8: нет
B9: МОДЕЛЬ | C9: КОД | D9: ЦЕНА | E9: Услуга | F9: Время | G9: Цена "ОТ" | H9: Гарантия | I9: Ссылка | J9: Описание | L9: ЗАВИСИМОСТЬ | X9: Ссылка | Y9: ЗАВИСИМОСТЬ | AA9: КОД | AI9: ЦЕНА | AJ9: дн | AL9: нет
B12: БЛОК 3 КАК ФОРМИРУЕТСЯ ЦЕНА ЗАПЧАСТИ | AA12: ШАБЛОН ДЛЯ ИМПОРТА ЗАПЧАСТЕЙ В РО
B13: Лист БД_ЗАПЧАСТИ СТОЛБЕЦ B В ручную прописываем наименование запчасти | C13: Лист БД_ЗАПЧАСТИ СТОЛБЕЦ C В ручную прописываем ID запчасти после ее создания в базе РО | D13: Лист БД_ЗАПЧАСТИ СТОЛБЕЦ D В ручную прописываем сроки гарантии | E13: Лист БД_ЗАПЧАСТИ СТОЛБЕЦ E Автоматически подставляется из названия по принципу "вставить все" до знака [ | F13: Лист БД_ЗАПЧАСТИ СТОЛБЕЦ F В ручную прописываем категорию запчасти | G13: Лист БД_ЗАПЧАСТИ СТОЛБЕЦ G Автоматически подставляется после выполнения скрипта парсинга - копирует напименование на сайте поставщика | H13: Лист БД_ЗАПЧАСТИ СТОЛБЕЦ H В ручную копируется из столбца I для сравнения цены последних двух закупочных цен - помогает понять подешевела запчасть или же подорожала | I13: Лист БД_ЗАПЧАСТИ СТОЛБЕЦ I Автоматически подставляется после выполнения скрипта парсинга - копирует розничную цену на сайте поставщика | J13: Лист БД_ЗАПЧАСТИ СТОЛБЕЦ J Не используется | K13: Лист БД_ЗАПЧАСТИ СТОЛБЕЦ K В ручную копируется из столбца I для сравнения цены последних двух закупочных цен - помогает понять подешевела запчасть или же подорожала | L13: Лист БД_ЗАПЧАСТИ СТОЛБЕЦ L Прописывается в ручную с ресурса, который предоставляет поставщик | M13: Лист БД_ЗАПЧАСТИ СТОЛБЕЦ M Автоматически сравнивает значения на странице БД_ЗАПЧАСТИ в столбцах I и L и выбирает максимальное значение | N13: Лист БД_ЗАПЧАСТИ СТОЛБЕЦ N В ручную подбираем нужный нам процент наценки на запчасть | O13: Лист БД_ЗАПЧАСТИ СТОЛБЕЦ O Автоматически берет значение со страницы БД_ЗАПЧАСТИ в столбце M - прибавляет процент наценки из столбца N, округляет значение до 50 и выводит итог | P13: Лист БД_ЗАПЧАСТИ СТОЛБЕЦ P В каждую строку указывается форула для копирования значения из столбца O | Q13: Лист БД_ЗАПЧАСТИ СТОЛБЕЦ Q В каждую строку указывается форула для копирования значения из столбца P | R13: Лист БД_ЗАПЧАСТИ СТОЛБЕЦ R Находим на сайте поставщика данную запчасть и в ручную вставляем ссылку. Далее запускаем парсер запчастей - идем в "Расширения" - "AppsScript" - выбираем файл "Парсер з/ч "выборочно" - Указываем в диапозон строк "от" и "до" var START_ROW = 149; var END_ROW = 149 и нажимаем кнопку выполнить | S13: Лист БД_ЗАПЧАСТИ СТОЛБЕЦ S Автоматически подставляется после выполнения скрипта парсинга - проставляет дату запуска скрипта | T13: Лист БД_ЗАПЧАСТИ СТОЛБЕЦ T ПУСТОЙ СТОЛБЕЦ | U13: Лист БД_ЗАПЧАСТИ СТОЛБЕЦ U Не используется | V13: Лист БД_ЗАПЧАСТИ СТОЛБЕЦ V Не используется | W13: Лист БД_ЗАПЧАСТИ СТОЛБЕЦ W ПУСТОЙ СТОЛБЕЦ | X13: Лист БД_ЗАПЧАСТИ СТОЛБЕЦ X Не используется | Y13: Лист БД_ЗАПЧАСТИ СТОЛБЕЦ Y Не используется | Z13: Лист БД_ЗАПЧАСТИ СТОЛБЕЦ Z ПУСТОЙ СТОЛБЕЦ | AA13: Лист БД_ЗАПЧАСТИ СТОЛБЕЦ AA Автоматически подтягивает значение со страницы БД_ЗАПЧАСТИ из столбца С | AB13: Лист БД_ЗАПЧАСТИ СТОЛБЕЦ AB Автоматически подтягивает значение со страницы БД_ЗАПЧАСТИ из столбца AA | AC13: Лист БД_ЗАПЧАСТИ СТОЛБЕЦ AC Не используется | AD13: Лист БД_ЗАПЧАСТИ СТОЛБЕЦ AD Автоматически подтягивает значение со страницы БД_ЗАПЧАСТИ из столбца AA | AE13: Лист БД_ЗАПЧАСТИ СТОЛБЕЦ AE Автоматически подтягивает значение со страницы БД_ЗАПЧАСТИ из столбца B | AF13: Лист БД_ЗАПЧАСТИ СТОЛБЕЦ AF Не используется | AG13: Лист БД_ЗАПЧАСТИ СТОЛБЕЦ AG Автоматически прописывает pcs до контца таблицы в каждой строке | AH13: Лист БД_ЗАПЧАСТИ СТОЛБЕЦ AH Прописывается в ручную - указывается путь в точности как в РО (место, где должна находится запчасть) | AI13: Лист БД_ЗАПЧАСТИ СТОЛБЕЦ AI Автоматически подтягивает значение со страницы БД_ЗАПЧАСТИ из столбца D | AJ13: Лист БД_ЗАПЧАСТИ СТОЛБЕЦ AJ Автоматически прописывает дн до контца таблицы в каждой строке | AK13: Лист БД_ЗАПЧАСТИ СТОЛБЕЦ AK Проставляется руками "да" или "нет" | AL13: Лист БД_ЗАПЧАСТИ СТОЛБЕЦ AL Автоматически прописывает нет до контца таблицы в каждой строке | AM13: Лист БД_ЗАПЧАСТИ СТОЛБЕЦ AM Не используется | AN13: Лист БД_ЗАПЧАСТИ СТОЛБЕЦ AN Не используется | AO13: Лист БД_ЗАПЧАСТИ СТОЛБЕЦ AO Не используется | AP13: Лист БД_ЗАПЧАСТИ СТОЛБЕЦ AP Не используется | AQ13: Лист БД_ЗАПЧАСТИ СТОЛБЕЦ AQ Не используется | AR13: Лист БД_ЗАПЧАСТИ СТОЛБЕЦ AR Не используется | AS13: Лист БД_ЗАПЧАСТИ СТОЛБЕЦ AS Не используется | AT13: Лист БД_ЗАПЧАСТИ СТОЛБЕЦ AT Не используется | AU13: Лист БД_ЗАПЧАСТИ СТОЛБЕЦ AU Автоматически подтягивает значение со страницы БД_ЗАПЧАСТИ из столбца M | AV13: Лист БД_ЗАПЧАСТИ СТОЛБЕЦ AV Автоматически подтягивает значение со страницы БД_ЗАПЧАСТИ из столбца Q
B14: НАИМЕНОВАНИЕ ЗАПЧАСТИ | C14: ID ЗАПЧАСТИ | D14: ГАРАНТИЯ | E14: МОДЕЛЬ | F14: КАТЕГОРИЯ | G14: НАИМЕНОВАНИЕ НА САЙТЕ ICOMPONENTS | H14: СТАРАЯ ЦЕНА ЗАПЧАСТИ ICOMPONENTS | I14: АКТ. ЦЕНА ЗАПЧАСТИ ICOMPONENTS | J14: НАИМЕНОВАНИЕ В ПРАЙСЕ MOS - LCD | K14: СТАРАЯ ЦЕНА ЗАПЧАСТИ MOS - LCD | L14: АКТ. ЦЕНА ЗАПЧАСТИ MOS - LCD | M14: {={"ПОДХОДЯЩАЯ ЦЕНА ЗАПЧАСТИ*"; BYROW(H15:L1014, LAMBDA(row, IF(COUNT(row)>0, MAX(row), "")))}} -> ПОДХОДЯЩАЯ ЦЕНА ЗАПЧАСТИ* | N14: НАЦЕНКА НА ЗАПЧАСТЬ | O14: {={"СТОИМОСТЬ ЗАПЧАСТИ С НАЦЕНКОЙ*"; IF(M15:M1014<>"", MROUND(M15:M1014*(1+N15:N1014), 50), "")}} -> СТОИМОСТЬ ЗАПЧАСТИ С НАЦЕНКОЙ* | P14: ИТОГОВАЯ СТОИМОСТЬ ЗАПЧАСТИ (ПРАЙС) | Q14: ИТОГОВАЯ СТОИМОСТЬ ЗАПЧАСТИ (РЕМОНЛАЙН) | R14: ССЫЛКА НА ЗАПЧАСТЬ ICOMPONENTS | S14: ДАТА ПАРСИНГА | U14: НАЦЕНКА В РУБЛЯХ ICOMPONENTS | V14: НАЦЕНКА В РУБЛЯХ MOS - LCD | X14: {={"ЦЕНА ICOMPONENTS*"; I15:I1014}} -> ЦЕНА ICOMPONENTS* | Y14: {={"ЦЕНА MOS - LCD*"; L15:L1014}} -> ЦЕНА MOS - LCD* | AA14: {={"ID*"; C15:C1014}} -> ID* | AB14: {={"КОД*"; AA15:AA1014}} -> КОД* | AC14: Артикул | AD14: {={"ШТРИХКОД*"; AA15:AA1014}} -> ШТРИХКОД* | AE14: {={"Наименование*"; B15:B1014}} -> Наименование* | AF14: Описание | AG14: {={ "Единица измерения*" ; IF(AG15:AG1014 <> "", "pcs", "pcs") }} -> Единица измерения* | AH14: Категория | AI14: {={"Гарантия*"; D15:D1014}} -> Гарантия* | AJ14: {={ "Гарантийный период*" ; IF(AJ15:AJ1014 <> "", "дн", "дн") }} -> Гарантийный период* | AK14: Серийный учет | AL14: {={ "Включить отслеживание срока годности*" ; IF(AL15:AL1014 <> "", "нет", "нет") }} -> Включить отслеживание срока годности* | AM14: Длина | AN14: Ширина | AO14: Высота | AP14: Единица измерения размеров | AQ14: Вес | AR14: Единица веса | AS14: ID поставщика по умолчанию | AT14: Имя поставщика по умолчанию | AU14: {={"Закупочная*"; M15:M1014}} -> Закупочная* | AV14: {={"Розничная*"; Q15:Q1014}} -> Розничная*
B15: iPhone 5 [BAT] Аккумулятор - Аналог ORIG | C15: 161 990 | D15: 180 | E15: =LEFT(B15,FIND("[",B15) - 2) -> iPhone 5 | F15: Аккумулятор | G15: iPhone 5 - аккумуляторная батарея (АКБ), ORIG | I15: 430 | L15: 340 | M15: 430 | N15: 0.12 | O15: 500 | P15: =O15 -> 500 | Q15: =P15 -> 500 | R15: https://icomponents.ru/catalog/iphone/iphone_5/iphone_5_akkumulyatornaya_batareya_akb_orig/ | S15: 46140.38 | U15: =IF(I15>0, Q15 - I15, "нет з/ч") -> 70 | V15: =IF(L15>0, Q15 - L15, "нет з/ч") -> 160 | X15: 430 | Y15: 340 | AA15: 161 990 | AB15: 161 990 | AD15: 161 990 | AE15: iPhone 5 [BAT] Аккумулятор - Аналог ORIG | AG15: pcs | AH15: Сервис > Ремонт Apple > Ремонт iPhone > 5 | AI15: 180 | AJ15: дн | AK15: да | AL15: нет | AU15: 430 | AV15: 500
AG16: pcs | AJ16: дн | AL16: нет
AG17: pcs | AJ17: дн | AL17: нет
AG18: pcs | AJ18: дн | AL18: нет
AG19: pcs | AJ19: дн | AL19: нет
B20: Попадающая на сайт информация - попадает со страницы БД_МОЙ СКЛАД | AE20: Попадающая на сайт информация - попадает со страницы БД_МОЙ СКЛАД | AG20: pcs | AJ20: дн | AL20: нет
B21: ЦЕНА | C21: БД_МОЙ СКЛАД СТОЛБЕЦ D | E21: Ссылкается на страницу ПРАЙС_ЛИСТ в столбец F - для забора цены, а так же проверяет это значение со столбцом H на том же листе ПРАЙС_ЛИСТ и если оба значения равны - заменяет на 0. 0 значит = уточняйте цену | AA21: БД_МОЙ СКЛАД СТОЛБЕЦ D | AB21: БД_МОЙ СКЛАД СТОЛБЕЦ D | AD21: БД_МОЙ СКЛАД СТОЛБЕЦ D | AE21: ЦЕНА | AG21: pcs | AJ21: дн | AL21: нет
B22: УСЛУГА | C22: БД_МОЙ СКЛАД СТОЛБЕЦ E | E22: Прописывается руками на странице БД_МОЙ СКЛАД | AA22: БД_МОЙ СКЛАД СТОЛБЕЦ E | AB22: БД_МОЙ СКЛАД СТОЛБЕЦ E | AD22: БД_МОЙ СКЛАД СТОЛБЕЦ E | AE22: УСЛУГА | AG22: pcs | AJ22: дн | AL22: нет
B23: ВРЕМЯ | C23: БД_МОЙ СКЛАД СТОЛБЕЦ F | E23: Прописывается руками на странице БД_МОЙ СКЛАД | AA23: БД_МОЙ СКЛАД СТОЛБЕЦ F | AB23: БД_МОЙ СКЛАД СТОЛБЕЦ F | AD23: БД_МОЙ СКЛАД СТОЛБЕЦ F | AE23: ВРЕМЯ | AG23: pcs | AJ23: дн | AL23: нет
B24: ЦЕНА ОТ | C24: БД_МОЙ СКЛАД СТОЛБЕЦ G | E24: Прописывается руками на странице БД_МОЙ СКЛАД | AA24: БД_МОЙ СКЛАД СТОЛБЕЦ G | AB24: БД_МОЙ СКЛАД СТОЛБЕЦ G | AD24: БД_МОЙ СКЛАД СТОЛБЕЦ G | AE24: ЦЕНА ОТ | AG24: pcs | AJ24: дн | AL24: нет
B25: ГАРАНТИЯ | C25: БД_МОЙ СКЛАД СТОЛБЕЦ H | E25: Прописывается руками на странице БД_МОЙ СКЛАД | AA25: БД_МОЙ СКЛАД СТОЛБЕЦ H | AB25: БД_МОЙ СКЛАД СТОЛБЕЦ H | AD25: БД_МОЙ СКЛАД СТОЛБЕЦ H | AE25: ГАРАНТИЯ | AG25: pcs | AJ25: дн | AL25: нет
B26: ОПИСАНИЕ | C26: БД_МОЙ СКЛАД СТОЛБЕЦ J | E26: Прописывается руками на странице БД_МОЙ СКЛАД | AA26: БД_МОЙ СКЛАД СТОЛБЕЦ J | AB26: БД_МОЙ СКЛАД СТОЛБЕЦ J | AD26: БД_МОЙ СКЛАД СТОЛБЕЦ J | AE26: ОПИСАНИЕ | AG26: pcs | AJ26: дн | AL26: нет
AG27: pcs | AJ27: дн | AL27: нет
AG28: pcs | AJ28: дн | AL28: нет
AG29: pcs | AJ29: дн | AL29: нет
AG30: pcs | AJ30: дн | AL30: нет
AG31: pcs | AJ31: дн | AL31: нет
AG32: pcs | AJ32: дн | AL32: нет
AG33: pcs | AJ33: дн | AL33: нет
AG34: pcs | AJ34: дн | AL34: нет
AG35: pcs | AJ35: дн | AL35: нет
AG36: pcs | AJ36: дн | AL36: нет
AG37: pcs | AJ37: дн | AL37: нет
AG38: pcs | AJ38: дн | AL38: нет
... AG1014: pcs | AJ1014: дн | AL1014: нет

Sheet НАИМЕНОВАНИЯ
